Workbook

Sheet Portuguese
B1: titulo | C1: ingredientes | D1: preparo | E1: url
A2: 0 | B2: Bolo de cenoura | C2: 1/2 xícara (chá) de óleo 3 cenouras médias raladas 4 ovos 2 xícaras (chá) de açúcar 2 e 1/2 xícaras (chá) de farinha de trigo 1 colher (sopa) de fermento em pó 1 colher (sopa) de manteiga 3 colheres (sopa) de chocolate em pó 1 xícara (chá) de açúcar 1 xícara (chá) de leite | D2: Em um liquidificador, adicione a cenoura, os ovos e o óleo, depois misture. Acrescente o açúcar e bata novamente por 5 minutos. Em uma tigela ou na batedeira, adicione a farinha de trigo e depoismisture novamente. Acrescente o fermento e misture lentamente com uma colher. Asse em um forno preaquecido a 180° C por aproximadamente 40 minutos. Despeje em uma tigela a manteiga, o chocolate em pó, o açúcar e o leite, depois misture. Leve a mistura ao fogo e continue misturando até obter uma consistência cremosa, depois despeje acalda por cima do bolo. | E2: https://www.tudogostoso.com.br/receita/23-bolo-de-cenoura.html
A3: 1 | B3: Bolo gelado | C3: 4 ovos 2 xícaras (chá) de açúcar 3 xícaras (chá) de farinha de trigo 1 copo (americano) de suco de laranja 1 colher (sopa) de fermento em pó 1 garrafa pequena de leite de coco 1 garrafa de leite (utilize a mesma garrafa do leite de coco como medida) 1 lata de leite condensado 1 pacote de coco ralado sem açúcar | D3: Em uma batedeira, bata as claras em neve acrescentando o açúcar aos poucos e bata por 3 minutos. Adicione as gemas, o trigo, o suco e continue batendo até formar uma massa homogênea. Por último, adicione o fermento e bata por mais 40 segundos na menor velocidade da batedeira. Despeje a massa em uma forma média e untada. Asse em forno preaquecido em temperatura média de 180 °C por 40 minutos ou até dourar. Em uma tigela, misture o leite de coco, o leite, o leite condensado e reserve. Após 40 minutos, retire o bolo do forno e fure toda a sua superfície com um garfo para facilitar a penetração da cobertura. Com o bolo ainda quente, despeje a cobertura sobre ele e salpique por cima o coco ralado. Leve a geladeira por 3 horas, depois corte o bolo em quadrados do tamanho que preferir e embrulhe com papel alumínio. Conserve na geladeira. | E3: https://www.tudogostoso.com.br/receita/2313-bolo-gelado.html
A4: 2 | B4: Torta de liquidificador | C4: 1 ovo 6 colheres (sopa) de farinha de trigo 5 colheres (sopa) de queijo ralado 1 pitada de orégano 1 colher (sobremesa) de fermento em pó 1/2 cebola 1 xícara (chá) de leite 1/2 xícara (chá) de óleo 1 pitada de sal | D4: Bata todos os ingredientes no liquidificador até que a massa esteja firme e encorpada. Para uma massa mais consistente, acrescente mais uma porção de farinha de trigo. Unte uma forma com óleo e despeje metade da massa até cobrir todo o fundo. Em seguida, acrescente um recheio de sua escolha e cubra com o restante da massa. Asse em forno médio (180° C), preaquecido, por 30 minutos. | E4: https://www.tudogostoso.com.br/receita/1362-torta-de-liquidificador.html
A5: 3 | B5: Fricassê de frango | C5: 1 lata de creme de leite 1 lata de milho verde 1 copo de requeijão cremoso 100 g de azeitona sem caroço 2 peitos de frango desfiados 200 g de mussarela fatiada 100 g de batata palha 1 xícara de água 1 pitada de sal | D5: Bata no liquidificador o milho, o requeijão, o creme de leite e a água. Refogue o creme do liquidificador com o frango desfiado, as azeitonas e o sal até ficar com uma textura espessa. Coloque o refogado numa assadeira, cubra com mussarela e espalhe a batata palha por cima. Leve ao forno até borbulhar. Sirvacom arroz branco. | E5: https://www.tudogostoso.com.br/receita/10254-fricasse-de-frango.html
A6: 4 | B6: Bolo de chocolate molhadinho | C6: 2 xícaras de farinha de trigo 2 xícaras de açúcar 1 xícara de leite 6 colheres (sopa) de chocolate em pó 1 colher (sopa) de fermento em pó 6 ovos Cobertura 2 colheres (sopa) de manteiga 2 xícaras de leite 1 xícara de chocolate em pó | D6: Em uma batedeira, bata as claras em neve. Acrescente as gemas, o açúcar e bata novamente. Adicione a farinha, o chocolate em pó, o fermento, o leite e bata por mais alguns minutos. Despeje a massa em uma forma untada e leve para assar em forno médio (180° C), preaquecido, por 40 minutos. Em uma panela, leve a fogo médio o chocolate em pó, a manteiga e o leite, deixe até ferver. Despeje quente sobre o bolo já assado. | E6: https://www.tudogostoso.com.br/receita/951-bolo-de-chocolate-molhadinho.html
A7: 5 | B7: Panqueca de carne moída | C7: 1 e 1/2 xícara (chá) de farinha de trigo 1 xícara (chá) de leite 2 ovos 4 colheres (sopa) de óleo sal a gosto 300 g de carne moída 2 colheres (sopa) de cebola picada ou ralada 1/2 tomate cortado em cubos 1/2 lata de extrato de tomate 1 caixa de creme de leite sal a gosto 400 g de muçarela fatiado queijo ralado a gosto | D7: Bata no liquidificador os ovos, o leite, o óleo, e acrescente a farinha de trigo aos poucos. Após acrescentar toda a farinha de trigo, adicione sal a gosto. Misture a massa até obter uma consistência cremosa. Com um papel-toalha, espalhe óleo por toda a frigideira e despeje uma concha de massa. Faça movimentos circulares para que a massa se espalhepor toda a frigideira. Espere até a massa soltar do fundo e vire a massa para fritar do outro lado. Em uma panela, doure a cebola com o óleo e acrescente a carne. Deixe cozinhar até que saia água da carne, diminua o fogo e tampe. Acrescente o tomate picado e tampe novamente. Deixe cozinhar por mais 3 minutos e misture. Acrescenteo extrato de tomatee temperos a gosto. Deixe cozinhar por mais 10 minutos. Quando o molho engrossar, desligue o fogo. Deixe esfriar o molho, acrescente o creme de leite e misture bem. Quando estiver bem homogêneo, leve novamente ao fogo e deixe cozinhar em fogo baixo por mais 5 minutos. Recheie a panqueca com uma fatia de mussarela, uma porção de carne e enrole. Faça esse processo com todas as panquecas. Despeje um pouco de caldo no fundo de um refratário,para untar. Disponha as panquecas já prontas no refratário e despeje sobre elas o restante do molho. Polvilhe queijo ralado sobre as panquecas. Leve ao forno para gratinar, em fogo médio, por 20 minutos ou até que o queijo esteja derretido. | E7: https://www.tudogostoso.com.br/receita/760-panqueca-de-carne-moida.html
A8: 6 | B8: Pudim de leite condensado simples | C8: 1 lata de leite condensado 1 xícara de leite de vaca 4 ovos inteiros 1 xícara (chá) de açúcar 1/3 de xícara (chá) de água | D8: Em uma panela, misture a água e o açúcar até formar uma calda. Unte uma forma com a calda e reserve. Bata todos os ingredientes no liquidificador e despeje na forma caramelizada. Leve para assar em banho-maria por 40 minutos. Desenforme e sirva. | E8: https://www.tudogostoso.com.br/receita/3687-pudim-de-leite-condensado.html
A9: 7 | B9: Bolo simples | C9: 2 xícaras (chá) de açúcar 3 xícaras (chá) de farinha de trigo 4 colheres (sopa) de margarina 3 ovos 1 e 1/2 xícara (chá) de leite 1 colher (sopa) bem cheia de fermento em pó | D9: Bata as claras em nevee reserve. Misture as gemas, a margarina e o açúcaraté obter uma massa homogênea. Acrescente o leite e a farinha de trigo aos poucos, sem parar de bater. Por último, adicione as claras em neve e o fermento. Despeje a massa em uma forma grande de furo centraluntada e enfarinhada. Asse em forno médio 180 °C, preaquecido, por aproximadamente 40 minutos ou ao furar o bolo com um garfo, este saia limpo. | E9: https://www.tudogostoso.com.br/receita/29124-bolo-simples.html
A10: 8 | B10: Bolinho de chuva | C10: 2 ovos 2 colheres (sopa) de açúcar 1 xícara (chá) de leite 2 e 1/2 xícaras (chá) de farinha de trigo 1 colher (sopa) de fermento 3 colheres (sopa) de açúcar 1 colher (chá) de canela | D10: Em um recipiente, adicione os ovos, o açúcar, o leite, a farinha de trigo e o fermento, depois misture-os até obter uma massa lisa e homogênea. Com a ajuda de uma colher, pegue porções da mistura e despeje em uma panela com o óleo quente. Retire do fogo quando estiver no ponto, depois misture a canela com açúcar e salpique no bolinho de chuva já frito. | E10: https://www.tudogostoso.com.br/receita/4683-bolinho-de-chuva.html
A11: 9 | B11: Torta de frango | C11: 500 g de peito de frango sem pele 1/2 litro de caldo de galinha 4 colheres (sopa) de óleo 1 dente de alho amassado 1 cebola picada 3 tomates sem pele e sem sementes 1 xícara (chá) de ervilhas sal a gosto pimenta-do-reino a gosto 250 ml de leite 3/4 de xícara (chá) de óleo 2 ovos 1 e 1/2 xícara (chá) de farinha de trigo sal a gosto 1 colher (sopa) de fermento em pó queijo ralado a gosto | D11: Cozinhe o peito de frango no caldo até ficar macio. Separe 1 xícara (chá) de caldo do cozimento e reserve. Refogue os demais ingredientes e acrescente as ervilhas por último. Desfie o frango, misture ao caldo e deixe cozinhar até secar. Bata o leite, o óleo e os ovos no liquidificador em velocidade baixa. Acrescente aos poucos a farinha, o sal e o fermento. Despeje metade da massa em uma forma untada e adicione o recheio sobre ela. Cubra com o restante de massa e o queijo ralado. Leve ao forno preaquecido (180° C) até dourar. | E11: https://www.tudogostoso.com.br/receita/1282-torta-de-frango.html
A12: 10 | B12: Danoninho caseiro | C12: 1 lata de leite condensado 2 caixas de creme de leite 200 g de iogurte natural 1 pacote de suco em pó sabor morango | D12: Em um liquidificador, bata todos os ingrediente até obter uma consistência cremosa. Dispense a mistura em um recipiente e leve à geladeira até que esteja firme. | E12: https://www.tudogostoso.com.br/receita/19728-danoninho-caseiro.html
A13: 11 | B13: Brigadeiro | C13: 1 caixa de leite condensado 1 colher (sopa) de margarina sem sal 7 colheres (sopa) de achocolatado ou 4 colheres (sopa) de chocolate em pó chocolate granulado | D13: Em uma panela funda, acrescente o leite condensado, a margarina e o chocolate em pó. Cozinhe em fogo médio e mexa até que o brigadeiro comece a desgrudar da panela. Deixe esfriar efaça pequenas bolascom a mão passando a massa no chocolate granulado. | E13: https://www.tudogostoso.com.br/receita/114-brigadeiro.html
... A136: 134 | B136: Mousse de chocolate | C136: 1 lata de leite condensado 1 colher (chá) de manteiga ou margarina 1 lata de creme de leite gelado 3 claras em neve 4 colheres de achocolatado em pó | D136: Leve ao fogo o leite condensado, a manteiga e o achocolatado, mexendo sem parar até que a mistura solte do fundo da panela. Reserve e deixa esfriar. Misture o creme de leite e as claras em neve até obter uma mistura homogênea. Despeje a massa em um refratário e leve ao congelador por aproximadamente 50 minutos. Sirva bem gelado. | E136: https://www.tudogostoso.com.br/receita/1117-mousse-de-chocolate.html
A139: Top 50 | E139: Top 100
B140: Ingridient | C140: Quantity | F140: Ingridient | G140: Quantity
A141: 8 | B141: leite | C141: 41 | E141: 8 | F141: leite | G141: 65
A142: 3 | B142: açúcar | C142: 37 | E142: 3 | F142: açúcar | G142: 62
A143: 2 | B143: ovo | C143: 36 | E143: 2 | F143: ovo | G143: 62
A144: 4 | B144: farinha de trigo | C144: 35 | E144: 4 | F144: farinha de trigo | G144: 58
A145: 5 | B145: fermento | C145: 27 | E145: 5 | F145: fermento | G145: 40
A146: 0 | B146: óleo | C146: 24 | E146: 16 | F146: sal | G146: 40
A147: 7 | B147: chocolate | C147: 21 | E147: 0 | F147: óleo | G147: 36
A148: 16 | B148: sal | C148: 20 | E148: 7 | F148: chocolate | G148: 34
A149: 17 | B149: creme de leite | C149: 16 | E149: 28 | F149: margarina | G149: 31
A150: 29 | B150: margarina | C150: 16 | E150: 19 | F150: queijo | G150: 28
A151: 13 | B151: queijo | C151: 15 | E151: 17 | F151: creme de leite | G151: 27
A152: 11 | B152: leite condensado | C152: 14 | E152: 11 | F152: leite condensado | G152: 25
... A200: 59 | B200: farinha de rosca | C200: 1 | E200: 48 | F200: palmito | G200: 1
E201: 49 | F201: caldo legume | G201: 1
E202: 57 | F202: flocão de milho | G202: 1
E203: 58 | F203: pinga | G203: 1
E204: 61 | F204: farinha de rosca | G204: 1
E205: 67 | F205: couve manteiga | G205: 1
E206: 68 | F206: porco | G206: 1
E207: 72 | F207: maçã | G207: 1
E208: 73 | F208: goiabada | G208: 1
E209: 74 | F209: erva-doce | G209: 1
E210: 77 | F210: amendoim | G210: 1
E211: 78 | F211: caldo de galinha | G211: 1
E212: 81 | F212: açúcar mascavo | G212: 1
... E222: 107 | F222: acelga | G222: 1

Sheet English
A1: Id | B1: =IFERROR(__xludf.DUMMYFUNCTION("GOOGLETRANSLATE(Portuguese!B1,""pt"",""en"")"),"title") -> title | C1: =IFERROR(__xludf.DUMMYFUNCTION("GOOGLETRANSLATE(Portuguese!C1,""pt"",""en"")"),"ingredients") -> ingredients | D1: =IFERROR(__xludf.DUMMYFUNCTION("GOOGLETRANSLATE(Portuguese!D1,""pt"",""en"")"),"preparation") -> preparation | E1: Link
A2: 0 | B2: =IFERROR(__xludf.DUMMYFUNCTION("GOOGLETRANSLATE(Portuguese!B2,""pt"",""en"")"),"Carrot cake") -> Carrot cake | C2: =IFERROR(__xludf.DUMMYFUNCTION("GOOGLETRANSLATE(Portuguese!C2,""pt"",""en"")"),"1/2 cup (tea) of oil 3 medium grated carrots 4 eggs 2 cups (tea) of sugar 2 and 1/2 cups (tea) of wheat flour 1 tablespoon of baking powder 1 tablespoon of butter 3 tablespoons of cocoa powder 1 cup (tea) of sugar 1 cup (tea) of milk") -> 1/2 cup (tea) of oil 3 medium grated carrots 4 eggs 2 cups (tea) of sugar 2 and 1/2 cups (tea) of wheat flour 1 tablespoon of baking powder 1 tablespoon of butter 3 tablespoons of cocoa powder 1 cup (tea) of sugar 1 cup (tea) of milk | D2: =IFERROR(__xludf.DUMMYFUNCTION("GOOGLETRANSLATE(Portuguese!D2,""pt"",""en"")"),"In a blender, add the carrot, eggs, and oil, then blend. Add the sugar and blend again for 5 minutes. In a bowl or stand mixer, add the flour and then mix again. Add the baking powder and mix slowly with a spoon. Bake in a preheated oven at 180°C (350°F) "&"for approximately 40 minutes. Pour the butter, cocoa powder, sugar, and milk into a bowl, then mix. Bring the mixture to a boil and continue stirring until it reaches a creamy consistency, then pour the syrup over the cake.") -> In a blender, add the carrot, eggs, and oil, then blend. Add the sugar and blend again for 5 minutes. In a bowl or stand mixer, add the flour and then mix again. Add the baking powder and mix slowly with a spoon. Bake in a preheated oven at 180°C (350°F) for approximately 40 minutes. Pour the butter, cocoa powder, sugar, and milk into a bowl, then mix. Bring the mixture to a boil and continue stirring until it reaches a creamy consistency, then pour the syrup over the cake. | E2: https://www.tudogostoso.com.br/receita/23-bolo-de-cenoura.html
A3: 1 | B3: =IFERROR(__xludf.DUMMYFUNCTION("GOOGLETRANSLATE(Portuguese!B3,""pt"",""en"")"),"Iced cake") -> Iced cake | C3: =IFERROR(__xludf.DUMMYFUNCTION("GOOGLETRANSLATE(Portuguese!C3,""pt"",""en"")"),"4 eggs 2 cups of sugar 3 cups of wheat flour 1 glass of orange juice 1 tablespoon of baking powder 1 small bottle of coconut milk 1 bottle of milk (use the same bottle as the coconut milk for measuring) 1 can of condensed milk 1 packet of unsweete"&"ned shredded coconut") -> 4 eggs 2 cups of sugar 3 cups of wheat flour 1 glass of orange juice 1 tablespoon of baking powder 1 small bottle of coconut milk 1 bottle of milk (use the same bottle as the coconut milk for measuring) 1 can of condensed milk 1 packet of unsweetened shredded coconut | D3: =IFERROR(__xludf.DUMMYFUNCTION("GOOGLETRANSLATE(Portuguese!D3,""pt"",""en"")"),"In a mixer, beat the egg whites until stiff peaks form, gradually adding the sugar, and beat for 3 minutes. Add the egg yolks, flour, and juice, and continue beating until a smooth batter forms. Finally, add the baking powder and beat for another 40 secon"&"ds on the lowest speed of the mixer. Pour the batter into a greased medium-sized baking pan. Bake in a preheated oven at 180°C (350°F) for 40 minutes, or until golden brown. In a bowl, mix the coconut milk, milk, and condensed milk, and set aside. After 4"&"0 minutes, remove the cake from the oven and prick the entire surface with a fork to facilitate the penetration of the topping. While the cake is still warm, pour the topping over it and sprinkle with grated coconut. Refrigerate for 3 hours, then cut the "&"cake into squares of your preferred size and wrap in aluminum foil. Keep refrigerated.") -> In a mixer, beat the egg whites until stiff peaks form, gradually adding the sugar, and beat for 3 minutes. Add the egg yolks, flour, and juice, and continue beating until a smooth batter forms. Finally, add the baking powder and beat for another 40 seconds on the lowest speed of the mixer. Pour the batter into a greased medium-sized baking pan. Bake in a preheated oven at 180°C (350°F) for 40 minutes, or until golden brown. In a bowl, mix the coconut milk, milk, and condensed milk, and set aside. After 40 minutes, remove the cake from the oven and prick the entire surface with a fork to facilitate the penetration of the topping. While the cake is still warm, pour the topping over it and sprinkle with grated coconut. Refrigerate for 3 hours, then cut the cake into squares of your preferred size and wrap in aluminum foil. Keep refrigerated. | E3: https://www.tudogostoso.com.br/receita/2313-bolo-gelado.html
A4: 2 | B4: =IFERROR(__xludf.DUMMYFUNCTION("GOOGLETRANSLATE(Portuguese!B4,""pt"",""en"")"),"Blender cake") -> Blender cake | C4: =IFERROR(__xludf.DUMMYFUNCTION("GOOGLETRANSLATE(Portuguese!C4,""pt"",""en"")"),"1 egg 6 tablespoons of wheat flour 5 tablespoons of grated cheese 1 pinch of oregano 1 dessert spoon of baking powder 1/2 onion 1 cup of milk 1/2 cup of oil 1 pinch of salt") -> 1 egg 6 tablespoons of wheat flour 5 tablespoons of grated cheese 1 pinch of oregano 1 dessert spoon of baking powder 1/2 onion 1 cup of milk 1/2 cup of oil 1 pinch of salt | D4: =IFERROR(__xludf.DUMMYFUNCTION("GOOGLETRANSLATE(Portuguese!D4,""pt"",""en"")"),"Blend all ingredients in a blender until the batter is firm and thick. For a thicker batter, add another portion of wheat flour. Grease a baking pan with oil and pour half of the batter to cover the entire bottom. Then, add a filling of your choice and co"&"ver with the remaining batter. Bake in a preheated medium oven (180°C) for 30 minutes.") -> Blend all ingredients in a blender until the batter is firm and thick. For a thicker batter, add another portion of wheat flour. Grease a baking pan with oil and pour half of the batter to cover the entire bottom. Then, add a filling of your choice and cover with the remaining batter. Bake in a preheated medium oven (180°C) for 30 minutes. | E4: https://www.tudogostoso.com.br/receita/1362-torta-de-liquidificador.html
A5: 3 | B5: =IFERROR(__xludf.DUMMYFUNCTION("GOOGLETRANSLATE(Portuguese!B5,""pt"",""en"")"),"Chicken Fricassee") -> Chicken Fricassee | C5: =IFERROR(__xludf.DUMMYFUNCTION("GOOGLETRANSLATE(Portuguese!C5,""pt"",""en"")"),"1 can of heavy cream 1 can of sweet corn 1 cup of creamy cream cheese 100g pitted olives 2 shredded chicken breasts 200g sliced ​​mozzarella cheese 100g potato sticks 1 cup of water 1 pinch of salt") -> 1 can of heavy cream 1 can of sweet corn 1 cup of creamy cream cheese 100g pitted olives 2 shredded chicken breasts 200g sliced ​​mozzarella cheese 100g potato sticks 1 cup of water 1 pinch of salt | D5: =IFERROR(__xludf.DUMMYFUNCTION("GOOGLETRANSLATE(Portuguese!D5,""pt"",""en"")"),"Blend the corn, cream cheese, heavy cream, and water in a blender. Sauté the blended mixture with the shredded chicken, olives, and salt until it thickens. Place the mixture in a baking dish, cover with mozzarella cheese, and sprinkle potato sticks on to"&"p. Bake until bubbly. Serve with white rice.") -> Blend the corn, cream cheese, heavy cream, and water in a blender. Sauté the blended mixture with the shredded chicken, olives, and salt until it thickens. Place the mixture in a baking dish, cover with mozzarella cheese, and sprinkle potato sticks on top. Bake until bubbly. Serve with white rice. | E5: https://www.tudogostoso.com.br/receita/10254-fricasse-de-frango.html
A6: 4 | B6: =IFERROR(__xludf.DUMMYFUNCTION("GOOGLETRANSLATE(Portuguese!B6,""pt"",""en"")"),"Moist chocolate cake") -> Moist chocolate cake | C6: =IFERROR(__xludf.DUMMYFUNCTION("GOOGLETRANSLATE(Portuguese!C6,""pt"",""en"")"),"2 cups all-purpose flour 2 cups sugar 1 cup milk 6 tablespoons cocoa powder 1 tablespoon baking powder 6 eggs Topping 2 tablespoons butter 2 cups milk 1 cup cocoa powder") -> 2 cups all-purpose flour 2 cups sugar 1 cup milk 6 tablespoons cocoa powder 1 tablespoon baking powder 6 eggs Topping 2 tablespoons butter 2 cups milk 1 cup cocoa powder | D6: =IFERROR(__xludf.DUMMYFUNCTION("GOOGLETRANSLATE(Portuguese!D6,""pt"",""en"")"),"In a mixer, beat the egg whites until stiff peaks form. Add the egg yolks and sugar and beat again. Add the flour, cocoa powder, baking powder, and milk and beat for a few more minutes. Pour the batter into a greased pan and bake in a preheated medium ove"&"n (180°C) for 40 minutes. In a saucepan, heat the cocoa powder, butter, and milk over medium heat until boiling. Pour the hot mixture over the baked cake.") -> In a mixer, beat the egg whites until stiff peaks form. Add the egg yolks and sugar and beat again. Add the flour, cocoa powder, baking powder, and milk and beat for a few more minutes. Pour the batter into a greased pan and bake in a preheated medium oven (180°C) for 40 minutes. In a saucepan, heat the cocoa powder, butter, and milk over medium heat until boiling. Pour the hot mixture over the baked cake. | E6: https://www.tudogostoso.com.br/receita/951-bolo-de-chocolate-molhadinho.html
A7: 5 | B7: =IFERROR(__xludf.DUMMYFUNCTION("GOOGLETRANSLATE(Portuguese!B7,""pt"",""en"")"),"Ground beef pancake") -> Ground beef pancake | C7: =IFERROR(__xludf.DUMMYFUNCTION("GOOGLETRANSLATE(Portuguese!C7,""pt"",""en"")"),"1 1/2 cups (tea) of wheat flour 1 cup (tea) of milk 2 eggs 4 tablespoons of oil Salt to taste 300g of ground beef 2 tablespoons of chopped or grated onion 1/2 tomato, diced 1/2 can of tomato paste 1 carton of heavy cream Salt to taste 400g of sliced ​​moz"&"zarella cheese Grated cheese to taste") -> 1 1/2 cups (tea) of wheat flour 1 cup (tea) of milk 2 eggs 4 tablespoons of oil Salt to taste 300g of ground beef 2 tablespoons of chopped or grated onion 1/2 tomato, diced 1/2 can of tomato paste 1 carton of heavy cream Salt to taste 400g of sliced ​​mozzarella cheese Grated cheese to taste | D7: =IFERROR(__xludf.DUMMYFUNCTION("GOOGLETRANSLATE(Portuguese!D7,""pt"",""en"")"),"In a blender, beat together the eggs, milk, and oil, gradually adding the wheat flour. After adding all the wheat flour, add salt to taste. Mix the batter until you obtain a creamy consistency. Using a paper towel, spread oil all over the skillet and pour"&" in a ladleful of batter. Make circular motions so that the batter spreads throughout the skillet. Wait until the batter releases from the bottom and flip it to fry on the other side. In a saucepan, sauté the onion in oil and add the meat. Cook until the "&"meat releases its juices, then reduce the heat and cover. Add the chopped tomato and cover again. Cook for another 3 minutes and stir. Add the tomato paste and seasonings to taste. Cook for another 10 minutes. When the sauce thickens, turn off the heat. L"&"et the sauce cool, add the cream, and mix well. Once well combined, return to the heat and cook over low heat for another 5 minutes. Fill the pancake with a slice of mozzarella, a portion of meat, and roll it up. Repeat this process with all the pancakes"&". Pour some broth into the bottom of a baking dish to grease it. Arrange the prepared pancakes in the baking dish and pour the remaining sauce over them. Sprinkle grated cheese over the pancakes. Bake in a preheated oven at medium heat for 20 minutes, or "&"until the cheese is melted and golden brown.") -> In a blender, beat together the eggs, milk, and oil, gradually adding the wheat flour. After adding all the wheat flour, add salt to taste. Mix the batter until you obtain a creamy consistency. Using a paper towel, spread oil all over the skillet and pour in a ladleful of batter. Make circular motions so that the batter spreads throughout the skillet. Wait until the batter releases from the bottom and flip it to fry on the other side. In a saucepan, sauté the onion in oil and add the meat. Cook until the meat releases its juices, then reduce the heat and cover. Add the chopped tomato and cover again. Cook for another 3 minutes and stir. Add the tomato paste and seasonings to taste. Cook for another 10 minutes. When the sauce thickens, turn off the heat. Let the sauce cool, add the cream, and mix well. Once well combined, return to the heat and cook over low heat for another 5 minutes. Fill the pancake with a slice of mozzarella, a portion of meat, and roll it up. Repeat this process with all the pancakes. Pour some broth into the bottom of a baking dish to grease it. Arrange the prepared pancakes in the baking dish and pour the remaining sauce over them. Sprinkle grated cheese over the pancakes. Bake in a preheated oven at medium heat for 20 minutes, or until the cheese is melted and golden brown. | E7: https://www.tudogostoso.com.br/receita/760-panqueca-de-carne-moida.html
A8: 6 | B8: =IFERROR(__xludf.DUMMYFUNCTION("GOOGLETRANSLATE(Portuguese!B8,""pt"",""en"")"),"Simple condensed milk pudding") -> Simple condensed milk pudding | C8: =IFERROR(__xludf.DUMMYFUNCTION("GOOGLETRANSLATE(Portuguese!C8,""pt"",""en"")"),"1 can of sweetened condensed milk 1 cup of cow's milk 4 whole eggs 1 cup of sugar 1/3 cup of water") -> 1 can of sweetened condensed milk 1 cup of cow's milk 4 whole eggs 1 cup of sugar 1/3 cup of water | D8: =IFERROR(__xludf.DUMMYFUNCTION("GOOGLETRANSLATE(Portuguese!D8,""pt"",""en"")"),"In a saucepan, mix the water and sugar until a syrup forms. Grease a mold with the syrup and set aside. Blend all the ingredients in a blender and pour into the caramelized mold. Bake in a water bath for 40 minutes. Unmold and serve.") -> In a saucepan, mix the water and sugar until a syrup forms. Grease a mold with the syrup and set aside. Blend all the ingredients in a blender and pour into the caramelized mold. Bake in a water bath for 40 minutes. Unmold and serve. | E8: https://www.tudogostoso.com.br/receita/3687-pudim-de-leite-condensado.html
A9: 7 | B9: =IFERROR(__xludf.DUMMYFUNCTION("GOOGLETRANSLATE(Portuguese!B9,""pt"",""en"")"),"Simple cake") -> Simple cake | C9: =IFERROR(__xludf.DUMMYFUNCTION("GOOGLETRANSLATE(Portuguese!C9,""pt"",""en"")"),"2 cups (tea) of sugar 3 cups (tea) of wheat flour 4 tablespoons of margarine 3 eggs 1 and 1/2 cups (tea) of milk 1 heaping tablespoon of baking powder") -> 2 cups (tea) of sugar 3 cups (tea) of wheat flour 4 tablespoons of margarine 3 eggs 1 and 1/2 cups (tea) of milk 1 heaping tablespoon of baking powder | D9: =IFERROR(__xludf.DUMMYFUNCTION("GOOGLETRANSLATE(Portuguese!D9,""pt"",""en"")"),"Beat the egg whites until stiff peaks form and set aside. Mix the egg yolks, margarine, and sugar until you obtain a homogeneous mixture. Gradually add the milk and wheat flour, continuing to beat. Finally, add the beaten egg whites and the baking powd"&"er. Pour the batter into a large, greased and floured bundt pan. Bake in a preheated medium oven (180°C) for approximately 40 minutes, or until a fork inserted into the center comes out clean.") -> Beat the egg whites until stiff peaks form and set aside. Mix the egg yolks, margarine, and sugar until you obtain a homogeneous mixture. Gradually add the milk and wheat flour, continuing to beat. Finally, add the beaten egg whites and the baking powder. Pour the batter into a large, greased and floured bundt pan. Bake in a preheated medium oven (180°C) for approximately 40 minutes, or until a fork inserted into the center comes out clean. | E9: https://www.tudogostoso.com.br/receita/29124-bolo-simples.html
A10: 8 | B10: =IFERROR(__xludf.DUMMYFUNCTION("GOOGLETRANSLATE(Portuguese!B10,""pt"",""en"")"),"Fritter") -> Fritter | C10: =IFERROR(__xludf.DUMMYFUNCTION("GOOGLETRANSLATE(Portuguese!C10,""pt"",""en"")"),"2 eggs 2 tablespoons of sugar 1 cup of milk 2 1/2 cups of wheat flour 1 tablespoon of baking powder 3 tablespoons of sugar 1 teaspoon of cinnamon") -> 2 eggs 2 tablespoons of sugar 1 cup of milk 2 1/2 cups of wheat flour 1 tablespoon of baking powder 3 tablespoons of sugar 1 teaspoon of cinnamon | D10: =IFERROR(__xludf.DUMMYFUNCTION("GOOGLETRANSLATE(Portuguese!D10,""pt"",""en"")"),"In a bowl, add the eggs, sugar, milk, wheat flour, and baking powder, then mix them until you obtain a smooth and homogeneous dough. With the help of a spoon, take portions of the mixture and drop them into a pan with hot oil. Remove from the heat when it"&"'s ready, then mix the cinnamon with sugar and sprinkle it on the already fried fritters.") -> In a bowl, add the eggs, sugar, milk, wheat flour, and baking powder, then mix them until you obtain a smooth and homogeneous dough. With the help of a spoon, take portions of the mixture and drop them into a pan with hot oil. Remove from the heat when it's ready, then mix the cinnamon with sugar and sprinkle it on the already fried fritters. | E10: https://www.tudogostoso.com.br/receita/4683-bolinho-de-chuva.html
A11: 9 | B11: =IFERROR(__xludf.DUMMYFUNCTION("GOOGLETRANSLATE(Portuguese!B11,""pt"",""en"")"),"Chicken pie") -> Chicken pie | C11: =IFERROR(__xludf.DUMMYFUNCTION("GOOGLETRANSLATE(Portuguese!C11,""pt"",""en"")"),"500g skinless chicken breast 1/2 liter chicken broth 4 tablespoons oil 1 clove garlic, crushed 1 onion, chopped 3 tomatoes, peeled and seeded 1 cup peas Salt to taste Black pepper to taste 250ml milk 3/4 cup oil 2 eggs 1 1/2 cups all-purpose flour Salt to"&" taste 1 tablespoon baking powder Grated cheese to taste") -> 500g skinless chicken breast 1/2 liter chicken broth 4 tablespoons oil 1 clove garlic, crushed 1 onion, chopped 3 tomatoes, peeled and seeded 1 cup peas Salt to taste Black pepper to taste 250ml milk 3/4 cup oil 2 eggs 1 1/2 cups all-purpose flour Salt to taste 1 tablespoon baking powder Grated cheese to taste | D11: =IFERROR(__xludf.DUMMYFUNCTION("GOOGLETRANSLATE(Portuguese!D11,""pt"",""en"")"),"Cook the chicken breast in the broth until tender. Set aside 1 cup of the cooking broth. Sauté the remaining ingredients and add the peas last. Shred the chicken, mix it with the broth, and cook until the liquid evaporates. Blend the milk, oil, and eggs i"&"n a blender on low speed. Gradually add the flour, salt, and baking powder. Pour half of the batter into a greased baking dish and add the filling on top. Cover with the remaining batter and grated cheese. Bake in a preheated oven (180°C) until golden bro"&"wn.") -> Cook the chicken breast in the broth until tender. Set aside 1 cup of the cooking broth. Sauté the remaining ingredients and add the peas last. Shred the chicken, mix it with the broth, and cook until the liquid evaporates. Blend the milk, oil, and eggs in a blender on low speed. Gradually add the flour, salt, and baking powder. Pour half of the batter into a greased baking dish and add the filling on top. Cover with the remaining batter and grated cheese. Bake in a preheated oven (180°C) until golden brown. | E11: https://www.tudogostoso.com.br/receita/1282-torta-de-frango.html
A12: 10 | B12: =IFERROR(__xludf.DUMMYFUNCTION("GOOGLETRANSLATE(Portuguese!B12,""pt"",""en"")"),"Homemade Danoninho") -> Homemade Danoninho | C12: =IFERROR(__xludf.DUMMYFUNCTION("GOOGLETRANSLATE(Portuguese!C12,""pt"",""en"")"),"1 can of sweetened condensed milk 2 cartons of heavy cream 200g of natural yogurt 1 packet of strawberry-flavored powdered juice") -> 1 can of sweetened condensed milk 2 cartons of heavy cream 200g of natural yogurt 1 packet of strawberry-flavored powdered juice | D12: =IFERROR(__xludf.DUMMYFUNCTION("GOOGLETRANSLATE(Portuguese!D12,""pt"",""en"")"),"In a blender, blend all ingredients until creamy. Pour the mixture into a container and refrigerate until firm.") -> In a blender, blend all ingredients until creamy. Pour the mixture into a container and refrigerate until firm. | E12: https://www.tudogostoso.com.br/receita/19728-danoninho-caseiro.html
A13: 11 | B13: =IFERROR(__xludf.DUMMYFUNCTION("GOOGLETRANSLATE(Portuguese!B13,""pt"",""en"")"),"Brigadier") -> Brigadier | C13: =IFERROR(__xludf.DUMMYFUNCTION("GOOGLETRANSLATE(Portuguese!C13,""pt"",""en"")"),"1 can of sweetened condensed milk 1 tablespoon of unsalted margarine 7 tablespoons of chocolate powder or 4 tablespoons of cocoa powder chocolate sprinkles") -> 1 can of sweetened condensed milk 1 tablespoon of unsalted margarine 7 tablespoons of chocolate powder or 4 tablespoons of cocoa powder chocolate sprinkles | D13: =IFERROR(__xludf.DUMMYFUNCTION("GOOGLETRANSLATE(Portuguese!D13,""pt"",""en"")"),"In a deep saucepan, add the condensed milk, margarine, and cocoa powder. Cook over medium heat and stir until the brigadeiro starts to come away from the sides of the pan. Let it cool and form small balls with your hands, rolling the dough in chocolate sp"&"rinkles.") -> In a deep saucepan, add the condensed milk, margarine, and cocoa powder. Cook over medium heat and stir until the brigadeiro starts to come away from the sides of the pan. Let it cool and form small balls with your hands, rolling the dough in chocolate sprinkles. | E13: https://www.tudogostoso.com.br/receita/114-brigadeiro.html
A14: 12 | B14: =IFERROR(__xludf.DUMMYFUNCTION("GOOGLETRANSLATE(Portuguese!B14,""pt"",""en"")"),"The best chocolate cake recipe") -> The best chocolate cake recipe | C14: =IFERROR(__xludf.DUMMYFUNCTION("GOOGLETRANSLATE(Portuguese!C14,""pt"",""en"")"),"4 eggs 4 tablespoons of cocoa powder 2 tablespoons of butter 3 cups of wheat flour 2 cups of sugar 2 tablespoons of baking powder 1 cup of milk 2 tablespoons of butter 7 tablespoons of cocoa powder 2 cans of heavy cream (with whey) 3 tablespoons o"&"f sugar") -> 4 eggs 4 tablespoons of cocoa powder 2 tablespoons of butter 3 cups of wheat flour 2 cups of sugar 2 tablespoons of baking powder 1 cup of milk 2 tablespoons of butter 7 tablespoons of cocoa powder 2 cans of heavy cream (with whey) 3 tablespoons of sugar | D14: =IFERROR(__xludf.DUMMYFUNCTION("GOOGLETRANSLATE(Portuguese!D14,""pt"",""en"")"),"In a blender, add the eggs, cocoa powder, butter, wheat flour, sugar, and milk, then blend for 5 minutes. Add the baking powder and gently mix with a spatula. In a greased pan, pour the batter and bake in a preheated medium oven (180 ºC) for about 40 minu"&"tes. Don't forget to use a tall pan for this recipe: since it uses two tablespoons of baking powder, it rises quite a bit! Another solution is to use only one tablespoon of baking powder and keep your recipe in a small pan. In a saucepan, heat the butter "&"and mix in the cocoa powder until smooth. Add the heavy cream and mix well until you obtain a creamy consistency. Turn off the heat and add the sugar.") -> In a blender, add the eggs, cocoa powder, butter, wheat flour, sugar, and milk, then blend for 5 minutes. Add the baking powder and gently mix with a spatula. In a greased pan, pour the batter and bake in a preheated medium oven (180 ºC) for about 40 minutes. Don't forget to use a tall pan for this recipe: since it uses two tablespoons of baking powder, it rises quite a bit! Another solution is to use only one tablespoon of baking powder and keep your recipe in a small pan. In a saucepan, heat the butter and mix in the cocoa powder until smooth. Add the heavy cream and mix well until you obtain a creamy consistency. Turn off the heat and add the sugar. | E14: https://www.tudogostoso.com.br/receita/62547-a-melhor-receita-de-bolo-de-chocolate.html
A15: 13 | B15: =IFERROR(__xludf.DUMMYFUNCTION("GOOGLETRANSLATE(Portuguese!B15,""pt"",""en"")"),"Pancakes (Grandma's recipe)") -> Pancakes (Grandma's recipe) | C15: =IFERROR(__xludf.DUMMYFUNCTION("GOOGLETRANSLATE(Portuguese!C15,""pt"",""en"")"),"1 cup of milk 1 egg 1 cup of wheat flour 1 tablespoon of oil 1 pinch of salt") -> 1 cup of milk 1 egg 1 cup of wheat flour 1 tablespoon of oil 1 pinch of salt | D15: =IFERROR(__xludf.DUMMYFUNCTION("GOOGLETRANSLATE(Portuguese!D15,""pt"",""en"")"),"Blend all ingredients in a blender until creamy. Grease a skillet with butter, wait for it to heat up, and pour in a ladleful of batter. Make circular motions so that the batter spreads across the entire skillet. Cook until the edges turn golden brown. Wa"&"it until the batter releases from the bottom, flip, and cook on the other side. Fill as desired, roll up, and serve.") -> Blend all ingredients in a blender until creamy. Grease a skillet with butter, wait for it to heat up, and pour in a ladleful of batter. Make circular motions so that the batter spreads across the entire skillet. Cook until the edges turn golden brown. Wait until the batter releases from the bottom, flip, and cook on the other side. Fill as desired, roll up, and serve. | E15: https://www.tudogostoso.com.br/receita/1316-panquecas-receita-da-vovo.html
A16: 14 | B16: =IFERROR(__xludf.DUMMYFUNCTION("GOOGLETRANSLATE(Portuguese!B16,""pt"",""en"")"),"Grandma Maria's cornmeal cake") -> Grandma Maria's cornmeal cake | C16: =IFERROR(__xludf.DUMMYFUNCTION("GOOGLETRANSLATE(Portuguese!C16,""pt"",""en"")"),"4 eggs 2 cups of sugar 2 cups of wheat flour 1 cup of cornmeal 3 tablespoons of margarine 1 cup of milk 4 teaspoons of baking powder") -> 4 eggs 2 cups of sugar 2 cups of wheat flour 1 cup of cornmeal 3 tablespoons of margarine 1 cup of milk 4 teaspoons of baking powder | D16: =IFERROR(__xludf.DUMMYFUNCTION("GOOGLETRANSLATE(Portuguese!D16,""pt"",""en"")"),"In a mixer, beat the egg whites until stiff peaks form and add the sugar. Add the egg yolks, margarine, milk, wheat flour, and cornmeal, and continue beating. Finally, add the baking powder and mix with a spoon or spatula. Pour the batter into a greased p"&"an and bake in a preheated medium oven (180°C) for approximately 30 minutes.") -> In a mixer, beat the egg whites until stiff peaks form and add the sugar. Add the egg yolks, margarine, milk, wheat flour, and cornmeal, and continue beating. Finally, add the baking powder and mix with a spoon or spatula. Pour the batter into a greased pan and bake in a preheated medium oven (180°C) for approximately 30 minutes. | E16: https://www.tudogostoso.com.br/receita/79-bolo-de-fuba-da-vo-maria.html
A17: 15 | B17: =IFERROR(__xludf.DUMMYFUNCTION("GOOGLETRANSLATE(Portuguese!B17,""pt"",""en"")"),"Creamy hot chocolate") -> Creamy hot chocolate | C17: =IFERROR(__xludf.DUMMYFUNCTION("GOOGLETRANSLATE(Portuguese!C17,""pt"",""en"")"),"2 cups of milk 1 tablespoon of cornstarch 3 tablespoons of cocoa powder 4 tablespoons of sugar 1 cinnamon stick 1 carton of heavy cream") -> 2 cups of milk 1 tablespoon of cornstarch 3 tablespoons of cocoa powder 4 tablespoons of sugar 1 cinnamon stick 1 carton of heavy cream | D17: =IFERROR(__xludf.DUMMYFUNCTION("GOOGLETRANSLATE(Portuguese!D17,""pt"",""en"")"),"In a blender, combine the milk, cornstarch, cocoa powder, and sugar. Pour the mixture into a saucepan with the cinnamon stick and cook over low heat, stirring constantly until it boils. Turn off the heat, add the heavy cream, and stir well until you have "&"a smooth mixture. Remove the cinnamon stick and serve hot.") -> In a blender, combine the milk, cornstarch, cocoa powder, and sugar. Pour the mixture into a saucepan with the cinnamon stick and cook over low heat, stirring constantly until it boils. Turn off the heat, add the heavy cream, and stir well until you have a smooth mixture. Remove the cinnamon stick and serve hot. | E17: https://www.tudogostoso.com.br/receita/130871-chocolate-quente-cremoso.html
A18: 16 | B18: =IFERROR(__xludf.DUMMYFUNCTION("GOOGLETRANSLATE(Portuguese!B18,""pt"",""en"")"),"Creamy cornmeal cake") -> Creamy cornmeal cake | C18: =IFERROR(__xludf.DUMMYFUNCTION("GOOGLETRANSLATE(Portuguese!C18,""pt"",""en"")"),"4 eggs 4 cups of milk 3 cups of sugar 2 tablespoons of wheat flour 1 1/2 cups of cornmeal 2 tablespoons of margarine 100g of grated cheese 1 tablespoon of baking powder") -> 4 eggs 4 cups of milk 3 cups of sugar 2 tablespoons of wheat flour 1 1/2 cups of cornmeal 2 tablespoons of margarine 100g of grated cheese 1 tablespoon of baking powder | D18: =IFERROR(__xludf.DUMMYFUNCTION("GOOGLETRANSLATE(Portuguese!D18,""pt"",""en"")"),"In a blender, mix all the ingredients until you obtain a creamy consistency. Pour the batter into a greased and floured baking pan. Bake in a preheated medium oven (180°C) for 40 minutes. Serve cold.") -> In a blender, mix all the ingredients until you obtain a creamy consistency. Pour the batter into a greased and floured baking pan. Bake in a preheated medium oven (180°C) for 40 minutes. Serve cold. | E18: https://www.tudogostoso.com.br/receita/3468-bolo-de-fuba-cremoso.html
A19: 17 | B19: =IFERROR(__xludf.DUMMYFUNCTION("GOOGLETRANSLATE(Portuguese!B19,""pt"",""en"")"),"Quick lemon mousse") -> Quick lemon mousse | C19: =IFERROR(__xludf.DUMMYFUNCTION("GOOGLETRANSLATE(Portuguese!C19,""pt"",""en"")"),"1 can of sweetened condensed milk 1 can of heavy cream 1/2 cup (American) of pure lemon juice Lemon biscuit") -> 1 can of sweetened condensed milk 1 can of heavy cream 1/2 cup (American) of pure lemon juice Lemon biscuit | D19: =IFERROR(__xludf.DUMMYFUNCTION("GOOGLETRANSLATE(Portuguese!D19,""pt"",""en"")"),"In a blender, beat the condensed milk and heavy cream for 3 minutes. Gradually add the lemon juice and continue beating. Pour the mousse into a baking dish and refrigerate. When ready to serve, crush the chocolate wafer and sprinkle it on top of the mouss"&"e to decorate.") -> In a blender, beat the condensed milk and heavy cream for 3 minutes. Gradually add the lemon juice and continue beating. Pour the mousse into a baking dish and refrigerate. When ready to serve, crush the chocolate wafer and sprinkle it on top of the mousse to decorate. | E19: https://www.tudogostoso.com.br/receita/155693-mousse-de-limao-rapido.html
A20: 18 | B20: =IFERROR(__xludf.DUMMYFUNCTION("GOOGLETRANSLATE(Portuguese!B20,""pt"",""en"")"),"Easy blender pizza") -> Easy blender pizza | C20: =IFERROR(__xludf.DUMMYFUNCTION("GOOGLETRANSLATE(Portuguese!C20,""pt"",""en"")"),"1 cup (tea) of milk 1 egg 1 teaspoon of salt 1 teaspoon of sugar 1 tablespoon of margarine 1 and 1/2 cups (tea) of wheat flour 1 dessert spoon of baking powder 1/2 can of tomato sauce 250 g of coarsely grated mozzarella cheese 2 sliced ​​tomatoes chopped "&"olives oregano to taste") -> 1 cup (tea) of milk 1 egg 1 teaspoon of salt 1 teaspoon of sugar 1 tablespoon of margarine 1 and 1/2 cups (tea) of wheat flour 1 dessert spoon of baking powder 1/2 can of tomato sauce 250 g of coarsely grated mozzarella cheese 2 sliced ​​tomatoes chopped olives oregano to taste | D20: =IFERROR(__xludf.DUMMYFUNCTION("GOOGLETRANSLATE(Portuguese!D20,""pt"",""en"")"),"In a blender, beat together the milk, egg, salt, sugar, margarine, wheat flour, and baking powder until everything is well combined. Pour the batter into a pizza pan greased with margarine and bake in a preheated oven for 20 minutes. Remove from the oven "&"and pour over the tomato sauce. Cover the dough with grated mozzarella, tomato, and oregano to taste. Bake again until the mozzarella melts.") -> In a blender, beat together the milk, egg, salt, sugar, margarine, wheat flour, and baking powder until everything is well combined. Pour the batter into a pizza pan greased with margarine and bake in a preheated oven for 20 minutes. Remove from the oven and pour over the tomato sauce. Cover the dough with grated mozzarella, tomato, and oregano to taste. Bake again until the mozzarella melts. | E20: https://www.tudogostoso.com.br/receita/93498-pizza-de-liquidificador-facil.html
A21: 19 | B21: =IFERROR(__xludf.DUMMYFUNCTION("GOOGLETRANSLATE(Portuguese!B21,""pt"",""en"")"),"Frozen coconut and chocolate dessert") -> Frozen coconut and chocolate dessert | C21: =IFERROR(__xludf.DUMMYFUNCTION("GOOGLETRANSLATE(Portuguese!C21,""pt"",""en"")"),"1 can of sweetened condensed milk 800 ml of milk 200 g of grated coconut 1 and 1/2 tablespoons of cornstarch 1 pinch of salt 1 can of heavy cream 12 tablespoons of chocolate powder") -> 1 can of sweetened condensed milk 800 ml of milk 200 g of grated coconut 1 and 1/2 tablespoons of cornstarch 1 pinch of salt 1 can of heavy cream 12 tablespoons of chocolate powder | D21: =IFERROR(__xludf.DUMMYFUNCTION("GOOGLETRANSLATE(Portuguese!D21,""pt"",""en"")"),"In a saucepan, mix all ingredients and cook over low heat until a smooth cream forms. Pour the cream into a serving dish or individual portions and set aside. In a bowl, mix the heavy cream and chocolate powder well without heating. Pour the mixture over "&"the white cream and refrigerate. Serve chilled.") -> In a saucepan, mix all ingredients and cook over low heat until a smooth cream forms. Pour the cream into a serving dish or individual portions and set aside. In a bowl, mix the heavy cream and chocolate powder well without heating. Pour the mixture over the white cream and refrigerate. Serve chilled. | E21: https://www.tudogostoso.com.br/receita/140770-doce-gelado-de-coco-com-chocolate.html
A22: 20 | B22: =IFERROR(__xludf.DUMMYFUNCTION("GOOGLETRANSLATE(Portuguese!B22,""pt"",""en"")"),"Homemade bread") -> Homemade bread | C22: =IFERROR(__xludf.DUMMYFUNCTION("GOOGLETRANSLATE(Portuguese!C22,""pt"",""en"")"),"2 1/2 cups of warm water 2 tablespoons of sugar 1 tablespoon of salt 1 egg 1 cup of oil 1 kg of wheat flour 50 g of baker's yeast") -> 2 1/2 cups of warm water 2 tablespoons of sugar 1 tablespoon of salt 1 egg 1 cup of oil 1 kg of wheat flour 50 g of baker's yeast | D22: =IFERROR(__xludf.DUMMYFUNCTION("GOOGLETRANSLATE(Portuguese!D22,""pt"",""en"")"),"Mix the yeast and warm water, set aside. In a blender, beat the sugar, oil, salt, egg, and water with the yeast for a few minutes. Pour the mixture into a bowl and gradually add the wheat flour, mixing with your hands. Add wheat flour until the dough no l"&"onger sticks to your hands and let it rise for 1 hour. Divide the dough into portions and shape the loaves. Let rise again for 40 minutes. Bake for 30 minutes.") -> Mix the yeast and warm water, set aside. In a blender, beat the sugar, oil, salt, egg, and water with the yeast for a few minutes. Pour the mixture into a bowl and gradually add the wheat flour, mixing with your hands. Add wheat flour until the dough no longer sticks to your hands and let it rise for 1 hour. Divide the dough into portions and shape the loaves. Let rise again for 40 minutes. Bake for 30 minutes. | E22: https://www.tudogostoso.com.br/receita/9589-pao-caseiro.html
A23: 21 | B23: =IFERROR(__xludf.DUMMYFUNCTION("GOOGLETRANSLATE(Portuguese!B23,""pt"",""en"")"),"Quick blender banana cake") -> Quick blender banana cake | C23: =IFERROR(__xludf.DUMMYFUNCTION("GOOGLETRANSLATE(Portuguese!C23,""pt"",""en"")"),"3 eggs 2 cups of sugar 1 cup of milk 1/2 cup of oil 2 cups of wheat flour 1 tablespoon of baking powder 7 bananas 3/4 cup of sugar 1/2 cup of hot water") -> 3 eggs 2 cups of sugar 1 cup of milk 1/2 cup of oil 2 cups of wheat flour 1 tablespoon of baking powder 7 bananas 3/4 cup of sugar 1/2 cup of hot water | D23: =IFERROR(__xludf.DUMMYFUNCTION("GOOGLETRANSLATE(Portuguese!D23,""pt"",""en"")"),"In a saucepan, add the sugar and stir until melted. Pour in the hot water and stir until the sugar dissolves. Let it thicken until it reaches the consistency of syrup and set aside. In a blender, beat the eggs, sugar, oil, and milk. Gradually add the whea"&"t flour and continue beating until you obtain a smooth and homogeneous batter. Finally, add the baking powder and blend at the lowest speed of the blender. Grease a medium baking pan with margarine and flour. Pour in the caramel and the bananas cut length"&"wise. Bake in a preheated medium oven at 180°C (350°F) for approximately 30 minutes.") -> In a saucepan, add the sugar and stir until melted. Pour in the hot water and stir until the sugar dissolves. Let it thicken until it reaches the consistency of syrup and set aside. In a blender, beat the eggs, sugar, oil, and milk. Gradually add the wheat flour and continue beating until you obtain a smooth and homogeneous batter. Finally, add the baking powder and blend at the lowest speed of the blender. Grease a medium baking pan with margarine and flour. Pour in the caramel and the bananas cut lengthwise. Bake in a preheated medium oven at 180°C (350°F) for approximately 30 minutes. | E23: https://www.tudogostoso.com.br/receita/119737-bolo-de-banana-rapido-de-liquidificador.html
A24: 22 | B24: =IFERROR(__xludf.DUMMYFUNCTION("GOOGLETRANSLATE(Portuguese!B24,""pt"",""en"")"),"Lemon mousse") -> Lemon mousse | C24: =IFERROR(__xludf.DUMMYFUNCTION("GOOGLETRANSLATE(Portuguese!C24,""pt"",""en"")"),"1 can of sweetened condensed milk 1 can of heavy cream 1/2 cup of lemon juice (this juice is pure, without water, just squeeze the lemon)") -> 1 can of sweetened condensed milk 1 can of heavy cream 1/2 cup of lemon juice (this juice is pure, without water, just squeeze the lemon) | D24: =IFERROR(__xludf.DUMMYFUNCTION("GOOGLETRANSLATE(Portuguese!D24,""pt"",""en"")"),"Place the heavy cream (with the whey) and the sweetened condensed milk in a blender. Blend briefly, then gradually add the lemon juice. It will become quite thick; refrigerate.") -> Place the heavy cream (with the whey) and the sweetened condensed milk in a blender. Blend briefly, then gradually add the lemon juice. It will become quite thick; refrigerate. | E24: https://www.tudogostoso.com.br/receita/1621-mousse-de-limao.html
A25: 23 | B25: =IFERROR(__xludf.DUMMYFUNCTION("GOOGLETRANSLATE(Portuguese!B25,""pt"",""en"")"),"Prestige cake") -> Prestige cake | C25: =IFERROR(__xludf.DUMMYFUNCTION("GOOGLETRANSLATE(Portuguese!C25,""pt"",""en"")"),"3 eggs 1/2 cup (tea) of oil 1 cup (tea) of milk 1 cup (tea) of sugar 1 cup (tea) of cocoa powder 2 cups (tea) of wheat flour 1 tablespoon of baking powder Grated coconut to taste 1 bottle of coconut milk 1 cup (tea) of milk 3 tablespoons of sugar 1 can o"&"f condensed milk 1 tablespoon of margarine 100 g of grated coconut 3 tablespoons of margarine 8 tablespoons of sugar 2 tablespoons of cocoa powder 2 cups (tea) of milk") -> 3 eggs 1/2 cup (tea) of oil 1 cup (tea) of milk 1 cup (tea) of sugar 1 cup (tea) of cocoa powder 2 cups (tea) of wheat flour 1 tablespoon of baking powder Grated coconut to taste 1 bottle of coconut milk 1 cup (tea) of milk 3 tablespoons of sugar 1 can of condensed milk 1 tablespoon of margarine 100 g of grated coconut 3 tablespoons of margarine 8 tablespoons of sugar 2 tablespoons of cocoa powder 2 cups (tea) of milk | D25: =IFERROR(__xludf.DUMMYFUNCTION("GOOGLETRANSLATE(Portuguese!D25,""pt"",""en"")"),"In a blender, beat the eggs, oil, and milk for 3 minutes and set aside. In a bowl, mix the sugar, flour, baking powder, chocolate, and shredded coconut to taste. Pour this mixture over the blender mixture and stir until the batter is consistent. Pour the "&"batter into a greased pan and bake in a preheated medium oven for 30 minutes, or until a fork inserted into the center comes out clean. Let cool, cut in half, and set aside. In a bowl, mix the coconut milk, milk, and sugar and pour over the halved cake to"&" moisten it. In a saucepan, cook the condensed milk, margarine, and shredded coconut over low heat until it pulls away from the bottom of the pan. Cook the margarine, sugar, cocoa powder, and milk over low heat until it thickens. Prick the bottom of the c"&"ake with a fork and pour some of the syrup over it. Spread the filling over the bottom half of the cake. Place the other half of the cake on top of the filling. Cover the cake with the chocolate frosting. Refrigerate for 45 minutes.") -> In a blender, beat the eggs, oil, and milk for 3 minutes and set aside. In a bowl, mix the sugar, flour, baking powder, chocolate, and shredded coconut to taste. Pour this mixture over the blender mixture and stir until the batter is consistent. Pour the batter into a greased pan and bake in a preheated medium oven for 30 minutes, or until a fork inserted into the center comes out clean. Let cool, cut in half, and set aside. In a bowl, mix the coconut milk, milk, and sugar and pour over the halved cake to moisten it. In a saucepan, cook the condensed milk, margarine, and shredded coconut over low heat until it pulls away from the bottom of the pan. Cook the margarine, sugar, cocoa powder, and milk over low heat until it thickens. Prick the bottom of the cake with a fork and pour some of the syrup over it. Spread the filling over the bottom half of the cake. Place the other half of the cake on top of the filling. Cover the cake with the chocolate frosting. Refrigerate for 45 minutes. | E25: https://www.tudogostoso.com.br/receita/51484-bolo-prestigio.html
A26: 24 | B26: =IFERROR(__xludf.DUMMYFUNCTION("GOOGLETRANSLATE(Portuguese!B26,""pt"",""en"")"),"Quick and easy Brigadeirão") -> Quick and easy Brigadeirão | C26: =IFERROR(__xludf.DUMMYFUNCTION("GOOGLETRANSLATE(Portuguese!C26,""pt"",""en"")"),"1 can of sweetened condensed milk 1 carton of heavy cream 8 tablespoons of chocolate powder 3 eggs 1 tablespoon of unsalted margarine chocolate sprinkles") -> 1 can of sweetened condensed milk 1 carton of heavy cream 8 tablespoons of chocolate powder 3 eggs 1 tablespoon of unsalted margarine chocolate sprinkles | D26: =IFERROR(__xludf.DUMMYFUNCTION("GOOGLETRANSLATE(Portuguese!D26,""pt"",""en"")"),"Blend all ingredients in a blender for 5 minutes until creamy. Pour the batter into a microwave-safe bundt pan greased with margarine. Microwave for 10 minutes. Let the batter cool for 15 minutes and refrigerate for 1 hour. Unmold and decorate with chocol"&"ate sprinkles.") -> Blend all ingredients in a blender for 5 minutes until creamy. Pour the batter into a microwave-safe bundt pan greased with margarine. Microwave for 10 minutes. Let the batter cool for 15 minutes and refrigerate for 1 hour. Unmold and decorate with chocolate sprinkles. | E26: https://www.tudogostoso.com.br/receita/73135-brigadeirao-rapido-e-facil.html
A27: 25 | B27: =IFERROR(__xludf.DUMMYFUNCTION("GOOGLETRANSLATE(Portuguese!B27,""pt"",""en"")"),"Chicken Stroganoff") -> Chicken Stroganoff | C27: =IFERROR(__xludf.DUMMYFUNCTION("GOOGLETRANSLATE(Portuguese!C27,""pt"",""en"")"),"3 chicken breasts, cubed 1 clove of garlic, minced Salt to taste Black pepper to taste 1 onion, chopped 2 tablespoons of mayonnaise 1 tablespoon of butter 1/2 cup of ketchup 1/3 cup of mustard 1 cup of mushrooms 1 cup of heavy cream Potato sticks to taste") -> 3 chicken breasts, cubed 1 clove of garlic, minced Salt to taste Black pepper to taste 1 onion, chopped 2 tablespoons of mayonnaise 1 tablespoon of butter 1/2 cup of ketchup 1/3 cup of mustard 1 cup of mushrooms 1 cup of heavy cream Potato sticks to taste | D27: =IFERROR(__xludf.DUMMYFUNCTION("GOOGLETRANSLATE(Portuguese!D27,""pt"",""en"")"),"In a saucepan, combine the chicken, garlic, mayonnaise, salt, and pepper. In a large skillet, melt the butter and sauté the onion until golden brown. Add the seasoned chicken and cook until browned. Add the mushrooms, ketchup, and mustard. Fold in the cre"&"am and remove from the heat before it boils. Serve with white rice and potato sticks.") -> In a saucepan, combine the chicken, garlic, mayonnaise, salt, and pepper. In a large skillet, melt the butter and sauté the onion until golden brown. Add the seasoned chicken and cook until browned. Add the mushrooms, ketchup, and mustard. Fold in the cream and remove from the heat before it boils. Serve with white rice and potato sticks. | E27: https://www.tudogostoso.com.br/receita/2462-strogonoff-de-frango.html
A28: 26 | B28: =IFERROR(__xludf.DUMMYFUNCTION("GOOGLETRANSLATE(Portuguese!B28,""pt"",""en"")"),"Passion fruit mousse") -> Passion fruit mousse | C28: =IFERROR(__xludf.DUMMYFUNCTION("GOOGLETRANSLATE(Portuguese!C28,""pt"",""en"")"),"1 can of sweetened condensed milk 1 can of passion fruit juice (measured using the sweetened condensed milk can) 1 can of heavy cream (without whey)") -> 1 can of sweetened condensed milk 1 can of passion fruit juice (measured using the sweetened condensed milk can) 1 can of heavy cream (without whey) | D28: =IFERROR(__xludf.DUMMYFUNCTION("GOOGLETRANSLATE(Portuguese!D28,""pt"",""en"")"),"In a blender, combine the heavy cream, sweetened condensed milk, and concentrated passion fruit juice. In a bowl, pour the mixture and refrigerate for at least 4 hours.") -> In a blender, combine the heavy cream, sweetened condensed milk, and concentrated passion fruit juice. In a bowl, pour the mixture and refrigerate for at least 4 hours. | E28: https://www.tudogostoso.com.br/receita/1599-mousse-de-maracuja.html
A29: 27 | B29: =IFERROR(__xludf.DUMMYFUNCTION("GOOGLETRANSLATE(Portuguese!B29,""pt"",""en"")"),"Creamy corn cake") -> Creamy corn cake | C29: =IFERROR(__xludf.DUMMYFUNCTION("GOOGLETRANSLATE(Portuguese!C29,""pt"",""en"")"),"1 can of sweet corn 1 can of oil (using the corn can as a measure) 1 can of sugar (using the corn can as a measure) 1 can of cornmeal (using the corn can as a measure) 4 eggs 2 tablespoons of wheat flour 2 tablespoons of shredded coconut 1 1/2 teaspoons "&"of baking powder") -> 1 can of sweet corn 1 can of oil (using the corn can as a measure) 1 can of sugar (using the corn can as a measure) 1 can of cornmeal (using the corn can as a measure) 4 eggs 2 tablespoons of wheat flour 2 tablespoons of shredded coconut 1 1/2 teaspoons of baking powder | D29: =IFERROR(__xludf.DUMMYFUNCTION("GOOGLETRANSLATE(Portuguese!D29,""pt"",""en"")"),"In a blender, add the corn, oil, sugar, cornmeal, eggs, and wheat flour, then blend until creamy. Next, add the shredded coconut and baking powder, and mix again. Pour the batter into a greased baking pan and bake in a preheated medium oven at 180°C (350°"&"F) for 40 minutes.") -> In a blender, add the corn, oil, sugar, cornmeal, eggs, and wheat flour, then blend until creamy. Next, add the shredded coconut and baking powder, and mix again. Pour the batter into a greased baking pan and bake in a preheated medium oven at 180°C (350°F) for 40 minutes. | E29: https://www.tudogostoso.com.br/receita/94018-bolo-de-milho-cremoso.html
A30: 28 | B30: =IFERROR(__xludf.DUMMYFUNCTION("GOOGLETRANSLATE(Portuguese!B30,""pt"",""en"")"),"Delicious and easy blender chicken pie") -> Delicious and easy blender chicken pie | C30: =IFERROR(__xludf.DUMMYFUNCTION("GOOGLETRANSLATE(Portuguese!C30,""pt"",""en"")"),"500 ml milk 250 ml soybean oil 3 cups wheat flour 1 teaspoon salt 4 eggs 2 teaspoons baking powder 25 g grated Parmesan cheese 1 pinch of oregano 1 large chicken breast, cooked for 30 minutes in a pressure cooker and shredded 1 can of chopped hearts of pa"&"lm 1 can of peas and corn 100 ml tomato sauce 1 chopped tomato 1 chopped onion olives oregano") -> 500 ml milk 250 ml soybean oil 3 cups wheat flour 1 teaspoon salt 4 eggs 2 teaspoons baking powder 25 g grated Parmesan cheese 1 pinch of oregano 1 large chicken breast, cooked for 30 minutes in a pressure cooker and shredded 1 can of chopped hearts of palm 1 can of peas and corn 100 ml tomato sauce 1 chopped tomato 1 chopped onion olives oregano | D30: =IFERROR(__xludf.DUMMYFUNCTION("GOOGLETRANSLATE(Portuguese!D30,""pt"",""en"")"),"Mix all the ingredients in a bowl until you obtain a firm consistency and set aside. Set aside the cheese. Blend the remaining dough ingredients in a blender and add the yeast last. Pour half of the dough into a large stainless steel or aluminum baking pa"&"n, greased with butter. Add the filling on top and cover with the remaining dough. Sprinkle with Parmesan cheese and bake in a preheated oven (220°C/425°F) for 40 minutes.") -> Mix all the ingredients in a bowl until you obtain a firm consistency and set aside. Set aside the cheese. Blend the remaining dough ingredients in a blender and add the yeast last. Pour half of the dough into a large stainless steel or aluminum baking pan, greased with butter. Add the filling on top and cover with the remaining dough. Sprinkle with Parmesan cheese and bake in a preheated oven (220°C/425°F) for 40 minutes. | E30: https://www.tudogostoso.com.br/receita/53203-torta-de-frango-de-liquidificador-deliciosa-e-facil.html
A31: 29 | B31: =IFERROR(__xludf.DUMMYFUNCTION("GOOGLETRANSLATE(Portuguese!B31,""pt"",""en"")"),"Creamed corn") -> Creamed corn | C31: =IFERROR(__xludf.DUMMYFUNCTION("GOOGLETRANSLATE(Portuguese!C31,""pt"",""en"")"),"1 can of corn 1 1/2 cups of milk 1 tablespoon of butter 1 medium grated onion 1 vegetable stock cube 1 can of cream 2 tablespoons of wheat flour") -> 1 can of corn 1 1/2 cups of milk 1 tablespoon of butter 1 medium grated onion 1 vegetable stock cube 1 can of cream 2 tablespoons of wheat flour | D31: =IFERROR(__xludf.DUMMYFUNCTION("GOOGLETRANSLATE(Portuguese!D31,""pt"",""en"")"),"In a blender, blend the corn and milk and set aside. In a saucepan, heat the butter, add the onion and sauté briefly. Add the flour and stir quickly. Let it brown and mix the blended corn and milk into the broth. Stir until completely dissolved and cook f"&"or about 10 minutes, until you obtain a creamy consistency. Add the cream, stir and turn off the heat.") -> In a blender, blend the corn and milk and set aside. In a saucepan, heat the butter, add the onion and sauté briefly. Add the flour and stir quickly. Let it brown and mix the blended corn and milk into the broth. Stir until completely dissolved and cook for about 10 minutes, until you obtain a creamy consistency. Add the cream, stir and turn off the heat. | E31: https://www.tudogostoso.com.br/receita/6662-creme-de-milho.html
A32: 30 | B32: =IFERROR(__xludf.DUMMYFUNCTION("GOOGLETRANSLATE(Portuguese!B32,""pt"",""en"")"),"American pancake") -> American pancake | C32: =IFERROR(__xludf.DUMMYFUNCTION("GOOGLETRANSLATE(Portuguese!C32,""pt"",""en"")"),"1 1/4 cups (tea) of wheat flour 1 tablespoon of sugar 3 teaspoons of baking powder 2 lightly beaten eggs 1 cup (tea) of milk 2 tablespoons of melted butter pinch of salt oil") -> 1 1/4 cups (tea) of wheat flour 1 tablespoon of sugar 3 teaspoons of baking powder 2 lightly beaten eggs 1 cup (tea) of milk 2 tablespoons of melted butter pinch of salt oil | D32: =IFERROR(__xludf.DUMMYFUNCTION("GOOGLETRANSLATE(Portuguese!D32,""pt"",""en"")"),"In one bowl, mix the flour, sugar, baking powder, and salt. In another bowl, mix the eggs, milk, and butter. Add the liquids to the dry ingredients, mixing gently without overmixing. The batter should not be too runny; it should drip slowly. Heat and grea"&"se a skillet with oil. Pour the batter into the center, about 1/4 cup per pancake. Flip the pancake to cook the other side, and it's ready!") -> In one bowl, mix the flour, sugar, baking powder, and salt. In another bowl, mix the eggs, milk, and butter. Add the liquids to the dry ingredients, mixing gently without overmixing. The batter should not be too runny; it should drip slowly. Heat and grease a skillet with oil. Pour the batter into the center, about 1/4 cup per pancake. Flip the pancake to cook the other side, and it's ready! | E32: https://www.tudogostoso.com.br/receita/13110-panqueca-americana.html
A33: 31 | B33: =IFERROR(__xludf.DUMMYFUNCTION("GOOGLETRANSLATE(Portuguese!B33,""pt"",""en"")"),"White sauce for pasta") -> White sauce for pasta | C33: =IFERROR(__xludf.DUMMYFUNCTION("GOOGLETRANSLATE(Portuguese!C33,""pt"",""en"")"),"1 small chopped onion 1 tablespoon of margarine 1 carton of heavy cream 1/2 liter of milk 1 tablespoon of cornstarch 1 cup of grated cheese Black pepper to taste 1 dessert spoon of salt") -> 1 small chopped onion 1 tablespoon of margarine 1 carton of heavy cream 1/2 liter of milk 1 tablespoon of cornstarch 1 cup of grated cheese Black pepper to taste 1 dessert spoon of salt | D33: =IFERROR(__xludf.DUMMYFUNCTION("GOOGLETRANSLATE(Portuguese!D33,""pt"",""en"")"),"In a saucepan, melt the margarine and add the onion, salt, and black pepper. When the onion is translucent, add the cream and mix. Dissolve the cornstarch in the milk and add it to the sauce. When the sauce has a firm consistency, turn off the heat and ad"&"d the cheese, stirring well so it doesn't stick. Serve with pasta or baked rice.") -> In a saucepan, melt the margarine and add the onion, salt, and black pepper. When the onion is translucent, add the cream and mix. Dissolve the cornstarch in the milk and add it to the sauce. When the sauce has a firm consistency, turn off the heat and add the cheese, stirring well so it doesn't stick. Serve with pasta or baked rice. | E33: https://www.tudogostoso.com.br/receita/8072-molho-branco-para-macarrao.html
A34: 32 | B34: =IFERROR(__xludf.DUMMYFUNCTION("GOOGLETRANSLATE(Portuguese!B34,""pt"",""en"")"),"Quick and fluffy homemade bread") -> Quick and fluffy homemade bread | C34: =IFERROR(__xludf.DUMMYFUNCTION("GOOGLETRANSLATE(Portuguese!C34,""pt"",""en"")"),"1 1/4 cups warm milk 1/2 cup oil 2 eggs 2 tablets of bread yeast 3 cups all-purpose flour 1 teaspoon salt 1/4 cup sugar") -> 1 1/4 cups warm milk 1/2 cup oil 2 eggs 2 tablets of bread yeast 3 cups all-purpose flour 1 teaspoon salt 1/4 cup sugar | D34: =IFERROR(__xludf.DUMMYFUNCTION("GOOGLETRANSLATE(Portuguese!D34,""pt"",""en"")"),"In a blender, combine the milk, oil, eggs, and yeast tablets; set aside. In a bowl, mix the flour, salt, and sugar, then pour over the blender mixture. Beat until bubbly and let rise for 20 minutes. Pour the batter into a greased and floured pan and bake "&"in a preheated medium-high oven (220°C) for 30 minutes.") -> In a blender, combine the milk, oil, eggs, and yeast tablets; set aside. In a bowl, mix the flour, salt, and sugar, then pour over the blender mixture. Beat until bubbly and let rise for 20 minutes. Pour the batter into a greased and floured pan and bake in a preheated medium-high oven (220°C) for 30 minutes. | E34: https://www.tudogostoso.com.br/receita/35829-pao-caseiro-rapido-e-fofo.html
A35: 33 | B35: =IFERROR(__xludf.DUMMYFUNCTION("GOOGLETRANSLATE(Portuguese!B35,""pt"",""en"")"),"Blender chocolate cake") -> Blender chocolate cake | C35: =IFERROR(__xludf.DUMMYFUNCTION("GOOGLETRANSLATE(Portuguese!C35,""pt"",""en"")"),"1 cup (tea) of warm milk 3 eggs 4 tablespoons of melted margarine 2 cups (tea) of sugar 1 cup (tea) of cocoa powder 2 cups (tea) of wheat flour 1 tablespoon of baking powder 1 cup (tea) of sugar 3 tablespoons of cornstarch 5 tablespoons of cocoa "&"powder 1 cup (tea) of water 3 tablespoons of margarine or butter 1 teaspoon of vanilla extract") -> 1 cup (tea) of warm milk 3 eggs 4 tablespoons of melted margarine 2 cups (tea) of sugar 1 cup (tea) of cocoa powder 2 cups (tea) of wheat flour 1 tablespoon of baking powder 1 cup (tea) of sugar 3 tablespoons of cornstarch 5 tablespoons of cocoa powder 1 cup (tea) of water 3 tablespoons of margarine or butter 1 teaspoon of vanilla extract | D35: =IFERROR(__xludf.DUMMYFUNCTION("GOOGLETRANSLATE(Portuguese!D35,""pt"",""en"")"),"Beat all the dough ingredients (except the yeast) well in a blender for approximately 2 to 3 minutes. Add the yeast and beat for another 15 seconds. Pour into a round pan, greased with butter and dusted with wheat flour. Bake for about 40 minutes in a pre"&"heated medium oven (180º C). Cook all the ingredients over low heat until thickened, to the consistency of brigadeiro (a Brazilian chocolate fudge). Cover the cake immediately.") -> Beat all the dough ingredients (except the yeast) well in a blender for approximately 2 to 3 minutes. Add the yeast and beat for another 15 seconds. Pour into a round pan, greased with butter and dusted with wheat flour. Bake for about 40 minutes in a preheated medium oven (180º C). Cook all the ingredients over low heat until thickened, to the consistency of brigadeiro (a Brazilian chocolate fudge). Cover the cake immediately. | E35: https://www.tudogostoso.com.br/receita/9614-bolo-de-chocolate-de-liquidificador.html
A36: 34 | B36: =IFERROR(__xludf.DUMMYFUNCTION("GOOGLETRANSLATE(Portuguese!B36,""pt"",""en"")"),"Savory blender pie") -> Savory blender pie | C36: =IFERROR(__xludf.DUMMYFUNCTION("GOOGLETRANSLATE(Portuguese!C36,""pt"",""en"")"),"3 eggs 13 tablespoons of wheat flour 1 1/2 cups of milk 3 tablespoons of cheese 1 tablespoon of baking powder 1/2 cup of oil Salt to taste 1 onion Garlic and salt to taste 1 bell pepper 2 peeled tomatoes Oregano 1 chili pepper French parsley Oil") -> 3 eggs 13 tablespoons of wheat flour 1 1/2 cups of milk 3 tablespoons of cheese 1 tablespoon of baking powder 1/2 cup of oil Salt to taste 1 onion Garlic and salt to taste 1 bell pepper 2 peeled tomatoes Oregano 1 chili pepper French parsley Oil | D36: =IFERROR(__xludf.DUMMYFUNCTION("GOOGLETRANSLATE(Portuguese!D36,""pt"",""en"")"),"In a pan with oil, sauté the onion and garlic until golden brown. Add the chosen filling and sauté. Add the remaining ingredients and cook for a few minutes. Blend all the dough ingredients in a blender and add the yeast last. Grease a rectangular baking "&"pan with margarine and dust with flour. Pour in the batter and carefully spread the filling. If desired, sprinkle cheese on top. Bake in a preheated oven at 180°C (350°F) for approximately 40 minutes.") -> In a pan with oil, sauté the onion and garlic until golden brown. Add the chosen filling and sauté. Add the remaining ingredients and cook for a few minutes. Blend all the dough ingredients in a blender and add the yeast last. Grease a rectangular baking pan with margarine and dust with flour. Pour in the batter and carefully spread the filling. If desired, sprinkle cheese on top. Bake in a preheated oven at 180°C (350°F) for approximately 40 minutes. | E36: https://www.tudogostoso.com.br/receita/1600-torta-salgada-de-liquidificador.html
A37: 35 | B37: =IFERROR(__xludf.DUMMYFUNCTION("GOOGLETRANSLATE(Portuguese!B37,""pt"",""en"")"),"Ground beef lasagna") -> Ground beef lasagna | C37: =IFERROR(__xludf.DUMMYFUNCTION("GOOGLETRANSLATE(Portuguese!C37,""pt"",""en"")"),"500g lasagna noodles 500g ground beef 2 cartons of heavy cream 3 tablespoons butter 3 tablespoons all-purpose flour 500g ham 500g mozzarella cheese Salt to taste 2 cups milk 1 grated onion 3 tablespoons oil 1 can of tomato sauce 3 cloves of crushed garlic"&" 1 package of grated cheese") -> 500g lasagna noodles 500g ground beef 2 cartons of heavy cream 3 tablespoons butter 3 tablespoons all-purpose flour 500g ham 500g mozzarella cheese Salt to taste 2 cups milk 1 grated onion 3 tablespoons oil 1 can of tomato sauce 3 cloves of crushed garlic 1 package of grated cheese | D37: =IFERROR(__xludf.DUMMYFUNCTION("GOOGLETRANSLATE(Portuguese!D37,""pt"",""en"")"),"Cook the pasta according to the manufacturer's instructions, pour it into a baking dish with ice water to prevent sticking, and set aside. Sauté the garlic, onion, ground beef, and tomato sauce; cook for 3 minutes and set aside. Melt the margarine, add th"&"e 3 tablespoons of flour, and stir. Pour in the milk gradually and continue stirring. Finally, add the cream, stir for 1 minute, and turn off the heat. Pour some of the Bolognese sauce into a baking dish, half of the pasta, half of the ham, half of the mo"&"zzarella, all of the white sauce, and the remaining pasta. Repeat the layers until you reach the edge of the dish. Finish with grated cheese and bake in a preheated oven (220°C/425°F) for about 20 minutes.") -> Cook the pasta according to the manufacturer's instructions, pour it into a baking dish with ice water to prevent sticking, and set aside. Sauté the garlic, onion, ground beef, and tomato sauce; cook for 3 minutes and set aside. Melt the margarine, add the 3 tablespoons of flour, and stir. Pour in the milk gradually and continue stirring. Finally, add the cream, stir for 1 minute, and turn off the heat. Pour some of the Bolognese sauce into a baking dish, half of the pasta, half of the ham, half of the mozzarella, all of the white sauce, and the remaining pasta. Repeat the layers until you reach the edge of the dish. Finish with grated cheese and bake in a preheated oven (220°C/425°F) for about 20 minutes. | E37: https://www.tudogostoso.com.br/receita/876-lasanha-de-carne-moida.html
A38: 36 | B38: =IFERROR(__xludf.DUMMYFUNCTION("GOOGLETRANSLATE(Portuguese!B38,""pt"",""en"")"),"Delicious chicken pot pie") -> Delicious chicken pot pie | C38: =IFERROR(__xludf.DUMMYFUNCTION("GOOGLETRANSLATE(Portuguese!C38,""pt"",""en"")"),"400g wheat flour 200g cold butter 1 whole egg 1 beaten egg yolk for the dough Salt to taste 6 tablespoons milk 1 egg yolk for brushing the dough 1kg boneless chicken breast 1 medium onion, finely chopped 2 cloves of garlic, chopped and crushed 1 tomato, c"&"hopped and peeled 1 tablespoon olive oil Chopped parsley 1 can of corn 1 can of tomato sauce 1 heaping tablespoon of wheat flour 3 chicken bouillon cubes Chopped olives") -> 400g wheat flour 200g cold butter 1 whole egg 1 beaten egg yolk for the dough Salt to taste 6 tablespoons milk 1 egg yolk for brushing the dough 1kg boneless chicken breast 1 medium onion, finely chopped 2 cloves of garlic, chopped and crushed 1 tomato, chopped and peeled 1 tablespoon olive oil Chopped parsley 1 can of corn 1 can of tomato sauce 1 heaping tablespoon of wheat flour 3 chicken bouillon cubes Chopped olives | D38: =IFERROR(__xludf.DUMMYFUNCTION("GOOGLETRANSLATE(Portuguese!D38,""pt"",""en"")"),"Cook the chicken breast, shred it, and set aside. In a pan, heat the olive oil, sauté the onion until golden brown. Add the garlic, sauté for a few more minutes, and then add the shredded chicken. Dissolve the chicken bouillon cubes in hot water and add t"&"o the mixture. Add the flour and stir vigorously until you obtain a creamy consistency. Pour in the corn, olives, parsley, and tomato and mix. In a bowl, mix the flour and butter until you obtain a crumbly mixture. Add the remaining ingredients and knead "&"well until you obtain a smooth dough. Wrap in plastic wrap and refrigerate for approximately 30 minutes. Use half of the dough to line the baking dish and the other half to cover the filling. Brush the pie with the egg yolk and bake in a preheated medium "&"oven (180°C) for approximately 40 minutes.") -> Cook the chicken breast, shred it, and set aside. In a pan, heat the olive oil, sauté the onion until golden brown. Add the garlic, sauté for a few more minutes, and then add the shredded chicken. Dissolve the chicken bouillon cubes in hot water and add to the mixture. Add the flour and stir vigorously until you obtain a creamy consistency. Pour in the corn, olives, parsley, and tomato and mix. In a bowl, mix the flour and butter until you obtain a crumbly mixture. Add the remaining ingredients and knead well until you obtain a smooth dough. Wrap in plastic wrap and refrigerate for approximately 30 minutes. Use half of the dough to line the baking dish and the other half to cover the filling. Brush the pie with the egg yolk and bake in a preheated medium oven (180°C) for approximately 40 minutes. | E38: https://www.tudogostoso.com.br/receita/8054-empadao-de-frango-delicioso.html
A39: 37 | B39: =IFERROR(__xludf.DUMMYFUNCTION("GOOGLETRANSLATE(Portuguese!B39,""pt"",""en"")"),"Canned corn cake made in a blender.") -> Canned corn cake made in a blender. | C39: =IFERROR(__xludf.DUMMYFUNCTION("GOOGLETRANSLATE(Portuguese!C39,""pt"",""en"")"),"1 can of corn (drained) 1 can of milk (using the corn can as a measure) 1 can of sugar (using the corn can as a measure) 1 can of cornmeal flakes 1/2 can of soybean oil 3 whole eggs 1 tablespoon of baking powder Margarine for greasing Wheat flour for grea"&"sing") -> 1 can of corn (drained) 1 can of milk (using the corn can as a measure) 1 can of sugar (using the corn can as a measure) 1 can of cornmeal flakes 1/2 can of soybean oil 3 whole eggs 1 tablespoon of baking powder Margarine for greasing Wheat flour for greasing | D39: =IFERROR(__xludf.DUMMYFUNCTION("GOOGLETRANSLATE(Portuguese!D39,""pt"",""en"")"),"Drain the corn and use the can itself for measurements. Grease and flour a bundt cake pan. Preheat the oven. Place the drained corn, milk, sugar, cornmeal, oil, and eggs in a blender and blend well until the corn is finely ground. If desired, add two tabl"&"espoons of shredded coconut. Add the baking powder and pulse the blender 3 times. Pour the batter into the pan and bake in a preheated oven at medium heat. Bake for approximately 40 minutes. Do the toothpick test and check for a medium golden color to kno"&"w that the cake is ready. Let it cool completely before unmolding.") -> Drain the corn and use the can itself for measurements. Grease and flour a bundt cake pan. Preheat the oven. Place the drained corn, milk, sugar, cornmeal, oil, and eggs in a blender and blend well until the corn is finely ground. If desired, add two tablespoons of shredded coconut. Add the baking powder and pulse the blender 3 times. Pour the batter into the pan and bake in a preheated oven at medium heat. Bake for approximately 40 minutes. Do the toothpick test and check for a medium golden color to know that the cake is ready. Let it cool completely before unmolding. | E39: https://www.tudogostoso.com.br/receita/143393-bolo-de-milho-de-lata-no-liquidificador.html
A40: 38 | B40: =IFERROR(__xludf.DUMMYFUNCTION("GOOGLETRANSLATE(Portuguese!B40,""pt"",""en"")"),"Easy passion fruit mousse") -> Easy passion fruit mousse | C40: =IFERROR(__xludf.DUMMYFUNCTION("GOOGLETRANSLATE(Portuguese!C40,""pt"",""en"")"),"2 boxes of passion fruit gelatin 2 cups of hot water 1/2 cup of passion fruit juice 2 cups of cow's milk 1 can of sweetened condensed milk 1 can of heavy cream (without whey)") -> 2 boxes of passion fruit gelatin 2 cups of hot water 1/2 cup of passion fruit juice 2 cups of cow's milk 1 can of sweetened condensed milk 1 can of heavy cream (without whey) | D40: =IFERROR(__xludf.DUMMYFUNCTION("GOOGLETRANSLATE(Portuguese!D40,""pt"",""en"")"),"Prepare the gelatin with hot water. Then simply blend all the ingredients in a blender and pour into a serving dish to chill.") -> Prepare the gelatin with hot water. Then simply blend all the ingredients in a blender and pour into a serving dish to chill. | E40: https://www.tudogostoso.com.br/receita/16-mousse-de-maracuja-facil.html
A41: 39 | B41: =IFERROR(__xludf.DUMMYFUNCTION("GOOGLETRANSLATE(Portuguese!B41,""pt"",""en"")"),"Super fluffy cornmeal cake") -> Super fluffy cornmeal cake | C41: =IFERROR(__xludf.DUMMYFUNCTION("GOOGLETRANSLATE(Portuguese!C41,""pt"",""en"")"),"2 eggs 2 cups of milk 2 cups of sugar 2 cups of cornmeal 2 cups of wheat flour 1 cup of oil 2 teaspoons of baking powder") -> 2 eggs 2 cups of milk 2 cups of sugar 2 cups of cornmeal 2 cups of wheat flour 1 cup of oil 2 teaspoons of baking powder | D41: =IFERROR(__xludf.DUMMYFUNCTION("GOOGLETRANSLATE(Portuguese!D41,""pt"",""en"")"),"In a blender, at high speed, beat the eggs, oil, milk, and sugar. Once smooth, gradually add the flour and cornmeal. The batter will start to thicken, so help it by stirring with a spoon. Once everything is well mixed, add the baking powder and mix well. "&"Grease a large bundt pan with oil and sugar (preferably granulated). Bake in a preheated oven until golden brown (about 40 minutes). Insert a toothpick or knife to check for doneness. When almost completely cool, unmold. It's soft, not a dry cornmeal cake"&", and it's wonderful!") -> In a blender, at high speed, beat the eggs, oil, milk, and sugar. Once smooth, gradually add the flour and cornmeal. The batter will start to thicken, so help it by stirring with a spoon. Once everything is well mixed, add the baking powder and mix well. Grease a large bundt pan with oil and sugar (preferably granulated). Bake in a preheated oven until golden brown (about 40 minutes). Insert a toothpick or knife to check for doneness. When almost completely cool, unmold. It's soft, not a dry cornmeal cake, and it's wonderful! | E41: https://www.tudogostoso.com.br/receita/144162-bolo-de-fuba-super-fofo.html
A42: 40 | B42: =IFERROR(__xludf.DUMMYFUNCTION("GOOGLETRANSLATE(Portuguese!B42,""pt"",""en"")"),"Pizza dough") -> Pizza dough | C42: =IFERROR(__xludf.DUMMYFUNCTION("GOOGLETRANSLATE(Portuguese!C42,""pt"",""en"")"),"1 kg of wheat flour 30 g of biological yeast 3 cups of warm water 3/4 cup of oil 1 teaspoon of salt 1 teaspoon of sugar 1 tablespoon of cachaça (Brazilian rum)") -> 1 kg of wheat flour 30 g of biological yeast 3 cups of warm water 3/4 cup of oil 1 teaspoon of salt 1 teaspoon of sugar 1 tablespoon of cachaça (Brazilian rum) | D42: =IFERROR(__xludf.DUMMYFUNCTION("GOOGLETRANSLATE(Portuguese!D42,""pt"",""en"")"),"Mix the yeast, salt, and sugar in a little warm water until the yeast is completely dissolved. Then, add half the measure of wheat flour, the oil, and stir until a paste-like consistency is formed. Add the remaining wheat flour, the cachaça, the warm wate"&"r, and mix well. Once the dough no longer sticks to your hands, let it rise for 30 minutes. Roll out the dough into discs, prick the dough with a fork, and brush with the sauce. Bake in a preheated medium oven (180°C) for 15 minutes.") -> Mix the yeast, salt, and sugar in a little warm water until the yeast is completely dissolved. Then, add half the measure of wheat flour, the oil, and stir until a paste-like consistency is formed. Add the remaining wheat flour, the cachaça, the warm water, and mix well. Once the dough no longer sticks to your hands, let it rise for 30 minutes. Roll out the dough into discs, prick the dough with a fork, and brush with the sauce. Bake in a preheated medium oven (180°C) for 15 minutes. | E42: https://www.tudogostoso.com.br/receita/324-massa-de-pizza.html
A43: 41 | B43: =IFERROR(__xludf.DUMMYFUNCTION("GOOGLETRANSLATE(Portuguese!B43,""pt"",""en"")"),"Fritter") -> Fritter | C43: =IFERROR(__xludf.DUMMYFUNCTION("GOOGLETRANSLATE(Portuguese!C43,""pt"",""en"")"),"2 eggs 1 cup of sugar 1 cup of milk 2 1/2 cups of wheat flour 1 tablespoon of baking powder 3 tablespoons of sugar for sprinkling 1 tablespoon of cinnamon for sprinkling 1 liter of oil for frying") -> 2 eggs 1 cup of sugar 1 cup of milk 2 1/2 cups of wheat flour 1 tablespoon of baking powder 3 tablespoons of sugar for sprinkling 1 tablespoon of cinnamon for sprinkling 1 liter of oil for frying | D43: =IFERROR(__xludf.DUMMYFUNCTION("GOOGLETRANSLATE(Portuguese!D43,""pt"",""en"")"),"Mix all the ingredients until you obtain a creamy and homogeneous dough. Heat a pan with plenty of oil so that the fritters can float. When the oil is very hot (180º C), using a spoon, start placing small amounts of dough and fry until they are golden bro"&"wn all over. Place the fritters on absorbent paper and then coat them in cinnamon sugar.") -> Mix all the ingredients until you obtain a creamy and homogeneous dough. Heat a pan with plenty of oil so that the fritters can float. When the oil is very hot (180º C), using a spoon, start placing small amounts of dough and fry until they are golden brown all over. Place the fritters on absorbent paper and then coat them in cinnamon sugar. | E43: https://www.tudogostoso.com.br/receita/76049-bolinho-de-chuva.html
A44: 42 | B44: =IFERROR(__xludf.DUMMYFUNCTION("GOOGLETRANSLATE(Portuguese!B44,""pt"",""en"")"),"Quick banana pie") -> Quick banana pie | C44: =IFERROR(__xludf.DUMMYFUNCTION("GOOGLETRANSLATE(Portuguese!C44,""pt"",""en"")"),"2 cups of wheat flour 2 cups of sugar 1 tablespoon of baking powder 2 beaten eggs 1 cup of milk 5 tablespoons of margarine 10 bananas, sliced ​​horizontally") -> 2 cups of wheat flour 2 cups of sugar 1 tablespoon of baking powder 2 beaten eggs 1 cup of milk 5 tablespoons of margarine 10 bananas, sliced ​​horizontally | D44: =IFERROR(__xludf.DUMMYFUNCTION("GOOGLETRANSLATE(Portuguese!D44,""pt"",""en"")"),"For the crumble topping, mix the flour, sugar, and yeast in a bowl and set aside. Melt the margarine, add the milk and eggs, and mix well. In a greased baking dish, place a layer of crumble topping and then a layer of bananas, and so on. Pour the liquid o"&"ver the top, without stirring. Bake in a warm oven until golden brown.") -> For the crumble topping, mix the flour, sugar, and yeast in a bowl and set aside. Melt the margarine, add the milk and eggs, and mix well. In a greased baking dish, place a layer of crumble topping and then a layer of bananas, and so on. Pour the liquid over the top, without stirring. Bake in a warm oven until golden brown. | E44: https://www.tudogostoso.com.br/receita/2211-torta-de-banana-rapida.html
A45: 43 | B45: =IFERROR(__xludf.DUMMYFUNCTION("GOOGLETRANSLATE(Portuguese!B45,""pt"",""en"")"),"Easy and delicious chicken croquette") -> Easy and delicious chicken croquette | C45: =IFERROR(__xludf.DUMMYFUNCTION("GOOGLETRANSLATE(Portuguese!C45,""pt"",""en"")"),"1 cup (tea) of water 2 cups (tea) of milk 2 bacon or rib bouillon cubes 1/2 cup (tea) of cooked and mashed potato 1 tablespoon of butter 2 and 1/2 cups (tea) of wheat flour margarine for greasing the pan breadcrumbs 2 beaten eggs oil for frying Filling 1 "&"and 1/2 kg of chicken 3 tablespoons of creamy cheese spread 2 tablespoons of olive oil 1 small onion 2 cloves of garlic seasoning to taste") -> 1 cup (tea) of water 2 cups (tea) of milk 2 bacon or rib bouillon cubes 1/2 cup (tea) of cooked and mashed potato 1 tablespoon of butter 2 and 1/2 cups (tea) of wheat flour margarine for greasing the pan breadcrumbs 2 beaten eggs oil for frying Filling 1 and 1/2 kg of chicken 3 tablespoons of creamy cheese spread 2 tablespoons of olive oil 1 small onion 2 cloves of garlic seasoning to taste | D45: =IFERROR(__xludf.DUMMYFUNCTION("GOOGLETRANSLATE(Portuguese!D45,""pt"",""en"")"),"In a saucepan, heat the olive oil, add the chopped garlic and onion. Sauté until softened, then add the shredded chicken and your preferred seasonings. Sauté everything for 5 minutes, remove from heat, add the cream cheese, mix, and set aside. In a large "&"saucepan, add the water, milk, bouillon cube, potato, and butter, and bring to a boil. Add the flour all at once, stirring until the dough pulls away from the bottom of the pan. Pour the dough onto a smooth, greased surface, knead well, and let cool. Open"&" the dough with your hands, fill it, and shape it into a coxinha (chicken croquette) shape. Dip the shaped dough in beaten egg and then in breadcrumbs. Fry in hot oil until golden brown and drain on absorbent paper.") -> In a saucepan, heat the olive oil, add the chopped garlic and onion. Sauté until softened, then add the shredded chicken and your preferred seasonings. Sauté everything for 5 minutes, remove from heat, add the cream cheese, mix, and set aside. In a large saucepan, add the water, milk, bouillon cube, potato, and butter, and bring to a boil. Add the flour all at once, stirring until the dough pulls away from the bottom of the pan. Pour the dough onto a smooth, greased surface, knead well, and let cool. Open the dough with your hands, fill it, and shape it into a coxinha (chicken croquette) shape. Dip the shaped dough in beaten egg and then in breadcrumbs. Fry in hot oil until golden brown and drain on absorbent paper. | E45: https://www.tudogostoso.com.br/receita/1363-coxinha-pratica-deliciosa.html
A46: 44 | B46: =IFERROR(__xludf.DUMMYFUNCTION("GOOGLETRANSLATE(Portuguese!B46,""pt"",""en"")"),"Bis Pavé") -> Bis Pavé | C46: =IFERROR(__xludf.DUMMYFUNCTION("GOOGLETRANSLATE(Portuguese!C46,""pt"",""en"")"),"1 can of sweetened condensed milk 1 liter of milk 4 tablespoons of cornstarch 2 separated eggs 2 boxes of chopped Bis chocolate bars 1 cup of sugar 1 can of heavy cream") -> 1 can of sweetened condensed milk 1 liter of milk 4 tablespoons of cornstarch 2 separated eggs 2 boxes of chopped Bis chocolate bars 1 cup of sugar 1 can of heavy cream | D46: =IFERROR(__xludf.DUMMYFUNCTION("GOOGLETRANSLATE(Portuguese!D46,""pt"",""en"")"),"Mix the condensed milk, milk, cornstarch, and egg yolks and cook over low heat. Stir constantly until thickened and set aside. Line the bottom of a large baking dish with half of the cream. Form a layer with the chopped chocolate and top with the remainin"&"g cream. Beat the egg whites until stiff peaks form and gradually add the sugar, beating constantly, until a firm meringue is obtained. Add the heavy cream and mix well. Place this mixture on top of the cream and refrigerate until ready to serve.") -> Mix the condensed milk, milk, cornstarch, and egg yolks and cook over low heat. Stir constantly until thickened and set aside. Line the bottom of a large baking dish with half of the cream. Form a layer with the chopped chocolate and top with the remaining cream. Beat the egg whites until stiff peaks form and gradually add the sugar, beating constantly, until a firm meringue is obtained. Add the heavy cream and mix well. Place this mixture on top of the cream and refrigerate until ready to serve. | E46: https://www.tudogostoso.com.br/receita/612-pave-de-bis.html
A47: 45 | B47: =IFERROR(__xludf.DUMMYFUNCTION("GOOGLETRANSLATE(Portuguese!B47,""pt"",""en"")"),"Oven-baked ham and cheese sandwich, my way.") -> Oven-baked ham and cheese sandwich, my way. | C47: =IFERROR(__xludf.DUMMYFUNCTION("GOOGLETRANSLATE(Portuguese!C47,""pt"",""en"")"),"Margarine for greasing 12 slices of white bread (crusts removed) 1/2 can of ready-made tomato sauce (I used 1 sachet of Sazon seasoning, Northeastern flavor) 6 slices of ham (or to taste) 4 tablespoons of cream cheese 12 slices of mozzarella cheese (or to"&" taste) 1/2 carton of heavy cream 1 large tomato, sliced Oregano to taste") -> Margarine for greasing 12 slices of white bread (crusts removed) 1/2 can of ready-made tomato sauce (I used 1 sachet of Sazon seasoning, Northeastern flavor) 6 slices of ham (or to taste) 4 tablespoons of cream cheese 12 slices of mozzarella cheese (or to taste) 1/2 carton of heavy cream 1 large tomato, sliced Oregano to taste | D47: =IFERROR(__xludf.DUMMYFUNCTION("GOOGLETRANSLATE(Portuguese!D47,""pt"",""en"")"),"Grease a baking dish with margarine. Line the bottom with 6 slices of bread. Place half of the seasoned tomato sauce, ham, a layer of cream cheese, half of the mozzarella, the remaining bread, tomato sauce, cream, mozzarella, sliced ​​tomatoes, and orega"&"no. Bake in the oven until the mozzarella melts (I did it in the microwave).") -> Grease a baking dish with margarine. Line the bottom with 6 slices of bread. Place half of the seasoned tomato sauce, ham, a layer of cream cheese, half of the mozzarella, the remaining bread, tomato sauce, cream, mozzarella, sliced ​​tomatoes, and oregano. Bake in the oven until the mozzarella melts (I did it in the microwave). | E47: https://www.tudogostoso.com.br/receita/138603-misto-quente-de-forno-a-minha-moda.html
A48: 46 | B48: =IFERROR(__xludf.DUMMYFUNCTION("GOOGLETRANSLATE(Portuguese!B48,""pt"",""en"")"),"Bread keeps husband safe.") -> Bread keeps husband safe. | C48: =IFERROR(__xludf.DUMMYFUNCTION("GOOGLETRANSLATE(Portuguese!C48,""pt"",""en"")"),"1 kg of wheat flour 2 cups of warm milk 1 cup of oil 1 tablespoon of yeast Salt to taste 250 g of ham 250 g of mozzarella cheese Tomato sauce Cream cheese Oregano") -> 1 kg of wheat flour 2 cups of warm milk 1 cup of oil 1 tablespoon of yeast Salt to taste 250 g of ham 250 g of mozzarella cheese Tomato sauce Cream cheese Oregano | D48: =IFERROR(__xludf.DUMMYFUNCTION("GOOGLETRANSLATE(Portuguese!D48,""pt"",""en"")"),"In a bowl, mix the milk, oil, yeast, salt, and a little flour. Add more flour gradually, mixing constantly until the dough no longer sticks to your hands. Let the dough rest for 15 minutes. Divide the dough and roll out one of the portions on a clean, dry"&" surface. Pour a layer of tomato sauce, cover with ham, mozzarella, cream cheese, and oregano. Fold the edges of the dough and roll it up like a roulade. Do the same with the other portion of dough. Bake in a preheated medium oven (180°C) for about 20 min"&"utes.") -> In a bowl, mix the milk, oil, yeast, salt, and a little flour. Add more flour gradually, mixing constantly until the dough no longer sticks to your hands. Let the dough rest for 15 minutes. Divide the dough and roll out one of the portions on a clean, dry surface. Pour a layer of tomato sauce, cover with ham, mozzarella, cream cheese, and oregano. Fold the edges of the dough and roll it up like a roulade. Do the same with the other portion of dough. Bake in a preheated medium oven (180°C) for about 20 minutes. | E48: https://www.tudogostoso.com.br/receita/1511-pao-segura-marido.html
A49: 47 | B49: =IFERROR(__xludf.DUMMYFUNCTION("GOOGLETRANSLATE(Portuguese!B49,""pt"",""en"")"),"Microwave mug cake") -> Microwave mug cake | C49: =IFERROR(__xludf.DUMMYFUNCTION("GOOGLETRANSLATE(Portuguese!C49,""pt"",""en"")"),"1 egg 2 tablespoons of chocolate powder 3 level tablespoons of sugar 4 level tablespoons of wheat flour 1 tablespoon of oil 1 level teaspoon of baking powder 4 tablespoons of milk 2 tablespoons of chocolate powder 1 tablespoon of margarine 1/2 cup"&" of milk") -> 1 egg 2 tablespoons of chocolate powder 3 level tablespoons of sugar 4 level tablespoons of wheat flour 1 tablespoon of oil 1 level teaspoon of baking powder 4 tablespoons of milk 2 tablespoons of chocolate powder 1 tablespoon of margarine 1/2 cup of milk | D49: =IFERROR(__xludf.DUMMYFUNCTION("GOOGLETRANSLATE(Portuguese!D49,""pt"",""en"")"),"Place all ingredients in a mug of approximately 300 ml or more. Stir until you obtain a homogeneous mixture and microwave for 3 minutes. Place all ingredients in a saucepan, bring to a medium heat and mix until you obtain a thick consistency. Pour the syr"&"up over the cake as soon as you remove it from the microwave.") -> Place all ingredients in a mug of approximately 300 ml or more. Stir until you obtain a homogeneous mixture and microwave for 3 minutes. Place all ingredients in a saucepan, bring to a medium heat and mix until you obtain a thick consistency. Pour the syrup over the cake as soon as you remove it from the microwave. | E49: https://www.tudogostoso.com.br/receita/60429-bolo-de-caneca-micro-ondas.html
A50: 48 | B50: =IFERROR(__xludf.DUMMYFUNCTION("GOOGLETRANSLATE(Portuguese!B50,""pt"",""en"")"),"Caramelized banana cake") -> Caramelized banana cake | C50: =IFERROR(__xludf.DUMMYFUNCTION("GOOGLETRANSLATE(Portuguese!C50,""pt"",""en"")"),"3 eggs 3 tablespoons of margarine 1 1/2 cups of sugar 1 pinch of salt 1 cup of milk 2 cups of wheat flour 1 level tablespoon of baking powder 1 cup of sugar 4 to 5 bananas") -> 3 eggs 3 tablespoons of margarine 1 1/2 cups of sugar 1 pinch of salt 1 cup of milk 2 cups of wheat flour 1 level tablespoon of baking powder 1 cup of sugar 4 to 5 bananas | D50: =IFERROR(__xludf.DUMMYFUNCTION("GOOGLETRANSLATE(Portuguese!D50,""pt"",""en"")"),"Pour the sugar into a round pan with a hole in the center and heat until completely melted. Immediately after, slice the bananas and arrange them over the caramelized sugar. Beat the egg whites until stiff peaks form and set aside. In another bowl, beat t"&"he eggs with the margarine and sugar. Add the flour, milk, salt, and baking powder. Finally, fold in the beaten egg whites and continue beating. Pour the batter into the caramelized pan with the sliced ​​bananas. Bake in a preheated medium oven (180°C) fo"&"r 30 minutes.") -> Pour the sugar into a round pan with a hole in the center and heat until completely melted. Immediately after, slice the bananas and arrange them over the caramelized sugar. Beat the egg whites until stiff peaks form and set aside. In another bowl, beat the eggs with the margarine and sugar. Add the flour, milk, salt, and baking powder. Finally, fold in the beaten egg whites and continue beating. Pour the batter into the caramelized pan with the sliced ​​bananas. Bake in a preheated medium oven (180°C) for 30 minutes. | E50: https://www.tudogostoso.com.br/receita/41516-bolo-de-banana-caramelada.html
A51: 49 | B51: =IFERROR(__xludf.DUMMYFUNCTION("GOOGLETRANSLATE(Portuguese!B51,""pt"",""en"")"),"Cake to catch husbands") -> Cake to catch husbands | C51: =IFERROR(__xludf.DUMMYFUNCTION("GOOGLETRANSLATE(Portuguese!C51,""pt"",""en"")"),"1 can of sweetened condensed milk 1 can of whole milk (same measure as the sweetened condensed milk can) 1 small jar of coconut milk 1 can of all-purpose flour (or regular flour) (same can) 1/2 can of sugar (same can) 3 large whole eggs 3 tablespoon"&"s of margarine") -> 1 can of sweetened condensed milk 1 can of whole milk (same measure as the sweetened condensed milk can) 1 small jar of coconut milk 1 can of all-purpose flour (or regular flour) (same can) 1/2 can of sugar (same can) 3 large whole eggs 3 tablespoons of margarine | D51: =IFERROR(__xludf.DUMMYFUNCTION("GOOGLETRANSLATE(Portuguese!D51,""pt"",""en"")"),"Blend all ingredients in a blender. Pour into a greased and floured baking pan. Bake in a moderate oven (200°C/390°F) until golden brown, 30 to 60 minutes, depending on the oven. Do the toothpick test to remove from the oven. The cake has the consistency "&"of a cheesecake and is very tasty!") -> Blend all ingredients in a blender. Pour into a greased and floured baking pan. Bake in a moderate oven (200°C/390°F) until golden brown, 30 to 60 minutes, depending on the oven. Do the toothpick test to remove from the oven. The cake has the consistency of a cheesecake and is very tasty! | E51: https://www.tudogostoso.com.br/receita/139339-bolo-pega-marido.html
A52: 50 | B52: =IFERROR(__xludf.DUMMYFUNCTION("GOOGLETRANSLATE(Portuguese!B52,""pt"",""en"")"),"Cornmeal cake made in a blender") -> Cornmeal cake made in a blender | C52: =IFERROR(__xludf.DUMMYFUNCTION("GOOGLETRANSLATE(Portuguese!C52,""pt"",""en"")"),"1 cup of oil 3 eggs 1 1/2 cups of sugar 2 cups of cornmeal 1 cup of wheat flour 1 cup of milk 1 tablespoon of baking powder 1 pinch of salt") -> 1 cup of oil 3 eggs 1 1/2 cups of sugar 2 cups of cornmeal 1 cup of wheat flour 1 cup of milk 1 tablespoon of baking powder 1 pinch of salt | D52: =IFERROR(__xludf.DUMMYFUNCTION("GOOGLETRANSLATE(Portuguese!D52,""pt"",""en"")"),"Blend everything in a blender. Pour into a greased and floured (or cornmeal-dusted) baking pan. Bake in a preheated oven at 180ºC (350ºF) for 45 minutes. When it comes out of the oven, sprinkle with sugar and cinnamon.") -> Blend everything in a blender. Pour into a greased and floured (or cornmeal-dusted) baking pan. Bake in a preheated oven at 180ºC (350ºF) for 45 minutes. When it comes out of the oven, sprinkle with sugar and cinnamon. | E52: https://www.tudogostoso.com.br/receita/25518-bolo-de-fuba-de-liquidificador.html
A53: 51 | B53: =IFERROR(__xludf.DUMMYFUNCTION("GOOGLETRANSLATE(Portuguese!B53,""pt"",""en"")"),"Condensed milk pudding") -> Condensed milk pudding | C53: =IFERROR(__xludf.DUMMYFUNCTION("GOOGLETRANSLATE(Portuguese!C53,""pt"",""en"")"),"1 can of sweetened condensed milk 1 can of milk (using the sweetened condensed milk can as a measure) 3 whole eggs 1 cup of sugar 1/2 cup of water") -> 1 can of sweetened condensed milk 1 can of milk (using the sweetened condensed milk can as a measure) 3 whole eggs 1 cup of sugar 1/2 cup of water | D53: =IFERROR(__xludf.DUMMYFUNCTION("GOOGLETRANSLATE(Portuguese!D53,""pt"",""en"")"),"First, beat the eggs well in a blender. Add the condensed milk and milk, and beat again. Melt the sugar in a saucepan until it turns brown, add the water and let it thicken. Pour into a round mold and pour the pudding mixture over it. Bake in a medium ove"&"n for 45 minutes, with the round mold inside a larger one filled with water. Insert a fork to check if it is fully baked. Let it cool and unmold.") -> First, beat the eggs well in a blender. Add the condensed milk and milk, and beat again. Melt the sugar in a saucepan until it turns brown, add the water and let it thicken. Pour into a round mold and pour the pudding mixture over it. Bake in a medium oven for 45 minutes, with the round mold inside a larger one filled with water. Insert a fork to check if it is fully baked. Let it cool and unmold. | E53: https://www.tudogostoso.com.br/receita/31593-pudim-de-leite-condensado.html
A54: 52 | B54: =IFERROR(__xludf.DUMMYFUNCTION("GOOGLETRANSLATE(Portuguese!B54,""pt"",""en"")"),"Apple cake made in a blender - the best in the world.") -> Apple cake made in a blender - the best in the world. | C54: =IFERROR(__xludf.DUMMYFUNCTION("GOOGLETRANSLATE(Portuguese!C54,""pt"",""en"")"),"2 cups all-purpose flour 2 cups sugar 1 tablespoon baking powder 1 tablespoon ground cinnamon 1 pinch of salt 3 eggs 3 large apples 1 cup vegetable oil") -> 2 cups all-purpose flour 2 cups sugar 1 tablespoon baking powder 1 tablespoon ground cinnamon 1 pinch of salt 3 eggs 3 large apples 1 cup vegetable oil | D54: =IFERROR(__xludf.DUMMYFUNCTION("GOOGLETRANSLATE(Portuguese!D54,""pt"",""en"")"),"Grease and flour a medium baking pan (23x35 cm), or a bundt pan. In a large bowl, sift together the flour and sugar. Add the remaining dry ingredients. Set aside. Peel the apples, reserving the peels. Dice them. In a blender, combine the eggs, oil, and ap"&"ple peels. Add this mixture to the bowl with the dry ingredients and mix gently. Add the diced apples, mix, and pour into the prepared pan. Bake for about 40 to 50 minutes in a moderate oven. Once done, sprinkle with sugar and cinnamon.") -> Grease and flour a medium baking pan (23x35 cm), or a bundt pan. In a large bowl, sift together the flour and sugar. Add the remaining dry ingredients. Set aside. Peel the apples, reserving the peels. Dice them. In a blender, combine the eggs, oil, and apple peels. Add this mixture to the bowl with the dry ingredients and mix gently. Add the diced apples, mix, and pour into the prepared pan. Bake for about 40 to 50 minutes in a moderate oven. Once done, sprinkle with sugar and cinnamon. | E54: https://www.tudogostoso.com.br/receita/109535-bolo-de-maca-de-liquidificador-o-melhor-do-mundo.html
A55: 53 | B55: =IFERROR(__xludf.DUMMYFUNCTION("GOOGLETRANSLATE(Portuguese!B55,""pt"",""en"")"),"Pressure cooker meat") -> Pressure cooker meat | C55: =IFERROR(__xludf.DUMMYFUNCTION("GOOGLETRANSLATE(Portuguese!C55,""pt"",""en"")"),"1 kg of meat (chuck, round steak or pork loin) 8 large onions, sliced 3 or 4 beef bouillon cubes") -> 1 kg of meat (chuck, round steak or pork loin) 8 large onions, sliced 3 or 4 beef bouillon cubes | D55: =IFERROR(__xludf.DUMMYFUNCTION("GOOGLETRANSLATE(Portuguese!D55,""pt"",""en"")"),"Line the bottom of a pressure cooker with half of the onions. Crumble a beef bouillon cube over the onions, add the meat, add another beef bouillon cube, and cover with the remaining onions. Close the pressure cooker, without adding water, and cook for 25"&" minutes. If desired, add sliced ​​potatoes and cook for another 10 minutes.") -> Line the bottom of a pressure cooker with half of the onions. Crumble a beef bouillon cube over the onions, add the meat, add another beef bouillon cube, and cover with the remaining onions. Close the pressure cooker, without adding water, and cook for 25 minutes. If desired, add sliced ​​potatoes and cook for another 10 minutes. | E55: https://www.tudogostoso.com.br/receita/1438-carne-de-panela-de-pressao.html
A56: 54 | B56: =IFERROR(__xludf.DUMMYFUNCTION("GOOGLETRANSLATE(Portuguese!B56,""pt"",""en"")"),"Simple pancake batter") -> Simple pancake batter | C56: =IFERROR(__xludf.DUMMYFUNCTION("GOOGLETRANSLATE(Portuguese!C56,""pt"",""en"")"),"1 egg 1 cup of wheat flour 1 cup of milk 1 pinch of salt 1 tablespoon of oil") -> 1 egg 1 cup of wheat flour 1 cup of milk 1 pinch of salt 1 tablespoon of oil | D56: =IFERROR(__xludf.DUMMYFUNCTION("GOOGLETRANSLATE(Portuguese!D56,""pt"",""en"")"),"Blend all ingredients in a blender until creamy. Grease a frying pan with oil and pour in a ladleful of batter. Make circular motions so that the batter spreads across the entire pan. Wait until the batter releases from the bottom, flip it, and let it fry"&" on the other side. Add your preferred filling, roll it up, and it's ready to serve.") -> Blend all ingredients in a blender until creamy. Grease a frying pan with oil and pour in a ladleful of batter. Make circular motions so that the batter spreads across the entire pan. Wait until the batter releases from the bottom, flip it, and let it fry on the other side. Add your preferred filling, roll it up, and it's ready to serve. | E56: https://www.tudogostoso.com.br/receita/113143-massa-de-panqueca-simples.html
A57: 55 | B57: =IFERROR(__xludf.DUMMYFUNCTION("GOOGLETRANSLATE(Portuguese!B57,""pt"",""en"")"),"Special hot chocolate") -> Special hot chocolate | C57: =IFERROR(__xludf.DUMMYFUNCTION("GOOGLETRANSLATE(Portuguese!C57,""pt"",""en"")"),"1 liter of skim milk 1 can of condensed milk 4 tablespoons of cocoa powder 2 tablespoons of cornstarch Cinnamon powder for sprinkling") -> 1 liter of skim milk 1 can of condensed milk 4 tablespoons of cocoa powder 2 tablespoons of cornstarch Cinnamon powder for sprinkling | D57: =IFERROR(__xludf.DUMMYFUNCTION("GOOGLETRANSLATE(Portuguese!D57,""pt"",""en"")"),"Blend all ingredients in a blender (except the cinnamon). Bring to a boil over medium heat until the liquid thickens. Serve in cups and sprinkle with cinnamon. For a special touch, you can add whipped cream on top of the chocolate cup.") -> Blend all ingredients in a blender (except the cinnamon). Bring to a boil over medium heat until the liquid thickens. Serve in cups and sprinkle with cinnamon. For a special touch, you can add whipped cream on top of the chocolate cup. | E57: https://www.tudogostoso.com.br/receita/33-chocolate-quente-especial.html
A58: 56 | B58: =IFERROR(__xludf.DUMMYFUNCTION("GOOGLETRANSLATE(Portuguese!B58,""pt"",""en"")"),"green broth") -> green broth | C58: =IFERROR(__xludf.DUMMYFUNCTION("GOOGLETRANSLATE(Portuguese!C58,""pt"",""en"")"),"4 medium potatoes 1 chicken bouillon cube 1 tablespoon of oil 1 level tablespoon of salt or to taste 5 cups of water 1 cup of shredded kale 1 smoked calabrese sausage, sliced") -> 4 medium potatoes 1 chicken bouillon cube 1 tablespoon of oil 1 level tablespoon of salt or to taste 5 cups of water 1 cup of shredded kale 1 smoked calabrese sausage, sliced | D58: =IFERROR(__xludf.DUMMYFUNCTION("GOOGLETRANSLATE(Portuguese!D58,""pt"",""en"")"),"In a pressure cooker, place the potato, chicken broth, oil, water, and salt. Cook for about 10 minutes (start counting the time after the pressure cooker starts hissing) until the potato is very soft. Then, blend everything in a blender. Add the sliced ​​"&"calabrese sausage and bring to a boil. Turn off the heat and add the collard greens. When serving, drizzle with olive oil or add croutons.") -> In a pressure cooker, place the potato, chicken broth, oil, water, and salt. Cook for about 10 minutes (start counting the time after the pressure cooker starts hissing) until the potato is very soft. Then, blend everything in a blender. Add the sliced ​​calabrese sausage and bring to a boil. Turn off the heat and add the collard greens. When serving, drizzle with olive oil or add croutons. | E58: https://www.tudogostoso.com.br/receita/9031-caldo-verde.html
A59: 57 | B59: =IFERROR(__xludf.DUMMYFUNCTION("GOOGLETRANSLATE(Portuguese!B59,""pt"",""en"")"),"Rice cake") -> Rice cake | C59: =IFERROR(__xludf.DUMMYFUNCTION("GOOGLETRANSLATE(Portuguese!C59,""pt"",""en"")"),"2 cups cooked rice 1/2 cup grated cheese 1/2 cup milk 2 tablespoons chopped parsley 1 tablespoon baking powder 1/2 cup cornstarch 1/2 cup wheat flour 3 eggs oil for frying") -> 2 cups cooked rice 1/2 cup grated cheese 1/2 cup milk 2 tablespoons chopped parsley 1 tablespoon baking powder 1/2 cup cornstarch 1/2 cup wheat flour 3 eggs oil for frying | D59: =IFERROR(__xludf.DUMMYFUNCTION("GOOGLETRANSLATE(Portuguese!D59,""pt"",""en"")"),"In a bowl, mix all the ingredients until a firm, consistent dough forms. Shape the dough into balls and fry them in hot oil until golden brown. Drain on absorbent paper.") -> In a bowl, mix all the ingredients until a firm, consistent dough forms. Shape the dough into balls and fry them in hot oil until golden brown. Drain on absorbent paper. | E59: https://www.tudogostoso.com.br/receita/4224-bolinho-de-arroz.html
A60: 58 | B60: =IFERROR(__xludf.DUMMYFUNCTION("GOOGLETRANSLATE(Portuguese!B60,""pt"",""en"")"),"Pancake batter") -> Pancake batter | C60: =IFERROR(__xludf.DUMMYFUNCTION("GOOGLETRANSLATE(Portuguese!C60,""pt"",""en"")"),"2 cups (tea) of wheat flour 2 cups (tea) of milk 3 eggs 1 pinch of salt") -> 2 cups (tea) of wheat flour 2 cups (tea) of milk 3 eggs 1 pinch of salt | D60: =IFERROR(__xludf.DUMMYFUNCTION("GOOGLETRANSLATE(Portuguese!D60,""pt"",""en"")"),"Blend all ingredients in a blender for 2 minutes. Then turn off the blender and, using a spoon, mix in the flour that stuck to the sides of the blender. Blend again just to mix and set aside. Grease a frying pan with a drizzle of oil and heat over medium "&"heat. Using a ladle, scoop a portion of batter and pour it into the pan, swirling the pan to spread the batter evenly. Lower the heat and let it brown on the bottom, then flip and brown the other side. Repeat the process with all the batter.") -> Blend all ingredients in a blender for 2 minutes. Then turn off the blender and, using a spoon, mix in the flour that stuck to the sides of the blender. Blend again just to mix and set aside. Grease a frying pan with a drizzle of oil and heat over medium heat. Using a ladle, scoop a portion of batter and pour it into the pan, swirling the pan to spread the batter evenly. Lower the heat and let it brown on the bottom, then flip and brown the other side. Repeat the process with all the batter. | E60: https://www.tudogostoso.com.br/receita/82681-massa-de-panqueca.html
A61: 59 | B61: =IFERROR(__xludf.DUMMYFUNCTION("GOOGLETRANSLATE(Portuguese!B61,""pt"",""en"")"),"Cornmeal cake with guava paste") -> Cornmeal cake with guava paste | C61: =IFERROR(__xludf.DUMMYFUNCTION("GOOGLETRANSLATE(Portuguese!C61,""pt"",""en"")"),"1 egg 1 cup (American) of milk 1 cup (American) of cornmeal 1 cup (American) of sugar 1/2 cup (American) of oil 1 cup (American) of wheat flour 1 tablespoon of baking powder Guava paste in pieces Anise seeds to taste") -> 1 egg 1 cup (American) of milk 1 cup (American) of cornmeal 1 cup (American) of sugar 1/2 cup (American) of oil 1 cup (American) of wheat flour 1 tablespoon of baking powder Guava paste in pieces Anise seeds to taste | D61: =IFERROR(__xludf.DUMMYFUNCTION("GOOGLETRANSLATE(Portuguese!D61,""pt"",""en"")"),"In a blender, mix the egg, milk, oil, sugar, and cornmeal and blend well. Pour the mixture into a bowl and mix in the flour and baking powder. Pour the batter into a greased and floured baking pan, and add a layer of guava paste. Repeat this process until"&" the pan is full. Bake the cornmeal cake with guava paste in a preheated medium oven (180°C) for 40 minutes.") -> In a blender, mix the egg, milk, oil, sugar, and cornmeal and blend well. Pour the mixture into a bowl and mix in the flour and baking powder. Pour the batter into a greased and floured baking pan, and add a layer of guava paste. Repeat this process until the pan is full. Bake the cornmeal cake with guava paste in a preheated medium oven (180°C) for 40 minutes. | E61: https://www.tudogostoso.com.br/receita/3004-bolo-de-fuba-com-goiabada.html
A62: 60 | B62: =IFERROR(__xludf.DUMMYFUNCTION("GOOGLETRANSLATE(Portuguese!B62,""pt"",""en"")"),"Brigadeirão") -> Brigadeirão | C62: =IFERROR(__xludf.DUMMYFUNCTION("GOOGLETRANSLATE(Portuguese!C62,""pt"",""en"")"),"2 cans of sweetened condensed milk 1 can of cow's milk (use the condensed milk can as a measure) 1 tablespoon of butter 200g of cocoa powder 4 eggs Sugar, enough to sprinkle on the mold") -> 2 cans of sweetened condensed milk 1 can of cow's milk (use the condensed milk can as a measure) 1 tablespoon of butter 200g of cocoa powder 4 eggs Sugar, enough to sprinkle on the mold | D62: =IFERROR(__xludf.DUMMYFUNCTION("GOOGLETRANSLATE(Portuguese!D62,""pt"",""en"")"),"Blend the condensed milk, cow's milk, butter, cocoa powder, and eggs in a blender. Grease a bundt pan and sprinkle with sugar. Pour the blended mixture into the pan and bake in a water bath for about 1 hour at 150°C (300°F).") -> Blend the condensed milk, cow's milk, butter, cocoa powder, and eggs in a blender. Grease a bundt pan and sprinkle with sugar. Pour the blended mixture into the pan and bake in a water bath for about 1 hour at 150°C (300°F). | E62: https://www.tudogostoso.com.br/receita/592-brigadeirao.html
A63: 61 | B63: =IFERROR(__xludf.DUMMYFUNCTION("GOOGLETRANSLATE(Portuguese!B63,""pt"",""en"")"),"Chicken with vegetables") -> Chicken with vegetables | C63: =IFERROR(__xludf.DUMMYFUNCTION("GOOGLETRANSLATE(Portuguese!C63,""pt"",""en"")"),"2 tablespoons olive oil 2 medium onions, diced 2 cloves garlic, crushed 500g skinless chicken breast, cubed Salt to taste 1 green bell pepper, diced 1 red bell pepper, diced 1 yellow bell pepper, diced 1 cup canned mushrooms, halved 1/4 cup soy sauce 1 ta"&"blespoon cornstarch 1/2 cup water 2 tablespoons roasted peanuts") -> 2 tablespoons olive oil 2 medium onions, diced 2 cloves garlic, crushed 500g skinless chicken breast, cubed Salt to taste 1 green bell pepper, diced 1 red bell pepper, diced 1 yellow bell pepper, diced 1 cup canned mushrooms, halved 1/4 cup soy sauce 1 tablespoon cornstarch 1/2 cup water 2 tablespoons roasted peanuts | D63: =IFERROR(__xludf.DUMMYFUNCTION("GOOGLETRANSLATE(Portuguese!D63,""pt"",""en"")"),"In a large skillet or pan, combine half the olive oil, the onion, and the garlic and sauté. Remove and set aside on a plate. In the same pan, add the salt and the remaining olive oil and sauté the bell peppers and mushrooms for 5 minutes. Remove and set a"&"side on another plate. In the same pan, add the chicken and sauté until golden brown. Return all ingredients to the skillet, mix well with a wooden spoon, and sauté for another 2 minutes. In a cup, combine the soy sauce, cornstarch, and water. Stir well a"&"nd add to the chicken mixture. Cook, stirring constantly, until a thick sauce forms. Place in a serving dish, sprinkle with peanuts, and serve hot.") -> In a large skillet or pan, combine half the olive oil, the onion, and the garlic and sauté. Remove and set aside on a plate. In the same pan, add the salt and the remaining olive oil and sauté the bell peppers and mushrooms for 5 minutes. Remove and set aside on another plate. In the same pan, add the chicken and sauté until golden brown. Return all ingredients to the skillet, mix well with a wooden spoon, and sauté for another 2 minutes. In a cup, combine the soy sauce, cornstarch, and water. Stir well and add to the chicken mixture. Cook, stirring constantly, until a thick sauce forms. Place in a serving dish, sprinkle with peanuts, and serve hot. | E63: https://www.tudogostoso.com.br/receita/897-frango-xadrez.html
A64: 62 | B64: =IFERROR(__xludf.DUMMYFUNCTION("GOOGLETRANSLATE(Portuguese!B64,""pt"",""en"")"),"Delicious ground beef roulade") -> Delicious ground beef roulade | C64: =IFERROR(__xludf.DUMMYFUNCTION("GOOGLETRANSLATE(Portuguese!C64,""pt"",""en"")"),"1/2 kg of ground beef 1 packet of onion soup mix sliced ​​ham sliced ​​cheese green seasoning salt to taste") -> 1/2 kg of ground beef 1 packet of onion soup mix sliced ​​ham sliced ​​cheese green seasoning salt to taste | D64: =IFERROR(__xludf.DUMMYFUNCTION("GOOGLETRANSLATE(Portuguese!D64,""pt"",""en"")"),"Season the ground beef with the onion soup mix, green seasoning, and salt. Place the seasoned meat on a sheet of aluminum foil or parchment paper and roll it out to a thickness of about 1 cm. Cover the meat with ham and cheese; you can also add corn, peas"&", and cream cheese. Roll the meat up, using the aluminum foil or parchment paper, into a roulade shape. Bake in a hot oven for about 30 minutes, or microwave for 15 minutes. Enjoy!") -> Season the ground beef with the onion soup mix, green seasoning, and salt. Place the seasoned meat on a sheet of aluminum foil or parchment paper and roll it out to a thickness of about 1 cm. Cover the meat with ham and cheese; you can also add corn, peas, and cream cheese. Roll the meat up, using the aluminum foil or parchment paper, into a roulade shape. Bake in a hot oven for about 30 minutes, or microwave for 15 minutes. Enjoy! | E64: https://www.tudogostoso.com.br/receita/1598-rocambole-de-carne-moida-maravilhoso.html
A65: 63 | B65: =IFERROR(__xludf.DUMMYFUNCTION("GOOGLETRANSLATE(Portuguese!B65,""pt"",""en"")"),"Cornmeal cake") -> Cornmeal cake | C65: =IFERROR(__xludf.DUMMYFUNCTION("GOOGLETRANSLATE(Portuguese!C65,""pt"",""en"")"),"3 whole eggs 2 cups of sugar 2 cups of cornmeal 3 tablespoons of wheat flour 1/2 cup of oil 1 cup of milk 1 tablespoon of baking powder") -> 3 whole eggs 2 cups of sugar 2 cups of cornmeal 3 tablespoons of wheat flour 1/2 cup of oil 1 cup of milk 1 tablespoon of baking powder | D65: =IFERROR(__xludf.DUMMYFUNCTION("GOOGLETRANSLATE(Portuguese!D65,""pt"",""en"")"),"In a blender, add the eggs, sugar, cornmeal, wheat flour, oil, milk, and baking powder, then blend until the batter is smooth and homogeneous. Pour the batter into a greased and floured pan. Bake in a preheated medium oven (180°C) for 40 minutes.") -> In a blender, add the eggs, sugar, cornmeal, wheat flour, oil, milk, and baking powder, then blend until the batter is smooth and homogeneous. Pour the batter into a greased and floured pan. Bake in a preheated medium oven (180°C) for 40 minutes. | E65: https://www.tudogostoso.com.br/receita/9254-bolo-de-fuba.html
A66: 64 | B66: =IFERROR(__xludf.DUMMYFUNCTION("GOOGLETRANSLATE(Portuguese!B66,""pt"",""en"")"),"Blender cake") -> Blender cake | C66: =IFERROR(__xludf.DUMMYFUNCTION("GOOGLETRANSLATE(Portuguese!C66,""pt"",""en"")"),"3 eggs 2 tablespoons of margarine 2 cups (cream cheese container) of sugar 2 cups (cream cheese container) of wheat flour 1 cup (cream cheese container) of milk 1 level teaspoon of baking powder") -> 3 eggs 2 tablespoons of margarine 2 cups (cream cheese container) of sugar 2 cups (cream cheese container) of wheat flour 1 cup (cream cheese container) of milk 1 level teaspoon of baking powder | D66: =IFERROR(__xludf.DUMMYFUNCTION("GOOGLETRANSLATE(Portuguese!D66,""pt"",""en"")"),"In a blender, beat together the eggs, sugar, and margarine. Then add the flour, milk, and baking powder, and blend again. Pour into a greased and floured baking pan and bake.") -> In a blender, beat together the eggs, sugar, and margarine. Then add the flour, milk, and baking powder, and blend again. Pour into a greased and floured baking pan and bake. | E66: https://www.tudogostoso.com.br/receita/11252-bolo-de-liquidificador.html
A67: 65 | B67: =IFERROR(__xludf.DUMMYFUNCTION("GOOGLETRANSLATE(Portuguese!B67,""pt"",""en"")"),"Bread pudding") -> Bread pudding | C67: =IFERROR(__xludf.DUMMYFUNCTION("GOOGLETRANSLATE(Portuguese!C67,""pt"",""en"")"),"3 stale or hard bread rolls 8 tablespoons of granulated sugar 2 whole eggs 500 ml of milk") -> 3 stale or hard bread rolls 8 tablespoons of granulated sugar 2 whole eggs 500 ml of milk | D67: =IFERROR(__xludf.DUMMYFUNCTION("GOOGLETRANSLATE(Portuguese!D67,""pt"",""en"")"),"Blend all ingredients in a blender until the mixture is smooth. Caramelize a pudding mold with burnt syrup and add the blended mixture. Cook in a water bath for approximately 30 to 40 minutes, or until the pudding is set.") -> Blend all ingredients in a blender until the mixture is smooth. Caramelize a pudding mold with burnt syrup and add the blended mixture. Cook in a water bath for approximately 30 to 40 minutes, or until the pudding is set. | E67: https://www.tudogostoso.com.br/receita/1558-pudim-de-pao.html
A68: 66 | B68: =IFERROR(__xludf.DUMMYFUNCTION("GOOGLETRANSLATE(Portuguese!B68,""pt"",""en"")"),"Authentic rice pudding") -> Authentic rice pudding | C68: =IFERROR(__xludf.DUMMYFUNCTION("GOOGLETRANSLATE(Portuguese!C68,""pt"",""en"")"),"1 and 1/2 liters of milk 2 cups of white rice (already washed) 3 cups of sugar Cinnamon stick to taste 1 can of condensed milk") -> 1 and 1/2 liters of milk 2 cups of white rice (already washed) 3 cups of sugar Cinnamon stick to taste 1 can of condensed milk | D68: =IFERROR(__xludf.DUMMYFUNCTION("GOOGLETRANSLATE(Portuguese!D68,""pt"",""en"")"),"Cook the rice in the milk, along with the cinnamon (use a large saucepan so that the milk boils over). After 20 minutes, stir occasionally. Add the sugar and let it cook for 20 minutes. Then, add the condensed milk and let it cook for another 20 minutes. "&"Place in a beautiful serving dish.") -> Cook the rice in the milk, along with the cinnamon (use a large saucepan so that the milk boils over). After 20 minutes, stir occasionally. Add the sugar and let it cook for 20 minutes. Then, add the condensed milk and let it cook for another 20 minutes. Place in a beautiful serving dish. | E68: https://www.tudogostoso.com.br/receita/5966-arroz-doce-verdadeiro.html
A69: 67 | B69: =IFERROR(__xludf.DUMMYFUNCTION("GOOGLETRANSLATE(Portuguese!B69,""pt"",""en"")"),"Easy gnocchi") -> Easy gnocchi | C69: =IFERROR(__xludf.DUMMYFUNCTION("GOOGLETRANSLATE(Portuguese!C69,""pt"",""en"")"),"2 chicken bouillon cubes 3 cups of milk 6 tablespoons of mayonnaise 2 tablespoons of chopped parsley Salt to taste 3 cups of wheat flour") -> 2 chicken bouillon cubes 3 cups of milk 6 tablespoons of mayonnaise 2 tablespoons of chopped parsley Salt to taste 3 cups of wheat flour | D69: =IFERROR(__xludf.DUMMYFUNCTION("GOOGLETRANSLATE(Portuguese!D69,""pt"",""en"")"),"Dissolve the 2 bouillon cubes in the milk and bring to a boil with the mayonnaise, parsley, and salt. When it boils and the mayonnaise melts, remove from the heat and add the wheat flour all at once. Mix very quickly to avoid lumps. Return the dough to lo"&"w heat, stirring for 1 or 2 minutes. Turn off the heat and let the dough cool slightly. On a floured surface, place the dough and roll it into small logs. Cut into gnocchi shapes. In another pot with water and salt, cook the gnocchi. The tip is to remove "&"the gnocchi from the water as soon as they rise to the surface; they will be ready. Drain and serve with your favorite sauce.") -> Dissolve the 2 bouillon cubes in the milk and bring to a boil with the mayonnaise, parsley, and salt. When it boils and the mayonnaise melts, remove from the heat and add the wheat flour all at once. Mix very quickly to avoid lumps. Return the dough to low heat, stirring for 1 or 2 minutes. Turn off the heat and let the dough cool slightly. On a floured surface, place the dough and roll it into small logs. Cut into gnocchi shapes. In another pot with water and salt, cook the gnocchi. The tip is to remove the gnocchi from the water as soon as they rise to the surface; they will be ready. Drain and serve with your favorite sauce. | E69: https://www.tudogostoso.com.br/receita/431-nhoque-facil.html
A70: 68 | B70: =IFERROR(__xludf.DUMMYFUNCTION("GOOGLETRANSLATE(Portuguese!B70,""pt"",""en"")"),"Brigadeiro without condensed milk") -> Brigadeiro without condensed milk | C70: =IFERROR(__xludf.DUMMYFUNCTION("GOOGLETRANSLATE(Portuguese!C70,""pt"",""en"")"),"1 cup of milk 4 tablespoons of chocolate powder 2 tablespoons of margarine 3 tablespoons of sugar") -> 1 cup of milk 4 tablespoons of chocolate powder 2 tablespoons of margarine 3 tablespoons of sugar | D70: =IFERROR(__xludf.DUMMYFUNCTION("GOOGLETRANSLATE(Portuguese!D70,""pt"",""en"")"),"In a saucepan, add the chocolate powder, sugar, and butter, mix quickly, and then add the milk. Stir with a wooden spoon over medium heat for approximately 25 minutes, until you obtain a creamy consistency. Turn off the heat and let it cool for 10 minutes"&". Shape the dough into small balls and roll them in chocolate sprinkles or serve in glasses.") -> In a saucepan, add the chocolate powder, sugar, and butter, mix quickly, and then add the milk. Stir with a wooden spoon over medium heat for approximately 25 minutes, until you obtain a creamy consistency. Turn off the heat and let it cool for 10 minutes. Shape the dough into small balls and roll them in chocolate sprinkles or serve in glasses. | E70: https://www.tudogostoso.com.br/receita/69649-brigadeiro-sem-leite-condensado.html
A71: 69 | B71: =IFERROR(__xludf.DUMMYFUNCTION("GOOGLETRANSLATE(Portuguese!B71,""pt"",""en"")"),"German cake (easy, simple and delicious)") -> German cake (easy, simple and delicious) | C71: =IFERROR(__xludf.DUMMYFUNCTION("GOOGLETRANSLATE(Portuguese!C71,""pt"",""en"")"),"200g unsalted butter 1 cup (tea) of sugar 1 can of heavy cream (without whey) 1 package of cornstarch cookies Milk, as needed, to soak the cookies 1 can of chocolate-flavored sweetened condensed milk (or ice cream topping)") -> 200g unsalted butter 1 cup (tea) of sugar 1 can of heavy cream (without whey) 1 package of cornstarch cookies Milk, as needed, to soak the cookies 1 can of chocolate-flavored sweetened condensed milk (or ice cream topping) | D71: =IFERROR(__xludf.DUMMYFUNCTION("GOOGLETRANSLATE(Portuguese!D71,""pt"",""en"")"),"Place the butter and sugar in a mixer and beat until you obtain a very fluffy and smooth cream. Add the heavy cream and beat quickly just to combine. Turn off the mixer and set aside. Prepare a medium-sized container to assemble the dessert. Add a little "&"milk to a shallow dish and quickly dip some Maria biscuits in the milk. Line the bottom of the chosen container with a layer of biscuits. Add a layer of the reserved cream over the biscuits. Add another layer of biscuits dipped in milk and repeat the proc"&"edure, finishing with a biscuit. Cover the last layer of biscuits with chocolate-flavored condensed milk (store-bought or topping). Refrigerate for at least 3 hours or until the dessert is well chilled. Remove the dessert from the refrigerator and serve i"&"mmediately.") -> Place the butter and sugar in a mixer and beat until you obtain a very fluffy and smooth cream. Add the heavy cream and beat quickly just to combine. Turn off the mixer and set aside. Prepare a medium-sized container to assemble the dessert. Add a little milk to a shallow dish and quickly dip some Maria biscuits in the milk. Line the bottom of the chosen container with a layer of biscuits. Add a layer of the reserved cream over the biscuits. Add another layer of biscuits dipped in milk and repeat the procedure, finishing with a biscuit. Cover the last layer of biscuits with chocolate-flavored condensed milk (store-bought or topping). Refrigerate for at least 3 hours or until the dessert is well chilled. Remove the dessert from the refrigerator and serve immediately. | E71: https://www.tudogostoso.com.br/receita/1412-torta-alema-facil-simples-e-deliciosa.html
A72: 70 | B72: =IFERROR(__xludf.DUMMYFUNCTION("GOOGLETRANSLATE(Portuguese!B72,""pt"",""en"")"),"Sweet popcorn") -> Sweet popcorn | C72: =IFERROR(__xludf.DUMMYFUNCTION("GOOGLETRANSLATE(Portuguese!C72,""pt"",""en"")"),"5 tablespoons of oil 5 tablespoons of popcorn kernels 5 tablespoons of sugar 3 tablespoons of water 1 tablespoon of cocoa powder") -> 5 tablespoons of oil 5 tablespoons of popcorn kernels 5 tablespoons of sugar 3 tablespoons of water 1 tablespoon of cocoa powder | D72: =IFERROR(__xludf.DUMMYFUNCTION("GOOGLETRANSLATE(Portuguese!D72,""pt"",""en"")"),"In a saucepan, add all the ingredients and mix gently. Turn off the heat when the time between poppings decreases. It's ready to eat.") -> In a saucepan, add all the ingredients and mix gently. Turn off the heat when the time between poppings decreases. It's ready to eat. | E72: https://www.tudogostoso.com.br/receita/7269-pipoca-doce.html
A73: 71 | B73: =IFERROR(__xludf.DUMMYFUNCTION("GOOGLETRANSLATE(Portuguese!B73,""pt"",""en"")"),"Cheese bread with 3 ingredients") -> Cheese bread with 3 ingredients | C73: =IFERROR(__xludf.DUMMYFUNCTION("GOOGLETRANSLATE(Portuguese!C73,""pt"",""en"")"),"1 carton of heavy cream (200 ml) 1 cup (cream cheese container) of grated cheese 1 cup (cream cheese container) of tapioca starch") -> 1 carton of heavy cream (200 ml) 1 cup (cream cheese container) of grated cheese 1 cup (cream cheese container) of tapioca starch | D73: =IFERROR(__xludf.DUMMYFUNCTION("GOOGLETRANSLATE(Portuguese!D73,""pt"",""en"")"),"Knead until the dough no longer sticks to your hands (if you need a little more tapioca starch, add it gradually until it reaches the point where you can roll it). Make small balls, place them on a greased baking sheet, and bake in a preheated oven at a h"&"igh temperature. Add salt if necessary. Bake until lightly golden brown.") -> Knead until the dough no longer sticks to your hands (if you need a little more tapioca starch, add it gradually until it reaches the point where you can roll it). Make small balls, place them on a greased baking sheet, and bake in a preheated oven at a high temperature. Add salt if necessary. Bake until lightly golden brown. | E73: https://www.tudogostoso.com.br/receita/79996-pao-de-queijo-3-ingredientes.html
A74: 72 | B74: =IFERROR(__xludf.DUMMYFUNCTION("GOOGLETRANSLATE(Portuguese!B74,""pt"",""en"")"),"Rice in a mold") -> Rice in a mold | C74: =IFERROR(__xludf.DUMMYFUNCTION("GOOGLETRANSLATE(Portuguese!C74,""pt"",""en"")"),"4 cups of rice 1 cup of creamy cheese spread 1 can of heavy cream 1 chicken breast Onion Garlic Corn and peas to taste Sliced ​​mozzarella cheese Sliced ​​ham 1 package of potato sticks") -> 4 cups of rice 1 cup of creamy cheese spread 1 can of heavy cream 1 chicken breast Onion Garlic Corn and peas to taste Sliced ​​mozzarella cheese Sliced ​​ham 1 package of potato sticks | D74: =IFERROR(__xludf.DUMMYFUNCTION("GOOGLETRANSLATE(Portuguese!D74,""pt"",""en"")"),"Cook the rice and set aside. Cook the chicken breast, shred it, and sauté it with the onion, garlic, corn, and peas. If desired, add tomato sauce; the idea is to make a sauce. Then, in a medium baking dish, assemble the dish. First, place the rice, then t"&"he cream and spread it out. Next, place the chicken in the sauce and spread it out. Add the creamy cheese, ham, cheese, and finally the potato sticks. Place in a preheated oven for 15 minutes.") -> Cook the rice and set aside. Cook the chicken breast, shred it, and sauté it with the onion, garlic, corn, and peas. If desired, add tomato sauce; the idea is to make a sauce. Then, in a medium baking dish, assemble the dish. First, place the rice, then the cream and spread it out. Next, place the chicken in the sauce and spread it out. Add the creamy cheese, ham, cheese, and finally the potato sticks. Place in a preheated oven for 15 minutes. | E74: https://www.tudogostoso.com.br/receita/114041-arroz-de-forma.html
A75: 73 | B75: =IFERROR(__xludf.DUMMYFUNCTION("GOOGLETRANSLATE(Portuguese!B75,""pt"",""en"")"),"Chocolate mousse") -> Chocolate mousse | C75: =IFERROR(__xludf.DUMMYFUNCTION("GOOGLETRANSLATE(Portuguese!C75,""pt"",""en"")"),"3 eggs 200g semi-sweet chocolate 2 tablespoons sugar 1 can of heavy cream") -> 3 eggs 200g semi-sweet chocolate 2 tablespoons sugar 1 can of heavy cream | D75: =IFERROR(__xludf.DUMMYFUNCTION("GOOGLETRANSLATE(Portuguese!D75,""pt"",""en"")"),"Beat the egg yolks until they double in volume. Add the sugar and continue beating. Melt the chocolate and add it to the egg yolk mixture. Add the heavy cream, beating constantly. Finally, add the beaten egg whites (very well beaten), mixing quickly with "&"the mixer. Refrigerate and serve, enjoying the best and simplest mousse to make!") -> Beat the egg yolks until they double in volume. Add the sugar and continue beating. Melt the chocolate and add it to the egg yolk mixture. Add the heavy cream, beating constantly. Finally, add the beaten egg whites (very well beaten), mixing quickly with the mixer. Refrigerate and serve, enjoying the best and simplest mousse to make! | E75: https://www.tudogostoso.com.br/receita/2513-mousse-de-chocolate.html
A76: 74 | B76: =IFERROR(__xludf.DUMMYFUNCTION("GOOGLETRANSLATE(Portuguese!B76,""pt"",""en"")"),"Shrimp bobó") -> Shrimp bobó | C76: =IFERROR(__xludf.DUMMYFUNCTION("GOOGLETRANSLATE(Portuguese!C76,""pt"",""en"")"),"1 kg of fresh shrimp Salt 3 cloves of garlic, chopped and crushed Juice of 1 lemon Black pepper 1 kg of cassava (preferably pre-packaged and peeled, it's more practical) 3 onions (1 sliced ​​and 2 grated) 1 bay leaf 6 tablespoons of olive oil 2 bottles of"&" coconut milk 1 bunch of chopped parsley and cilantro 2 cans of ready-made tomato sauce 2 finely chopped green bell peppers 2 tablespoons of palm oil") -> 1 kg of fresh shrimp Salt 3 cloves of garlic, chopped and crushed Juice of 1 lemon Black pepper 1 kg of cassava (preferably pre-packaged and peeled, it's more practical) 3 onions (1 sliced ​​and 2 grated) 1 bay leaf 6 tablespoons of olive oil 2 bottles of coconut milk 1 bunch of chopped parsley and cilantro 2 cans of ready-made tomato sauce 2 finely chopped green bell peppers 2 tablespoons of palm oil | D76: =IFERROR(__xludf.DUMMYFUNCTION("GOOGLETRANSLATE(Portuguese!D76,""pt"",""en"")"),"Wash the shrimp and season with salt, garlic, pepper, and lemon; let marinate. Take a pot with water and cook the cassava in small pieces, with bay leaf and sliced ​​onion. When it is soft, add a can of coconut milk. Let it cool a little and blend in a bl"&"ender. Heat the olive oil, add the grated onion and let it brown. Add the shrimp and fry. Add the 2 cans of tomato sauce, the green onions, the bell pepper, and let it cook for a few minutes. In the same pot, add the blended cassava, another can of coconu"&"t milk, and the palm oil. Let it come to a boil and it's ready.") -> Wash the shrimp and season with salt, garlic, pepper, and lemon; let marinate. Take a pot with water and cook the cassava in small pieces, with bay leaf and sliced ​​onion. When it is soft, add a can of coconut milk. Let it cool a little and blend in a blender. Heat the olive oil, add the grated onion and let it brown. Add the shrimp and fry. Add the 2 cans of tomato sauce, the green onions, the bell pepper, and let it cook for a few minutes. In the same pot, add the blended cassava, another can of coconut milk, and the palm oil. Let it come to a boil and it's ready. | E76: https://www.tudogostoso.com.br/receita/112-bobo-de-camarao.html
A77: 75 | B77: =IFERROR(__xludf.DUMMYFUNCTION("GOOGLETRANSLATE(Portuguese!B77,""pt"",""en"")"),"Pancake") -> Pancake | C77: =IFERROR(__xludf.DUMMYFUNCTION("GOOGLETRANSLATE(Portuguese!C77,""pt"",""en"")"),"1 egg 1 cup of milk 1 cup of wheat flour 1 pinch of salt 1 pinch of baking powder") -> 1 egg 1 cup of milk 1 cup of wheat flour 1 pinch of salt 1 pinch of baking powder | D77: =IFERROR(__xludf.DUMMYFUNCTION("GOOGLETRANSLATE(Portuguese!D77,""pt"",""en"")"),"Blend all ingredients in a blender until smooth. Then, fry in a skillet over medium heat. Fill as desired.") -> Blend all ingredients in a blender until smooth. Then, fry in a skillet over medium heat. Fill as desired. | E77: https://www.tudogostoso.com.br/receita/4255-panqueca.html
A78: 76 | B78: =IFERROR(__xludf.DUMMYFUNCTION("GOOGLETRANSLATE(Portuguese!B78,""pt"",""en"")"),"Carrot cake with melt-in-your-mouth chocolate frosting") -> Carrot cake with melt-in-your-mouth chocolate frosting | C78: =IFERROR(__xludf.DUMMYFUNCTION("GOOGLETRANSLATE(Portuguese!C78,""pt"",""en"")"),"2 cups chopped raw carrots 1 cup sugar 1 cup oil 4 eggs 1/2 teaspoon salt 2 cups all-purpose flour 1 heaping tablespoon baking powder 3 tablespoons Nesquik (chocolate powder) 1 1/2 sticks margarine 12 tablespoons sugar 10 tablespoons milk") -> 2 cups chopped raw carrots 1 cup sugar 1 cup oil 4 eggs 1/2 teaspoon salt 2 cups all-purpose flour 1 heaping tablespoon baking powder 3 tablespoons Nesquik (chocolate powder) 1 1/2 sticks margarine 12 tablespoons sugar 10 tablespoons milk | D78: =IFERROR(__xludf.DUMMYFUNCTION("GOOGLETRANSLATE(Portuguese!D78,""pt"",""en"")"),"Blend all ingredients in a blender, except for the flour and baking powder. Then, in a large bowl, mix the blended mixture well with the flour and baking powder. Pour into a baking pan greased with butter and dusted with sugar or flour. Bake in a preheate"&"d oven at 180°C (350°F) for about 40 minutes, or until golden brown. Mix all ingredients and bring to a boil. Make small holes in the still-warm cake and pour the mixture over it.") -> Blend all ingredients in a blender, except for the flour and baking powder. Then, in a large bowl, mix the blended mixture well with the flour and baking powder. Pour into a baking pan greased with butter and dusted with sugar or flour. Bake in a preheated oven at 180°C (350°F) for about 40 minutes, or until golden brown. Mix all ingredients and bring to a boil. Make small holes in the still-warm cake and pour the mixture over it. | E78: https://www.tudogostoso.com.br/receita/59066-bolo-de-cenoura-com-calda-de-chocolate-que-derrete-na-boca.html
A79: 77 | B79: =IFERROR(__xludf.DUMMYFUNCTION("GOOGLETRANSLATE(Portuguese!B79,""pt"",""en"")"),"Petit gateau") -> Petit gateau | C79: =IFERROR(__xludf.DUMMYFUNCTION("GOOGLETRANSLATE(Portuguese!C79,""pt"",""en"")"),"200g semi-sweet chocolate 2 tablespoons unsalted butter 1/4 cup sugar 2 level tablespoons all-purpose flour 2 whole eggs (remove the membrane from the yolks) 2 egg yolks") -> 200g semi-sweet chocolate 2 tablespoons unsalted butter 1/4 cup sugar 2 level tablespoons all-purpose flour 2 whole eggs (remove the membrane from the yolks) 2 egg yolks | D79: =IFERROR(__xludf.DUMMYFUNCTION("GOOGLETRANSLATE(Portuguese!D79,""pt"",""en"")"),"Melt the butter and chocolate in a double boiler. Beat the eggs and yolks with sugar in a mixer until very light. Add the melted chocolate and wheat flour, mixing with a spatula. Then, grease the mini tartlet molds, dust with wheat flour, and pour in the "&"batter. Preheat the oven and bake for 6 to 10 minutes (on high heat) until the cakes rise, but the center should remain soft. Unmold while still warm. Serve directly on a plate, accompanied by vanilla ice cream.") -> Melt the butter and chocolate in a double boiler. Beat the eggs and yolks with sugar in a mixer until very light. Add the melted chocolate and wheat flour, mixing with a spatula. Then, grease the mini tartlet molds, dust with wheat flour, and pour in the batter. Preheat the oven and bake for 6 to 10 minutes (on high heat) until the cakes rise, but the center should remain soft. Unmold while still warm. Serve directly on a plate, accompanied by vanilla ice cream. | E79: https://www.tudogostoso.com.br/receita/6179-petit-gateau.html
A80: 78 | B80: =IFERROR(__xludf.DUMMYFUNCTION("GOOGLETRANSLATE(Portuguese!B80,""pt"",""en"")"),"Chocolate dessert") -> Chocolate dessert | C80: =IFERROR(__xludf.DUMMYFUNCTION("GOOGLETRANSLATE(Portuguese!C80,""pt"",""en"")"),"250g milk chocolate 250g semi-sweet chocolate 2 cans sweetened condensed milk 2 cans heavy cream 2 tablespoons margarine 2 boxes of strawberries") -> 250g milk chocolate 250g semi-sweet chocolate 2 cans sweetened condensed milk 2 cans heavy cream 2 tablespoons margarine 2 boxes of strawberries | D80: =IFERROR(__xludf.DUMMYFUNCTION("GOOGLETRANSLATE(Portuguese!D80,""pt"",""en"")"),"Place the cans of condensed milk in a saucepan with the butter and make a soft brigadeiro-like consistency. Place in a serving dish and, on top of this soft brigadeiro, place the strawberries cut in half. Set aside to make the topping. To make the topping"&", grate the milk chocolate and the semi-sweet chocolate and mix with the heavy cream. Mix and microwave for 1 minute. Remove and stir. Microwave again for another minute. Pour the topping over the strawberries and refrigerate, covered with plastic wrap.") -> Place the cans of condensed milk in a saucepan with the butter and make a soft brigadeiro-like consistency. Place in a serving dish and, on top of this soft brigadeiro, place the strawberries cut in half. Set aside to make the topping. To make the topping, grate the milk chocolate and the semi-sweet chocolate and mix with the heavy cream. Mix and microwave for 1 minute. Remove and stir. Microwave again for another minute. Pour the topping over the strawberries and refrigerate, covered with plastic wrap. | E80: https://www.tudogostoso.com.br/receita/49802-bombom-de-travessa.html
A81: 79 | B81: =IFERROR(__xludf.DUMMYFUNCTION("GOOGLETRANSLATE(Portuguese!B81,""pt"",""en"")"),"Microwave Brigadeirão") -> Microwave Brigadeirão | C81: =IFERROR(__xludf.DUMMYFUNCTION("GOOGLETRANSLATE(Portuguese!C81,""pt"",""en"")"),"1 can of sweetened condensed milk 1 can of heavy cream 1 cup of cocoa powder 1 tablespoon of margarine 3 whole eggs Chocolate sprinkles for decoration") -> 1 can of sweetened condensed milk 1 can of heavy cream 1 cup of cocoa powder 1 tablespoon of margarine 3 whole eggs Chocolate sprinkles for decoration | D81: =IFERROR(__xludf.DUMMYFUNCTION("GOOGLETRANSLATE(Portuguese!D81,""pt"",""en"")"),"Place all ingredients in a blender and blend well until doubled in volume. Pour the batter into a greased round pan with a hole in the center and microwave for 10 minutes. After removing from the microwave, decorate with chocolate sprinkles and enjoy!") -> Place all ingredients in a blender and blend well until doubled in volume. Pour the batter into a greased round pan with a hole in the center and microwave for 10 minutes. After removing from the microwave, decorate with chocolate sprinkles and enjoy! | E81: https://www.tudogostoso.com.br/receita/3623-brigadeirao-de-micro-ondas.html
A82: 80 | B82: =IFERROR(__xludf.DUMMYFUNCTION("GOOGLETRANSLATE(Portuguese!B82,""pt"",""en"")"),"Perfect American cookie") -> Perfect American cookie | C82: =IFERROR(__xludf.DUMMYFUNCTION("GOOGLETRANSLATE(Portuguese!C82,""pt"",""en"")"),"125g unsalted butter at room temperature 3/4 cup sugar 1/2 cup brown sugar 1 egg 1 3/4 cups all-purpose flour 1 teaspoon baking powder 300g chopped semi-sweet chocolate 1 teaspoon vanilla extract To make chocolate chip cookies, add 1/4 cup cocoa powder") -> 125g unsalted butter at room temperature 3/4 cup sugar 1/2 cup brown sugar 1 egg 1 3/4 cups all-purpose flour 1 teaspoon baking powder 300g chopped semi-sweet chocolate 1 teaspoon vanilla extract To make chocolate chip cookies, add 1/4 cup cocoa powder | D82: =IFERROR(__xludf.DUMMYFUNCTION("GOOGLETRANSLATE(Portuguese!D82,""pt"",""en"")"),"Mix the butter, brown sugar, sugar, vanilla extract (and cocoa powder, if making chocolate-based cookies). Add the beaten egg gradually and mix well. Add the flour gradually and mix well (you can do this by hand or with a stand mixer). Finally, add the ba"&"king powder and mix just to incorporate it into the dough. After the dough is well mixed, add the chopped chocolate. Form small balls and bake in a preheated oven, on parchment paper, for approximately 15 to 20 minutes (250°C).") -> Mix the butter, brown sugar, sugar, vanilla extract (and cocoa powder, if making chocolate-based cookies). Add the beaten egg gradually and mix well. Add the flour gradually and mix well (you can do this by hand or with a stand mixer). Finally, add the baking powder and mix just to incorporate it into the dough. After the dough is well mixed, add the chopped chocolate. Form small balls and bake in a preheated oven, on parchment paper, for approximately 15 to 20 minutes (250°C). | E82: https://www.tudogostoso.com.br/receita/94434-cookie-americano-perfeito.html
A83: 81 | B83: =IFERROR(__xludf.DUMMYFUNCTION("GOOGLETRANSLATE(Portuguese!B83,""pt"",""en"")"),"Corn cake") -> Corn cake | C83: =IFERROR(__xludf.DUMMYFUNCTION("GOOGLETRANSLATE(Portuguese!C83,""pt"",""en"")"),"Measuring cup (using a cream cheese container): 1/2 cup of oil 1 cup of milk 1 can of sweet corn with its liquid 3 eggs 1 1/2 cups of sugar 1 cup of cornmeal 1 tablespoon of baking powder") -> Measuring cup (using a cream cheese container): 1/2 cup of oil 1 cup of milk 1 can of sweet corn with its liquid 3 eggs 1 1/2 cups of sugar 1 cup of cornmeal 1 tablespoon of baking powder | D83: =IFERROR(__xludf.DUMMYFUNCTION("GOOGLETRANSLATE(Portuguese!D83,""pt"",""en"")"),"Blend all ingredients in a blender. Bake in a greased pan until golden brown. It will be slightly moist. It's delicious.") -> Blend all ingredients in a blender. Bake in a greased pan until golden brown. It will be slightly moist. It's delicious. | E83: https://www.tudogostoso.com.br/receita/1650-bolo-de-milho.html
A84: 82 | B84: =IFERROR(__xludf.DUMMYFUNCTION("GOOGLETRANSLATE(Portuguese!B84,""pt"",""en"")"),"Blender orange cake") -> Blender orange cake | C84: =IFERROR(__xludf.DUMMYFUNCTION("GOOGLETRANSLATE(Portuguese!C84,""pt"",""en"")"),"3 eggs Juice of 2 oranges 1 cup of oil 2 cups of sugar 3 cups of wheat flour 1 tablespoon of baking powder Juice of 1 orange 3 tablespoons of sugar") -> 3 eggs Juice of 2 oranges 1 cup of oil 2 cups of sugar 3 cups of wheat flour 1 tablespoon of baking powder Juice of 1 orange 3 tablespoons of sugar | D84: =IFERROR(__xludf.DUMMYFUNCTION("GOOGLETRANSLATE(Portuguese!D84,""pt"",""en"")"),"Blend the first 4 ingredients (except flour and baking powder) in a blender, pour into a bowl, gradually add the wheat flour and finally the baking powder. Place in a greased and floured round bundt pan. Bake in a preheated medium oven for 35 minutes, or "&"until cooked through. Heat the orange juice and sugar over low heat, then pour over the still-warm cake.") -> Blend the first 4 ingredients (except flour and baking powder) in a blender, pour into a bowl, gradually add the wheat flour and finally the baking powder. Place in a greased and floured round bundt pan. Bake in a preheated medium oven for 35 minutes, or until cooked through. Heat the orange juice and sugar over low heat, then pour over the still-warm cake. | E84: https://www.tudogostoso.com.br/receita/85429-bolo-de-laranja-de-liquidificador.html
A85: 83 | B85: =IFERROR(__xludf.DUMMYFUNCTION("GOOGLETRANSLATE(Portuguese!B85,""pt"",""en"")"),"Simple and easy mashed potatoes") -> Simple and easy mashed potatoes | C85: =IFERROR(__xludf.DUMMYFUNCTION("GOOGLETRANSLATE(Portuguese!C85,""pt"",""en"")"),"1 kg of potatoes 1/2 cup of milk 2 tablespoons of margarine Salt to taste 1 clove of garlic, crushed") -> 1 kg of potatoes 1/2 cup of milk 2 tablespoons of margarine Salt to taste 1 clove of garlic, crushed | D85: =IFERROR(__xludf.DUMMYFUNCTION("GOOGLETRANSLATE(Portuguese!D85,""pt"",""en"")"),"Cook the potatoes until very soft. Peel them while still hot and mash them using a potato ricer. Pour the potatoes into a bowl and add the margarine, salt, and garlic, stirring until the margarine is completely melted. Add the milk gradually and continue"&" stirring.") -> Cook the potatoes until very soft. Peel them while still hot and mash them using a potato ricer. Pour the potatoes into a bowl and add the margarine, salt, and garlic, stirring until the margarine is completely melted. Add the milk gradually and continue stirring. | E85: https://www.tudogostoso.com.br/receita/59-pure-de-batata.html
A86: 84 | B86: =IFERROR(__xludf.DUMMYFUNCTION("GOOGLETRANSLATE(Portuguese!B86,""pt"",""en"")"),"Chicken with creamed corn") -> Chicken with creamed corn | C86: =IFERROR(__xludf.DUMMYFUNCTION("GOOGLETRANSLATE(Portuguese!C86,""pt"",""en"")"),"1 cooked and shredded chicken breast Olive oil to taste 1/2 chopped onion 2 crushed garlic cloves Salt 1/2 container of cream cheese Black pepper to taste 1 can of drained sweet corn 1 can of milk 1 tablespoon of cornstarch 1 chicken bouillon cube 2 crush"&"ed garlic cloves 1/2 chopped onion Olive oil as needed Grated cheese for sprinkling") -> 1 cooked and shredded chicken breast Olive oil to taste 1/2 chopped onion 2 crushed garlic cloves Salt 1/2 container of cream cheese Black pepper to taste 1 can of drained sweet corn 1 can of milk 1 tablespoon of cornstarch 1 chicken bouillon cube 2 crushed garlic cloves 1/2 chopped onion Olive oil as needed Grated cheese for sprinkling | D86: =IFERROR(__xludf.DUMMYFUNCTION("GOOGLETRANSLATE(Portuguese!D86,""pt"",""en"")"),"In a saucepan, sauté the onion and garlic in olive oil. Add the chicken and season to taste. Incorporate the cream cheese. Blend the corn, milk, cornstarch, and chicken broth in a blender. In a saucepan, sauté the onion and garlic in olive oil. Incorporat"&"e the blended mixture, stirring until bubbling. Arrange the chicken in a baking dish, top with the corn cream. Cover with grated cheese and bake in a hot oven for about 30 minutes, or until golden brown.") -> In a saucepan, sauté the onion and garlic in olive oil. Add the chicken and season to taste. Incorporate the cream cheese. Blend the corn, milk, cornstarch, and chicken broth in a blender. In a saucepan, sauté the onion and garlic in olive oil. Incorporate the blended mixture, stirring until bubbling. Arrange the chicken in a baking dish, top with the corn cream. Cover with grated cheese and bake in a hot oven for about 30 minutes, or until golden brown. | E86: https://www.tudogostoso.com.br/receita/91302-frango-ao-creme-de-milho.html
A87: 85 | B87: =IFERROR(__xludf.DUMMYFUNCTION("GOOGLETRANSLATE(Portuguese!B87,""pt"",""en"")"),"Homemade Yakisoba") -> Homemade Yakisoba | C87: =IFERROR(__xludf.DUMMYFUNCTION("GOOGLETRANSLATE(Portuguese!C87,""pt"",""en"")"),"300g spaghetti 1 large onion, cut into medium pieces 1 tablespoon oil 1/2 small bunch of broccoli 1/2 small bunch of cauliflower 10 tablespoons soy sauce 400g beef, cut into strips 100g mushrooms 1 carrot, sliced 250ml water 1 tablespoon cornstarch, disso"&"lved in 50ml water Chard to taste") -> 300g spaghetti 1 large onion, cut into medium pieces 1 tablespoon oil 1/2 small bunch of broccoli 1/2 small bunch of cauliflower 10 tablespoons soy sauce 400g beef, cut into strips 100g mushrooms 1 carrot, sliced 250ml water 1 tablespoon cornstarch, dissolved in 50ml water Chard to taste | D87: =IFERROR(__xludf.DUMMYFUNCTION("GOOGLETRANSLATE(Portuguese!D87,""pt"",""en"")"),"Cook the pasta until al dente and set aside. In a pan, add the olive oil, onion, and meat and sauté well. Add the soy sauce and cook for 3 minutes over medium heat. Add more water, wait for it to boil, and add the cornstarch. Stir until thickened, reduce "&"the heat, and add the mushrooms, cauliflower, broccoli, and carrots. Cook for 8 minutes and finally add the bok choy and pasta. Mix well, adjust the salt, and cover the pan for 1 more minute. It's ready to serve!") -> Cook the pasta until al dente and set aside. In a pan, add the olive oil, onion, and meat and sauté well. Add the soy sauce and cook for 3 minutes over medium heat. Add more water, wait for it to boil, and add the cornstarch. Stir until thickened, reduce the heat, and add the mushrooms, cauliflower, broccoli, and carrots. Cook for 8 minutes and finally add the bok choy and pasta. Mix well, adjust the salt, and cover the pan for 1 more minute. It's ready to serve! | E87: https://www.tudogostoso.com.br/receita/2085-yakissoba-da-casa.html
A88: 86 | B88: =IFERROR(__xludf.DUMMYFUNCTION("GOOGLETRANSLATE(Portuguese!B88,""pt"",""en"")"),"Lemon pie") -> Lemon pie | C88: =IFERROR(__xludf.DUMMYFUNCTION("GOOGLETRANSLATE(Portuguese!C88,""pt"",""en"")"),"200g cornstarch cookies 150g margarine 1 can sweetened condensed milk (395g) 1 carton heavy cream (200g) Juice of 4 lemons Zest of 2 lemons 3 or 4 egg whites 3 tablespoons sugar Zest of 2 lemons for decoration") -> 200g cornstarch cookies 150g margarine 1 can sweetened condensed milk (395g) 1 carton heavy cream (200g) Juice of 4 lemons Zest of 2 lemons 3 or 4 egg whites 3 tablespoons sugar Zest of 2 lemons for decoration | D88: =IFERROR(__xludf.DUMMYFUNCTION("GOOGLETRANSLATE(Portuguese!D88,""pt"",""en"")"),"Crush the cornstarch cookies in a blender or food processor. Add the margarine and blend a little more. Pour the mixture into a removable-bottom pan (27 cm in diameter). With your hands, spread the crushed cookies on the bottom and sides of the pan, cover"&"ing the entire area evenly. Bake in a preheated medium oven (180°C) for approximately 10 minutes. Blend all the ingredients in a blender (except the lemon zest) until you obtain a smooth and firm cream. Fill the already baked crust and refrigerate for 30 "&"minutes. Beat the egg whites until stiff peaks form and add the sugar. Mix until you obtain a meringue consistency and bake until golden brown. Unmold the tart (without removing the false bottom), pour the topping and add the lemon zest.") -> Crush the cornstarch cookies in a blender or food processor. Add the margarine and blend a little more. Pour the mixture into a removable-bottom pan (27 cm in diameter). With your hands, spread the crushed cookies on the bottom and sides of the pan, covering the entire area evenly. Bake in a preheated medium oven (180°C) for approximately 10 minutes. Blend all the ingredients in a blender (except the lemon zest) until you obtain a smooth and firm cream. Fill the already baked crust and refrigerate for 30 minutes. Beat the egg whites until stiff peaks form and add the sugar. Mix until you obtain a meringue consistency and bake until golden brown. Unmold the tart (without removing the false bottom), pour the topping and add the lemon zest. | E88: https://www.tudogostoso.com.br/receita/104383-torta-de-limao.html
A89: 87 | B89: =IFERROR(__xludf.DUMMYFUNCTION("GOOGLETRANSLATE(Portuguese!B89,""pt"",""en"")"),"Microwave Brigadeiro") -> Microwave Brigadeiro | C89: =IFERROR(__xludf.DUMMYFUNCTION("GOOGLETRANSLATE(Portuguese!C89,""pt"",""en"")"),"1 can of sweetened condensed milk 4 tablespoons of cocoa powder or chocolate powder 1 tablespoon of butter Chocolate sprinkles or colored sprinkles") -> 1 can of sweetened condensed milk 4 tablespoons of cocoa powder or chocolate powder 1 tablespoon of butter Chocolate sprinkles or colored sprinkles | D89: =IFERROR(__xludf.DUMMYFUNCTION("GOOGLETRANSLATE(Portuguese!D89,""pt"",""en"")"),"In a microwave-safe bowl, preferably round and with high sides, mix all the ingredients. Microwave for 6 minutes on high power or using the ""brigadeiro"" setting on your microwave. Stir the mixture halfway through. Once cooked, remove from the oven and s"&"tir until the mixture is smooth and shiny. Refrigerate to cool, then roll the candies, coat them in sprinkles, and place them in paper cups.") -> In a microwave-safe bowl, preferably round and with high sides, mix all the ingredients. Microwave for 6 minutes on high power or using the "brigadeiro" setting on your microwave. Stir the mixture halfway through. Once cooked, remove from the oven and stir until the mixture is smooth and shiny. Refrigerate to cool, then roll the candies, coat them in sprinkles, and place them in paper cups. | E89: https://www.tudogostoso.com.br/receita/456-brigadeiro-de-micro-ondas.html
A90: 88 | B90: =IFERROR(__xludf.DUMMYFUNCTION("GOOGLETRANSLATE(Portuguese!B90,""pt"",""en"")"),"Cheese ball") -> Cheese ball | C90: =IFERROR(__xludf.DUMMYFUNCTION("GOOGLETRANSLATE(Portuguese!C90,""pt"",""en"")"),"1 cup (tea) of milk 1 cup (tea) of wheat flour 1 tablespoon of margarine 1 egg yolk 1 pinch of salt white cheese or mozzarella to taste oil for frying") -> 1 cup (tea) of milk 1 cup (tea) of wheat flour 1 tablespoon of margarine 1 egg yolk 1 pinch of salt white cheese or mozzarella to taste oil for frying | D90: =IFERROR(__xludf.DUMMYFUNCTION("GOOGLETRANSLATE(Portuguese!D90,""pt"",""en"")"),"In a saucepan, add the milk, wheat flour, margarine, egg yolk, and salt. Cook over low heat and stir with a fork until the dough comes away from the sides of the pan, then let it cool. Shape the dough into small balls and fill with cheese, then coat the b"&"alls in egg yolk and breadcrumbs. In a pan, add the oil, and once hot, add the balls and fry them.") -> In a saucepan, add the milk, wheat flour, margarine, egg yolk, and salt. Cook over low heat and stir with a fork until the dough comes away from the sides of the pan, then let it cool. Shape the dough into small balls and fill with cheese, then coat the balls in egg yolk and breadcrumbs. In a pan, add the oil, and once hot, add the balls and fry them. | E90: https://www.tudogostoso.com.br/receita/2082-bolinha-de-queijo.html
A91: 89 | B91: =IFERROR(__xludf.DUMMYFUNCTION("GOOGLETRANSLATE(Portuguese!B91,""pt"",""en"")"),"Easy ice cream") -> Easy ice cream | C91: =IFERROR(__xludf.DUMMYFUNCTION("GOOGLETRANSLATE(Portuguese!C91,""pt"",""en"")"),"1 can of sweetened condensed milk 1 can of heavy cream 1 packet of gelatin (any flavor)") -> 1 can of sweetened condensed milk 1 can of heavy cream 1 packet of gelatin (any flavor) | D91: =IFERROR(__xludf.DUMMYFUNCTION("GOOGLETRANSLATE(Portuguese!D91,""pt"",""en"")"),"Prepare the gelatin as usual and do not refrigerate. Once ready, while still hot, place it in a blender along with the condensed milk and heavy cream. Blend well. Then place it in a covered container in the freezer to prevent ice crystals from forming. On"&"ce frozen, remove from the freezer and beat in a mixer until creamy. Return to the freezer. It's ready, an easy, practical and delicious ice cream.") -> Prepare the gelatin as usual and do not refrigerate. Once ready, while still hot, place it in a blender along with the condensed milk and heavy cream. Blend well. Then place it in a covered container in the freezer to prevent ice crystals from forming. Once frozen, remove from the freezer and beat in a mixer until creamy. Return to the freezer. It's ready, an easy, practical and delicious ice cream. | E91: https://www.tudogostoso.com.br/receita/4730-sorvete-facil.html
A92: 90 | B92: =IFERROR(__xludf.DUMMYFUNCTION("GOOGLETRANSLATE(Portuguese!B92,""pt"",""en"")"),"Homemade condensed milk") -> Homemade condensed milk | C92: =IFERROR(__xludf.DUMMYFUNCTION("GOOGLETRANSLATE(Portuguese!C92,""pt"",""en"")"),"1 cup of powdered milk 1 cup of granulated sugar 1/2 cup of boiling water") -> 1 cup of powdered milk 1 cup of granulated sugar 1/2 cup of boiling water | D92: =IFERROR(__xludf.DUMMYFUNCTION("GOOGLETRANSLATE(Portuguese!D92,""pt"",""en"")"),"Place the boiling water, powdered milk, and sugar in a blender. Blend until it reaches the consistency of condensed milk. Yield: 340g.") -> Place the boiling water, powdered milk, and sugar in a blender. Blend until it reaches the consistency of condensed milk. Yield: 340g. | E92: https://www.tudogostoso.com.br/receita/2921-leite-condensado-caseiro.html
A93: 91 | B93: =IFERROR(__xludf.DUMMYFUNCTION("GOOGLETRANSLATE(Portuguese!B93,""pt"",""en"")"),"Milk pudding") -> Milk pudding | C93: =IFERROR(__xludf.DUMMYFUNCTION("GOOGLETRANSLATE(Portuguese!C93,""pt"",""en"")"),"3 eggs 1 can of sweetened condensed milk 1 can of milk (using the sweetened condensed milk can as a measure) 3 tablespoons of sugar") -> 3 eggs 1 can of sweetened condensed milk 1 can of milk (using the sweetened condensed milk can as a measure) 3 tablespoons of sugar | D93: =IFERROR(__xludf.DUMMYFUNCTION("GOOGLETRANSLATE(Portuguese!D93,""pt"",""en"")"),"Turn the oven on to preheat for 10 minutes on low heat. In a blender, beat the eggs, sweetened condensed milk, and milk for 3 minutes. Make a caramel with the sugar and let it cool slightly. Pour the caramel into a bundt pan, then pour the pudding mixture"&" over the caramel. Bake in the oven (no need for a water bath) until golden brown on top, about 40 minutes. Let it cool and refrigerate (it's best to make it the day before).") -> Turn the oven on to preheat for 10 minutes on low heat. In a blender, beat the eggs, sweetened condensed milk, and milk for 3 minutes. Make a caramel with the sugar and let it cool slightly. Pour the caramel into a bundt pan, then pour the pudding mixture over the caramel. Bake in the oven (no need for a water bath) until golden brown on top, about 40 minutes. Let it cool and refrigerate (it's best to make it the day before). | E93: https://www.tudogostoso.com.br/receita/1045-pudim-de-leite-moca.html
A94: 92 | B94: =IFERROR(__xludf.DUMMYFUNCTION("GOOGLETRANSLATE(Portuguese!B94,""pt"",""en"")"),"Ground beef casserole") -> Ground beef casserole | C94: =IFERROR(__xludf.DUMMYFUNCTION("GOOGLETRANSLATE(Portuguese!C94,""pt"",""en"")"),"1 kg of potatoes 500 g of ground beef 200 g of mozzarella cheese olive oil 1 onion 1 clove of crushed garlic salt to taste white pepper to taste parsley to taste 1/2 cup of milk 2 tablespoons of butter") -> 1 kg of potatoes 500 g of ground beef 200 g of mozzarella cheese olive oil 1 onion 1 clove of crushed garlic salt to taste white pepper to taste parsley to taste 1/2 cup of milk 2 tablespoons of butter | D94: =IFERROR(__xludf.DUMMYFUNCTION("GOOGLETRANSLATE(Portuguese!D94,""pt"",""en"")"),"Peel the potatoes, cut them in half, and cook them in salted water. Once cooked, mash the potatoes, add the milk and butter, mix well until a puree forms, and set aside. In a pan, add a drizzle of olive oil, the onion, the garlic, and sauté the ground bee"&"f. Season with salt, white pepper, and parsley, and cook until the water that forms in the pan evaporates. Line a baking dish with half of the mashed potatoes. Add a layer of cheese and a layer of ground beef. Repeat the process and finish with grated che"&"ese on top. Bake for 40 minutes.") -> Peel the potatoes, cut them in half, and cook them in salted water. Once cooked, mash the potatoes, add the milk and butter, mix well until a puree forms, and set aside. In a pan, add a drizzle of olive oil, the onion, the garlic, and sauté the ground beef. Season with salt, white pepper, and parsley, and cook until the water that forms in the pan evaporates. Line a baking dish with half of the mashed potatoes. Add a layer of cheese and a layer of ground beef. Repeat the process and finish with grated cheese on top. Bake for 40 minutes. | E94: https://www.tudogostoso.com.br/receita/136814-escondidinho-de-carne-moida.html
A95: 93 | B95: =IFERROR(__xludf.DUMMYFUNCTION("GOOGLETRANSLATE(Portuguese!B95,""pt"",""en"")"),"Raindrop fritters") -> Raindrop fritters | C95: =IFERROR(__xludf.DUMMYFUNCTION("GOOGLETRANSLATE(Portuguese!C95,""pt"",""en"")"),"1 cup all-purpose flour 1 cup cornstarch 1/2 cup milk 2 eggs 4 tablespoons sugar 1 tablespoon baking powder") -> 1 cup all-purpose flour 1 cup cornstarch 1/2 cup milk 2 eggs 4 tablespoons sugar 1 tablespoon baking powder | D95: =IFERROR(__xludf.DUMMYFUNCTION("GOOGLETRANSLATE(Portuguese!D95,""pt"",""en"")"),"Beat the sugar with the eggs and add the remaining ingredients. In a pan, heat the oil and fry spoonfuls over low heat. After frying, coat the fritters in cinnamon sugar.") -> Beat the sugar with the eggs and add the remaining ingredients. In a pan, heat the oil and fry spoonfuls over low heat. After frying, coat the fritters in cinnamon sugar. | E95: https://www.tudogostoso.com.br/receita/538-bolinhos-de-chuva.html
A96: 94 | B96: =IFERROR(__xludf.DUMMYFUNCTION("GOOGLETRANSLATE(Portuguese!B96,""pt"",""en"")"),"Breaded steak") -> Breaded steak | C96: =IFERROR(__xludf.DUMMYFUNCTION("GOOGLETRANSLATE(Portuguese!C96,""pt"",""en"")"),"1/2 kg of beef (round steak, sirloin, or tenderloin) 3 beaten eggs Breadcrumbs to taste Wheat flour to taste 3 cloves of crushed garlic (optional) Salt to taste Black pepper to taste") -> 1/2 kg of beef (round steak, sirloin, or tenderloin) 3 beaten eggs Breadcrumbs to taste Wheat flour to taste 3 cloves of crushed garlic (optional) Salt to taste Black pepper to taste | D96: =IFERROR(__xludf.DUMMYFUNCTION("GOOGLETRANSLATE(Portuguese!D96,""pt"",""en"")"),"Season the steaks to taste and set aside. In a shallow dish, beat the eggs until smooth. Separate the breadcrumbs and wheat flour into different dishes. Dress the steaks in wheat flour, then in the beaten eggs, and finally in the breadcrumbs. In a frying "&"pan, fry the steaks in hot oil until golden brown. When removing from the pan, place the steaks on paper towels to absorb excess oil.") -> Season the steaks to taste and set aside. In a shallow dish, beat the eggs until smooth. Separate the breadcrumbs and wheat flour into different dishes. Dress the steaks in wheat flour, then in the beaten eggs, and finally in the breadcrumbs. In a frying pan, fry the steaks in hot oil until golden brown. When removing from the pan, place the steaks on paper towels to absorb excess oil. | E96: https://www.tudogostoso.com.br/receita/55-bife-a-milanesa.html
A97: 95 | B97: =IFERROR(__xludf.DUMMYFUNCTION("GOOGLETRANSLATE(Portuguese!B97,""pt"",""en"")"),"Super easy brownie") -> Super easy brownie | C97: =IFERROR(__xludf.DUMMYFUNCTION("GOOGLETRANSLATE(Portuguese!C97,""pt"",""en"")"),"6 heaping tablespoons of unsalted margarine 3/4 cup chocolate powder 1/2 cup cocoa powder 1 1/4 cups all-purpose flour 2 cups sugar 4 eggs 2 pinches of salt 1 teaspoon vanilla extract or essence 1 bar of semi-sweet chocolate, chopped into small cubes 1"&"/2 cup chopped walnuts or granulated cashews") -> 6 heaping tablespoons of unsalted margarine 3/4 cup chocolate powder 1/2 cup cocoa powder 1 1/4 cups all-purpose flour 2 cups sugar 4 eggs 2 pinches of salt 1 teaspoon vanilla extract or essence 1 bar of semi-sweet chocolate, chopped into small cubes 1/2 cup chopped walnuts or granulated cashews | D97: =IFERROR(__xludf.DUMMYFUNCTION("GOOGLETRANSLATE(Portuguese!D97,""pt"",""en"")"),"Mix the eggs and sugar. Then, add all the other ingredients until a smooth batter forms. Pour into a baking pan lined with parchment paper and bake in a moderate oven for 40 minutes. The brownie will be ready when the top is lightly browned and, when a to"&"othpick inserted comes out slightly moist (due to the melted chocolate). Cut into squares while still warm and serve with a scoop of vanilla ice cream, or freeze in a freezer bag. To defrost, place the brownie on a dessert plate and microwave on high for "&"1 minute.") -> Mix the eggs and sugar. Then, add all the other ingredients until a smooth batter forms. Pour into a baking pan lined with parchment paper and bake in a moderate oven for 40 minutes. The brownie will be ready when the top is lightly browned and, when a toothpick inserted comes out slightly moist (due to the melted chocolate). Cut into squares while still warm and serve with a scoop of vanilla ice cream, or freeze in a freezer bag. To defrost, place the brownie on a dessert plate and microwave on high for 1 minute. | E97: https://www.tudogostoso.com.br/receita/11659-brownie-super-facil.html
A98: 96 | B98: =IFERROR(__xludf.DUMMYFUNCTION("GOOGLETRANSLATE(Portuguese!B98,""pt"",""en"")"),"Potato gnocchi") -> Potato gnocchi | C98: =IFERROR(__xludf.DUMMYFUNCTION("GOOGLETRANSLATE(Portuguese!C98,""pt"",""en"")"),"6 medium potatoes 1 cup of wheat flour Salt to taste 1 can of tomato sauce 1/2 onion 1 tablespoon of olive oil 2 beef bouillon cubes 1/2 kg of ground beef 1 package of grated cheese") -> 6 medium potatoes 1 cup of wheat flour Salt to taste 1 can of tomato sauce 1/2 onion 1 tablespoon of olive oil 2 beef bouillon cubes 1/2 kg of ground beef 1 package of grated cheese | D98: =IFERROR(__xludf.DUMMYFUNCTION("GOOGLETRANSLATE(Portuguese!D98,""pt"",""en"")"),"Cook the potatoes in water until tender. Peel them and mash them while still hot. Gradually add the flour and salt, kneading well. Place the dough on a floured surface and roll it into logs. Cut each log into pieces of approximately 2 cm. Bring to a boil "&"in a pot with plenty of salted water. When the water boils, add the gnocchi until they begin to float. Place cold water in a bowl with a colander inside, remove the cooked gnocchi and place them in the colander to give them a thermal shock. Repeat the pro"&"cess until all the dough is cooked. Drain well and place the gnocchi in a baking dish, set aside. Finely chop the onion and sauté it in olive oil in a pan. Add the meat and the beef bouillon cubes. Stir well, and when the meat is cooked, add the sauce an"&"d let it cook for another 4 minutes. Pour it over the gnocchi, sprinkle cheese on top, and bake until golden brown. Serve hot and enjoy!") -> Cook the potatoes in water until tender. Peel them and mash them while still hot. Gradually add the flour and salt, kneading well. Place the dough on a floured surface and roll it into logs. Cut each log into pieces of approximately 2 cm. Bring to a boil in a pot with plenty of salted water. When the water boils, add the gnocchi until they begin to float. Place cold water in a bowl with a colander inside, remove the cooked gnocchi and place them in the colander to give them a thermal shock. Repeat the process until all the dough is cooked. Drain well and place the gnocchi in a baking dish, set aside. Finely chop the onion and sauté it in olive oil in a pan. Add the meat and the beef bouillon cubes. Stir well, and when the meat is cooked, add the sauce and let it cook for another 4 minutes. Pour it over the gnocchi, sprinkle cheese on top, and bake until golden brown. Serve hot and enjoy! | E98: https://www.tudogostoso.com.br/receita/1348-nhoque-de-batata.html
A99: 97 | B99: =IFERROR(__xludf.DUMMYFUNCTION("GOOGLETRANSLATE(Portuguese!B99,""pt"",""en"")"),"Simple chicken gratin") -> Simple chicken gratin | C99: =IFERROR(__xludf.DUMMYFUNCTION("GOOGLETRANSLATE(Portuguese!C99,""pt"",""en"")"),"1 kg shredded chicken breast 1 can of tomato sauce 2 chicken bouillon cubes 1 cup of water 1 tablespoon of wheat flour 1 can of cream Grated cheese to taste 100 g melted butter") -> 1 kg shredded chicken breast 1 can of tomato sauce 2 chicken bouillon cubes 1 cup of water 1 tablespoon of wheat flour 1 can of cream Grated cheese to taste 100 g melted butter | D99: =IFERROR(__xludf.DUMMYFUNCTION("GOOGLETRANSLATE(Portuguese!D99,""pt"",""en"")"),"Place the water in a saucepan and dissolve the chicken bouillon cubes. Add the tomato sauce and chicken, stir until it begins to boil. Add the flour and stir until thickened. Add the cream, mix well. Pour everything into a baking dish and spread the butte"&"r and grated cheese on top. Bake in the oven to gratin for about 20 minutes.") -> Place the water in a saucepan and dissolve the chicken bouillon cubes. Add the tomato sauce and chicken, stir until it begins to boil. Add the flour and stir until thickened. Add the cream, mix well. Pour everything into a baking dish and spread the butter and grated cheese on top. Bake in the oven to gratin for about 20 minutes. | E99: https://www.tudogostoso.com.br/receita/116-gratinado-de-frango.html
A100: 98 | B100: =IFERROR(__xludf.DUMMYFUNCTION("GOOGLETRANSLATE(Portuguese!B100,""pt"",""en"")"),"Knee") -> Knee | C100: =IFERROR(__xludf.DUMMYFUNCTION("GOOGLETRANSLATE(Portuguese!C100,""pt"",""en"")"),"1 cup of warm milk 30g of bread yeast 1 level tablespoon of sugar 1 teaspoon of salt 1/2 cup of oil 1/2 kg of wheat flour (more or less) Cheese Ham") -> 1 cup of warm milk 30g of bread yeast 1 level tablespoon of sugar 1 teaspoon of salt 1/2 cup of oil 1/2 kg of wheat flour (more or less) Cheese Ham | D100: =IFERROR(__xludf.DUMMYFUNCTION("GOOGLETRANSLATE(Portuguese!D100,""pt"",""en"")"),"Dissolve the yeast with the sugar. Add the oil, milk, and all the other ingredients. Let it rest for 15 minutes. Make small balls. Then, flatten the dough and fill it with a slice of cheese and another of ham. Roll it up like a Swiss roll and brush with "&"egg yolk. Bake until golden brown.") -> Dissolve the yeast with the sugar. Add the oil, milk, and all the other ingredients. Let it rest for 15 minutes. Make small balls. Then, flatten the dough and fill it with a slice of cheese and another of ham. Roll it up like a Swiss roll and brush with egg yolk. Bake until golden brown. | E100: https://www.tudogostoso.com.br/receita/7201-joelho.html
...

Sheet Ingredient analysis
A1: Top 50 | E1: Top 100 | K1: Total unique ingredients
B2: Ingredient | C2: Quantity | F2: Ingredient | G2: Quantity | J2: Top 50 | K2: 58
C3: 41 | F3: milk | G3: 65 | J3: Top 100 | K3: 79
B4: sugar | C4: 37 | F4: sugar | G4: 62
B5: egg | C5: 36 | F5: egg | G5: 62
B6: wheat flour | C6: 35 | F6: wheat flour | G6: 58
B7: yeast | C7: 27 | F7: oil | G7: 43
B8: oil | C8: 26 | F8: yeast | G8: 40
B9: chocolate | C9: 21 | F9: salt | G9: 40
B10: salt | C10: 20 | F10: chocolate | G10: 34
B11: milk cream | C11: 16 | F11: Margarine | G11: 31
B12: Margarine | C12: 16 | F12: cheese | G12: 28
B13: cheese | C13: 15 | F13: milk cream | G13: 27
B14: condensed milk | C14: 14 | F14: condensed milk | G14: 25
B15: onion | C15: 11 | F15: onion | G15: 20
... B60: breadcrumbs | C60: 1 | F60: palm heart | G60: 1
F61: vegetable broth | G61: 1
F62: corn flakes | G62: 1
F63: pinga | G63: 1
B64: Total | C64: 58 | F64: breadcrumbs | G64: 1
F65: kale | G65: 1
F66: pork | G66: 1
F67: apple | G67: 1
F68: Guava paste | G68: 1
F69: anise | G69: 1
F70: peanut | G70: 1
F71: brown sugar | G71: 1
F72: shrimp | G72: 1
F73: cassava | G73: 1
F74: bay leaf | G74: 1
F75: palm oil | G75: 1
F76: tuna | G76: 1
... F86: Total | G86: 79

Sheet recipes percentage
A1: Everyday black beans | F1: Black bean pick-me-up | G1: 450g | H1: =450/C11 -> 0.30363041 | K1: Bean pureé | L1: 500g | M1: =500/C11 -> 0.33736712
D2: porcentage
A3: Black beans | B3: 350g | C3: 350 | D3: =C3/$C$11 -> 0.23615698 | F3: 106g | G3: =$H$1*C3 -> 106.27064 | H3: =G3/450 -> 0.23615698 | K3: 118g | L3: =$M$1*C3 -> 118.07849
A4: Water | B4: 1 litre | C4: 1000 | D4: =C4/$C$11 -> 0.67473424 | F4: 304ml | G4: =$H$1*C4 -> 303.63041 | H4: =G4/450 -> 0.67473424 | K4: 337ml | L4: =$M$1*C4 -> 337.36712
A5: vegetable oil | B5: 45ml | C5: =45*0.927 -> 41.715 | D5: =C5/$C$11 -> 0.028146539 | F5: 13ml | G5: =$H$1*C5 -> 12.665942 | H5: =G5/450 -> 0.028146539 | K5: 14ml | L5: =$M$1*C5 -> 14.073269
A6: onion | B6: 1 | C6: =1*70 -> 70 | D6: =C6/$C$11 -> 0.047231397 | F6: 0.3 | G6: =$H$1*C6 -> 21.254129 | H6: =G6/450 -> 0.047231397 | K6: 0.3 | L6: =$M$1*C6 -> 23.615698
A7: clove garlic | B7: 3 | C7: =4.4*3 -> 13.2 | D7: =C7/$C$11 -> 0.008906492 | F7: 1 | G7: =$H$1*C7 -> 4.0079214 | H7: =G7/450 -> 0.008906492 | K7: 1 | L7: =$M$1*C7 -> 4.453246
A8: bay leaf | B8: 1 | C8: =0.25*1 -> 0.25 | D8: =C8/$C$11 -> 0.00016868356 | F8: 46025 | G8: =$H$1*C8 -> 0.075907602 | H8: =G8/450 -> 0.00016868356 | K8: 46025 | L8: =$M$1*C8 -> 0.08434178
A9: salt | B9: 5ml | C9: =1.38*5 -> 6.9 | D9: =C9/$C$11 -> 0.0046556662 | F9: 1.7ml | G9: =$H$1*C9 -> 2.0950498 | H9: =G9/450 -> 0.0046556662 | K9: 1.7ml | L9: =$M$1*C9 -> 2.3278331
B11: Total | C11: =SUM(C3:C9) -> 1482.065
F14: Salted cod rice | G14: 1Kg | H14: =1000/C23 -> 0.95675011 | K14: Octopus and brocoli rice | L14: 350g | M14: =350/C23 -> 0.33486254
D15: porcentage
A16: white rice | B16: 350g | C16: 350 | D16: =C16/$C$23 -> 0.33486254 | F16: 335g | G16: =$H$14*C16 -> 334.86254 | H16: =G16/1000 -> 0.33486254 | K16: 117g | L16: =C16*$M$14 -> 117.20189
A17: vegetable oil | B17: 15ml | C17: =15*0.927 -> 13.905 | D17: =C17/$C$23 -> 0.01330361 | F17: =G17/0.927 -> 14.351252 | G17: =$H$14*C17 -> 13.30361 | H17: =G17/1000 -> 0.01330361 | K17: 5ml | L17: =C17*$M$14 -> 4.6562636
A18: onion | B18: 1 | C18: 70 | D18: =C18/$C$23 -> 0.066972508 | F18: 1 | G18: =$H$14*C18 -> 66.972508 | H18: =G18/1000 -> 0.066972508 | K18: 46025 | L18: =C18*$M$14 -> 23.440378
A19: clove garlic | B19: 1 | C19: 4.4 | D19: =C19/$C$23 -> 0.0042097005 | F19: 1 | G19: =$H$14*C19 -> 4.2097005 | H19: =G19/1000 -> 0.0042097005 | K19: 46025 | L19: =C19*$M$14 -> 1.4733952
A20: water | B20: 600ml | C20: 600 | D20: =C20/$C$23 -> 0.57405007 | F20: 574ml | G20: =$H$14*C20 -> 574.05007 | H20: =G20/1000 -> 0.57405007 | K20: 200ml | L20: =C20*$M$14 -> 200.91752
A21: salt | B21: 5ml | C21: =1.38*5 -> 6.9 | D21: =C21/$C$23 -> 0.0066015758 | F21: =G21/1.38 -> 4.7837506 | G21: =$H$14*C21 -> 6.6015758 | H21: =G21/1000 -> 0.0066015758 | K21: 1.68ml | L21: =C21*$M$14 -> 2.3105515
B23: Total | C23: =SUM(C16:C21) -> 1045.205
D25: FC
A26: Cold mashed potatoes | C26: 400g | D26: 0.779
B27: necessário | C27: =400/D26 -> 513.47882

Sheet TFCB
A1: TFCB | L1: mudar glove garlic para clove garlic | N1: verificar o açucar
L2: verificar egg wash e mudar | N2: verificar se não tem nenhuma clara que eu deixei como egg
A3: Type A | B3: Type B | C3: Type C | D3: Original class | E3: Title (Eng) | F3: Title(Pt) | G3: Ingredients | H3: units | I3: Servings | J3: Servings Avg | L3: verificar farinha (se esta tudo plain flour) | N3: colocar média servings
A4: Meat | B4: Sea food | C4: Side | D4: Sreet food and snacks | E4: Salt cod fritters | F4: Bolinho de bacalhau | G4: salt cod cold mashed potatoes freash parsley eggs olive oil dry breadcrumbs ground black pepper vegetable oil | H4: 450g 400g 15ml 3 15ml 115g not specified not specified | I4: 25 | J4: 25
A5: Meat | B5: Beef | C5: Side | D5: Sreet food and snacks | E5: Lebanese meat fritters | F5: Kibe | G5: bulgur wheat minced lamb onion fresh mint white pepper nutmeg ground cinnamon salt vegetable oil vegetable oil onion minced beef pine nuts parsley spring onions | H5: 250g 1kg 1 115g 2.5-5ml 5ml 5ml 5ml not specified 30 ml 1/2 400g 50g 30 ml 30 ml | I5: 12 | J5: 12
A6: Meat | B6: Beef | C6: Side | D6: Sreet food and snacks | E6: Beef jerky and casava pureé cottage pie | F6: Escondidinho de carne seca | G6: cassava root butter heavy cream vegetable oil onion beef jerky garlic clove tomato fresh parsley cream cheese cheddar or Gouda cheese salt black pepper | H6: 500g 15 ml 200 ml 30 ml 1/2 350g 2 1 15g 225g 115g not specified not specified | I6: 6 | J6: 6
A7: Meat | B7: Beef | C7: Side | D7: Sreet food and snacks | E7: Pastel pastries with meat filing | F7: Pastel de feira de carne | G7: plain flour salt lard or white cooking fat cachaça or vodka white vinegar warm water onion minced beef clove garlic green olives parsley spring onions black pepper | H7: 260g 5ml 30ml 5ml 15ml 120ml 1/4 400g 2 40g 15ml 15ml not specified | I7: 6 | J7: 6
A8: No meat | B8: Vegetarian | C8: Side | D8: Sreet food and snacks | E8: deep-fried pastry with cheese filling | F8: Pastel de feira de queijo | G8: Plain flour salt lard or white cooking fat cachaça or vodka white vinegar warm water mozzarella | H8: 260g 5ml 30ml 5ml 15ml 120ml 200g | I8: 6 | J8: 6
A9: No meat | B9: Vegan | C9: Side | D9: Sreet food and snacks | E9: Tapioca pancakes | F9: Tapioca | G9: cassava starch water | H9: 450g 285 ml | I9: 6 | J9: 6
A10: Meat | B10: Sea food | C10: Side | D10: Sreet food and snacks | E10: Black-eyed bean fritters with prawn sauce | F10: Acarajé | G10: black-eyed beans onion salt black pepper palm oil vegetable oil olive oil onion clove garlic dried shrimp green chillies tomato shrimp cilantro salt black pepper | H10: 300g 1/4 not specified not specified not specifed not specified 30 ml 1/2 2 150g 2 400g 200g 25g not specified not specified | I10: 20 | J10: 20
A11: Meat | B11: Pork | C11: Side | D11: Sreet food and snacks | E11: Black bean pick-me-up | F11: Caldinho de feijão | G11: vegetable oil bacon or prok scratchings everyday black beans water salt black pepper olive oil parsley | H11: 15ml 225g 450g 250ml not specified not specified not specified 30ml | I11: 6 | J11: 6
A12: Meat | B12: Pork | C12: Side | D12: Sreet food and snacks | E12: Green broth | F12: Caldo verde | G12: olive oil onion clove garlic chorizo potatoes water spring greens salt black pepper | H12: 60ml 1 2 200g 675g 2litres 350g not specified not specified | I12: 6 | J12: 6
A13: No meat | B13: Vegan | C13: Side | D13: Sreet food and snacks | E13: Deep-fried chunky cassava chips | F13: Aipin frito | G13: cassava root onion whole clove salt vegetable oil | H13: 675g 1 24 30ml not specified | I13: 6 | J13: 6
A14: No meat | B14: Vegetarian | C14: Side | D14: Sreet food and snacks | E14: Coconut and tapioca cake | F14: Cuscuz de tapioca com coco | G14: tapioca salt water milk coconut milk sugar grated coconut | H14: 250g 2.5ml 400ml 120ml 100ml 175g 200g | I14: 8 | J14: 8
A15: No meat | B15: Vegetarian | C15: Dessert | D15: Sreet food and snacks | E15: Açaí in a bowl | F15: Açaí na tijela | G15: açai pulp guaraná syrup or honey water ice | H15: 250ml 100ml 120ml 250ml | I15: 1 | J15: 1
... A66: No meat | B66: Vegetarian | C66: Dessert | D66: Desserts and Baking | E66: Peanut brittle | F66: Pé de moleque | G66: golden syrup sugar peanuts baking soda butter | H66: 250ml 450g 350g 10ml 15ml | I66: 30 | J66: 30
A67: No meat | B67: Vegetarian | C67: Dessert | D67: Desserts and Baking | E67: Chocolate truffles | F67: Brigadeiro | G67: condensed milk butter chocolate powder chocolate sprinkles | H67: 400g 15ml 45ml 100g | I67: 25-30 | J67: 27.5
A68: No meat | B68: Vegetarian | C68: Dessert | D68: Desserts and Baking | E68: Coconut drops | F68: Beijinho de coco | G68: sugar milk butter grated coconut orange orange rind lime rind yolk vanilla extract sugar clove | H68: 225g 120ml 7g 175g 120ml 5ml 2.5ml 1 2.5ml not specified not specified | I68: 60 | J68: 60
A70: Meat | B70: Pork | C70: Main | D70: =COUNTIFS(A4:A68,"Meat",B4:B68,"Pork",C4:C68,"Main") -> 2
A71: =COUNTIF(A4:A68,"Meat") -> 25 | B71: =COUNTIFS(A4:A68,"Meat",B4:B68,"Pork") -> 4 | C71: Side | D71: =COUNTIFS(A4:A68,"Meat",B4:B68,"Pork",C4:C68,"Side") -> 2
C72: Dessert | D72: =COUNTIFS(A4:A68,"Meat",B4:B68,"Pork",C4:C68,"Dessert") -> 0
B73: Beef | C73: Main | D73: =COUNTIFS(A4:A68,"Meat",B4:B68,"Beef",C4:C68,"Main") -> 6
B74: =COUNTIFS(A4:A68,"Meat",B4:B68,"Beef") -> 9 | C74: Side | D74: =COUNTIFS(A4:A68,"Meat",B4:B68,"Beef",C4:C68,"Side") -> 3
C75: Dessert | D75: =COUNTIFS(A4:A68,"Meat",B4:B68,"Beef",C4:C68,"Dessert") -> 0
B76: Poultry | C76: Main | D76: =COUNTIFS(A4:A68,"Meat",B4:B68,"Poultry",C4:C68,"Main") -> 2
B77: =COUNTIFS(A4:A68,"Meat",B4:B68,"Poultry") -> 3 | C77: Side | D77: =COUNTIFS(A4:A68,"Meat",B4:B68,"Poultry",C4:C68,"Side") -> 1
C78: Dessert | D78: =COUNTIFS(A4:A68,"Meat",B4:B68,"Poultry",C4:C68,"Dessert") -> 0
B79: Sea food | C79: Main | D79: =COUNTIFS(A4:A68,"Meat",B4:B68,"Sea food ",C4:C68,"Main") -> 5
B80: =COUNTIFS(A4:A68,"Meat",B4:B68,"Sea food ") -> 9 | C80: Side | D80: =COUNTIFS(A4:A68,"Meat",B4:B68,"Sea food ",C4:C68,"Side") -> 4
C81: Dessert | D81: =COUNTIFS(A4:A68,"Meat",B4:B68,"Sea food ",C4:C68,"Dessert") -> 0
A82: No Meat | B82: Vegan | C82: Main | D82: =COUNTIFS(A4:A68,"No meat",B4:B68,"Vegan",C4:C68,"Main") -> 0
A83: =COUNTIF(A4:A68,"No meat") -> 40 | B83: =COUNTIFS(A4:A68,"No meat",B4:B68,"Vegan") -> 14 | C83: Side | D83: =COUNTIFS(A4:A68,"No meat",B4:B68,"Vegan",C4:C68,"Side") -> 14
C84: Dessert | D84: =COUNTIFS(A4:A68,"No meat",B4:B68,"Vegan",C4:C68,"Dessert") -> 0
B85: Vegetarian | C85: Main | D85: =COUNTIFS(A4:A68,"No meat",B4:B68,"Vegetarian",C4:C68,"Main)") -> 0
B86: =COUNTIFS(A4:A68,"No meat",B4:B68,"Vegetarian") -> 26 | C86: Side | D86: =COUNTIFS(A4:A68,"No meat",B4:B68,"Vegetarian",C4:C68,"Side") -> 9
C87: Dessert | D87: =COUNTIFS(A4:A68,"No meat",B4:B68,"Vegetarian",C4:C68,"Dessert") -> 17
A93: Type | B93: Main | C93: Side | D93: Dessert
A94: Pork | B94: 2 | C94: 2 | D94: 0
A95: Beef | B95: 7 | C95: 3 | D95: 0
A96: Poultry | B96: 2 | C96: 1 | D96: 0
A97: Seafood | B97: 5 | C97: 4 | D97: 0
A98: Vegan | B98: 0 | C98: 14 | D98: 0
A99: Vegetarian | B99: 0 | C99: 9 | D99: 17
A104: Label | B104: Parent | C104: Value
A105: Recipes | C105: 0
A106: Meat | B106: Recipes | C106: 0
A107: Pork | B107: Meat | C107: 0
A108: Pork Main | B108: Pork | C108: 2
A109: Pork Side | B109: Pork | C109: 2
A110: Pork Dessert | B110: Pork | C110: 0
A111: Beef | B111: Meat | C111: 0
A112: Beef Main | B112: Beef | C112: 6
A113: Beef Side | B113: Beef | C113: 3
A114: Beef Dessert | B114: Beef | C114: 0
A115: Poultry | B115: Meat | C115: 0
A116: Poultry Main | B116: Poultry | C116: 2
A117: Poultry Side | B117: Poultry | C117: 1
... A131: Vegetarian Dessert | B131: Vegetarian | C131: 17

Sheet ABHC
A1: ABHC | T1: mudar glove garlic para clove garlic | V1: verificar o açucar
T2: verificar egg wash e mudar | V2: verificar se não tem nenhuma clara que eu deixei como egg
A3: Type A | B3: Type B | C3: Type C | D3: Original Class | E3: Title (Eng) | F3: Title(Pt) | G3: Ingredients | H3: units | I3: Servings | J3: Servings Avg | T3: verificar farinha (se esta tudo plain flour)
A4: Meat | B4: Beef | C4: Main | D4: Meats | E4: Beef stroganoff | F4: Estrogonoffe de carne | G4: steak salt black pepper paprika plain flour olive oil butter onion cognac dijon mustard ketchup worcesterchire sauce tomato mushroom heavy cream | H4: 907g not specified not specified 7g 8g 28g 28g 2 60ml 15ml 30ml 30ml 397g 170g 240ml | I4: 6 | J4: 6
A5: Meat | B5: Beef | C5: Main | D5: Meats | E5: Brazilian Cottage pie | F5: Escondidinho de carne seca | G5: olive oil onion clove garlic beef jerky tomato salt black pepper parsley yuca heaby cream parmesan cheese mozzarella | H5: 30ml 1 4 907g 2 not specified not specified 21g 1.5Kg 240ml 100g 112g | I5: 46181 | J5: 7
A6: Meat | B6: Beef | C6: Main | D6: Meats | E6: Braised beef with onions, tomato and peppers | F6: Carne louca | G6: chuck roast salt black pepper vegetable oil onion clove garlic red wine tomato paste brown sugar can tomato worcetershire sauce beef stock bay leaf red pepper balsamic vinegar parsley onion | H6: 1.1Kg not specified not specified 15ml 2 4 120ml 16g 14g 397g 30ml 240ml 1 2 10ml 21g 2 | I6: 6 | J6: 6
A7: Meat | B7: Beef | C7: Main | D7: Meats | E7: Filet Parmigiana | F7: Filé à parmigiana | G7: tomato butter onion salt black pepper steak salt black pepper plain flour egg breadcrumbs vegetable oil clove garlic mozzarella parmesan cheese | H7: 794g 57g 1 not specified not specified 454g not specified not specified 125g 2 216g not specified 1 226g 100g | I7: 46057 | J7: 3
A8: Meat | B8: Beef | C8: Main | D8: Meats | E8: Instant pto cumin beef stew | F8: Barreado na panela de pressão | G8: chuck roast salt black pepper cumin red wine vinegar onion tomato clove garlic parsley green onion vegetable oil bacon bay leaf water | H8: 1.5Kg not specified not specified 2-4g 30ml 2 4 1 30g 3 1tsp 226g 3 960ml | I8: 46244 | J8: 9
A9: Meat | B9: Beef | C9: Main | D9: Meats | E9: Oven-roasted picanha with garlic butter | F9: Picanha ao forno com manteiga de alho | G9: clove garlic olive oil salt black pepper butter picanha potato red onion thyme spring | H9: 8 80ml not specified not specified 57g 1.6Kg 8 3 | I9: 46181 | J9: 7
A10: Meat | B10: Beef | C10: Main | D10: Meats | E10: Picanha Burguer with green milk mayo | F10: Hambúrguer de picanha com maionese verde | G10: milk clove garlic green onion parsley dijon mostard worcetershire sauce lime salt black pepper vegetable oil picanha salt black pepper cheddar buguer buns | H10: 240ml 2 2 60g 15ml 15ml 1 not specified not specified 480ml 907g not specified not specified 6 6 | I10: 6 | J10: 6
A11: Meat | B11: Beef | C11: Main | D11: Meats | E11: Beef tips in beer sauce | F11: Picadinho na cerveja | G11: tenderloin salt black pepper paprika plain flour vegetable oil bacon onion clove garlic brown ale beef stock brown sugar dijon mostard worcetershire sauce parsley butter flour | H11: 680g not specified not specified 1/2 tsp 8g 30ml 57g 1 3 240ml 120ml 1tsp 15g 15g 4g 14g 8g | I11: 4 | J11: 4
A12: Meat | B12: Beef | C12: Main | D12: Meats | E12: Filet mignon with garlic | F12: Filé à Oswaldo aranha | G12: potato vegetable oil clove gatlic salt black pepper tenderloin | H12: 2 not specified 10 not specified not specified 170-225g | I12: 2 | J12: 2
A13: Meat | B13: Beef | C13: Main | D13: Meats | E13: Plantain Gnocchi | F13: Nhoque de banana da terra com carne seca | G13: ripe plantain salt cornstarch water flour ghee onion tomato clove garlic beef jerky parsley | H13: 4 not specififed 64g 120ml not specified 42g 1 2 3 454g 15g | I13: 4 | J13: 4
A14: Meat | B14: Poultry | C14: Main | D14: Meats | E14: Chicken with okra | F14: Frango com quiabo | G14: chicken lime salt black pepper sweet paprika okra butter vegetable oil onion tomato clove garlic tomato paste chicken broth parsley | H14: 907g 1 not specified not specified 5g 454g 28g 30ml 1 1 6 16g 450ml 15g | I14: 4 | J14: 4
A15: Meat | B15: Poultry | C15: Main | D15: Meats | E15: Chicken with yuca stew | F15: Bobó de frango | G15: chicken lime salt black pepper yuca root chicken broth olive oil onion red pepper tomato clove garlic red chile pepper tomato paste coconut milk heaby cream palm oil cilantro | H15: 907g 1 not specified not specified 454g 360ml 15ml 1 1 2 3 1 16g 403ml 120ml 15ml 8g | I15: 46181 | J15: 7
... A63: No meat | B63: Vegetarian | C63: Dessert | D63: Desserts and treats | E63: Layered banana dessert | F63: Chico balanceado | G63: yolk cornstarch condensed milk milk vanilla extract heavy cream granulated sugar water banana granulated sugar salt egg white | H63: 4 19g 396g 480ml 15ml 120ml 200g 120ml 7 200g 1/4tsp 4 | I63: 46244 | J63: 9
A66: Meat | B66: Pork | C66: Main | D66: =COUNTIFS(A4:A63,"Meat",B4:B63,"Pork",C4:C63,"Main") -> 6
A67: =COUNTIF(A4:A63,"Meat") -> 37 | B67: =COUNTIFS(A4:A63,"Meat",B4:B63,"Pork") -> 12 | C67: Side | D67: =COUNTIFS(A4:A63,"Meat",B4:B63,"Pork",C4:C63,"Side") -> 6
C68: Dessert | D68: =COUNTIFS(A4:A63,"Meat",B4:B63,"Pork",C4:C63,"Dessert") -> 0
B69: Beef | C69: Main | D69: =COUNTIFS(A4:A63,"Meat",B4:B63,"Beef",C4:C63,"Main") -> 12
B70: =COUNTIFS(A4:A63,"Meat",B4:B63,"Beef") -> 12 | C70: Side | D70: =COUNTIFS(A4:A63,"Meat",B4:B63,"Beef",C4:C63,"Side") -> 0
C71: Dessert | D71: =COUNTIFS(A4:A63,"Meat",B4:B63,"Beef",C4:C63,"Dessert") -> 0
B72: Poultry | C72: Main | D72: =COUNTIFS(A4:A63,"Meat",B4:B63,"Poultry",C4:C63,"Main") -> 5
B73: =COUNTIFS(A4:A63,"Meat",B4:B63,"Poultry") -> 6 | C73: Side | D73: =COUNTIFS(A4:A63,"Meat",B4:B63,"Poultry",C4:C63,"Side") -> 1
C74: Dessert | D74: =COUNTIFS(A4:A63,"Meat",B4:B63,"Poultry",C4:C63,"Dessert") -> 0
B75: Sea food | C75: Main | D75: =COUNTIFS(A4:A63,"Meat",B4:B63,"Sea food",C4:C63,"Main") -> 6
B76: =COUNTIFS(A4:A63,"Meat",B4:B63,"Sea food") -> 7 | C76: Side | D76: =COUNTIFS(A4:A63,"Meat",B4:B63,"Sea food",C4:C63,"Side") -> 1
C77: Dessert | D77: =COUNTIFS(A4:A63,"Meat",B4:B63,"Sea food",C4:C63,"Dessert") -> 0
A78: No Meat | B78: Vegan | C78: Main | D78: =COUNTIFS(A4:A63,"No meat",B4:B63,"Vegan",C4:C63,"Main") -> 1
A79: =COUNTIF(A4:A63,"No meat") -> 23 | B79: =COUNTIFS(A4:A63,"No meat",B4:B63,"Vegan") -> 4 | C79: Side | D79: =COUNTIFS(A4:A63,"No meat",B4:B63,"Vegan",C4:C63,"Side") -> 3
C80: Dessert | D80: =COUNTIFS(A4:A63,"No meat",B4:B63,"Vegan",C4:C63,"Dessert") -> 0 | M80: Meet
B81: Vegetarian | C81: Main | D81: =COUNTIFS(A4:A63,"No meat",B4:B63,"Vegetarian",C4:C63,"Main") -> 1 | M81: Vegetarian
B82: =COUNTIFS(A4:A63,"No meat",B4:B63,"Vegetarian") -> 19 | C82: Side | D82: =COUNTIFS(A4:A63,"No meat",B4:B63,"Vegetarian",C4:C63,"Side") -> 7 | M82: Desserts
C83: Dessert | D83: =COUNTIFS(A4:A63,"No meat",B4:B63,"Vegetarian",C4:C63,"Dessert") -> 11
A86: Meat | B86: Pork | C86: Main | D86: 6
A87: Meat | B87: Pork | C87: Side | D87: 6
A88: Meat | B88: Pork | C88: Dessert | D88: 0
A89: Meat | B89: Beef | C89: Main | D89: 12
A90: Meat | B90: Beef | C90: Side | D90: 0
A91: Meat | B91: Beef | C91: Dessert | D91: 0
A92: Meat | B92: Poultry | C92: Main | D92: 5
A93: Meat | B93: Poultry | C93: Side | D93: 1
A94: Meat | B94: Poultry | C94: Dessert | D94: 0
A95: Meat | B95: Sea food | C95: Main | D95: 6
A96: Meat | B96: Sea food | C96: Side | D96: 1
A97: Meat | B97: Sea food | C97: Dessert | D97: 0
... A103: No Meat | B103: Vegetarian | C103: Dessert | D103: 11
A107: Label | B107: Parent | C107: Value
A108: Recipes | C108: 0
A109: Meat | B109: Recipes | C109: 0
A110: Pork | B110: Meat | C110: 0
A111: Pork Main | B111: Pork | C111: 6
A112: Pork Side | B112: Pork | C112: 6
A113: Pork Dessert | B113: Pork | C113: 0
A114: =B89 -> Beef | B114: Meat | C114: 0
A115: =A114 & " "&C98 -> Beef Main | B115: Beef | C115: 12
A116: =B89 & " "&C99 -> Beef Side | B116: Beef | C116: 0
A117: =B90 & " "&C100 -> Beef Dessert | B117: Beef | C117: 0
A118: =B93 -> Poultry | B118: Meat | C118: 0
A119: =B92 & " "&C66 -> Poultry Main | B119: =A118 -> Poultry | C119: 5
A120: =B93 & " "&C67 -> Poultry Side | B120: Poultry | C120: 1
A121: =B94 & " "&C68 -> Poultry Dessert | B121: Poultry | C121: 0
A122: Sea food | B122: Meat | C122: 0
A123: =B96 & " "&C69 -> Sea food Main | B123: Sea food | C123: 6
A124: =B97 & " "&C70 -> Sea food Side | B124: Sea food | C124: 1
A125: =B97 & " "&C71 -> Sea food Dessert | B125: Sea food | C125: 0
A126: No Meat | B126: Recipes | C126: 0
A127: Vegan | B127: No Meat | C127: 0
A128: Vegan Main | B128: Vegan | C128: 1
A129: Vegan Side | B129: Vegan | C129: 3
A130: Vegan Dessert | B130: Vegan | C130: 0
A131: Vegetarian | B131: No Meat | C131: 0
A132: Vegetarian Main | B132: Vegetarian | C132: 1
A133: Vegetarian Side | B133: Vegetarian | C133: 7
A134: Vegetarian Dessert | B134: Vegetarian | C134: 11
A145: Type | B145: Main | C145: Side | D145: Dessert
A146: Pork | B146: 6 | C146: 6 | D146: 0
A147: Beef | B147: 12 | C147: 0 | D147: 0
A148: Poultry | B148: 5 | C148: 1 | D148: 0
A149: Seafood | B149: 6 | C149: 1 | D149: 0
A150: Vegan | B150: 1 | C150: 3 | D150: 0
A151: Vegetarian | B151: 1 | C151: 7 | D151: 11

Sheet Books combined
A1: Type A | B1: Type B | C1: Type C | D1: Title (Eng) | E1: Title(Pt) | F1: Ingredients | G1: units | H1: Total weight | I1: Servings | J1: Servings Avg | K1: BOOK | L1: CF ingredients | M1: CF cooking | N1: CF total | O1: CF per serving | P1: CF per 100 grams
A2: Meat | B2: Beef | C2: Main | D2: Oxtail stew with watercress | E2: Rabada com agrião | F2: onion clove garlic olive oil white wine oxtail vegetable oil tomato bay leaf water cornstarch watercress salt black pepper | G2: 1 4 45 ml 250 ml 1.5 Kg 30 ml 2 2 250ml 5 ml 2 not specified not specified | H2: 2426.54 | I2: 4 | J2: 4 | K2: TFCB | L2: 32680.86 | M2: 240.66069 | N2: =SUM(L2+M2) -> 32921.521 | O2: =N2/J2 -> 8230.3802 | P2: =100*L2/H2 -> 1346.809
A3: Meat | B3: Beef | C3: Main | D3: Fillet steak with crunchy garlic topping | E3: Filé Osvaldo Aranha | F3: vegetable oil fillet steak clove garlic butter salt black pepper | G3: 15 ml 400 g 3 75 g not specified not specified | H3: 502.105 | I3: 1 | J3: 1 | K3: TFCB | L3: 445.97963 | M3: 48.46208 | N3: =SUM(L3+M3) -> 494.44171 | O3: =N3/J3 -> 494.44171 | P3: =100*L3/H3 -> 88.821985
A4: Meat | B4: Beef | C4: Main | D4: Beef stew | E4: Picadinho à carioca | F4: fillet steak clove garlic vegetable oil bacon small onion beef broth white wine vinegar egg cornstarch parsley salt black pepper | G4: 400 g 2 30 ml 125 g 1 400 ml 30 ml 2 5 ml 15 ml not specified not specified | H4: 1099.1 | I4: 2 | J4: 2 | K4: TFCB | L4: 3297.7662 | M4: 110.83074 | N4: =SUM(L4+M4) -> 3408.597 | O4: =N4/J4 -> 1704.2985 | P4: =100*L4/H4 -> 300.04242
A5: Meat | B5: Beef | C5: Main | D5: Beef jerky and pumpkin | E5: Jabá com jerimum | F5: beef jerky pumpkin vegetable oil onion clove garlic parsley black pepper | G5: 500g 1kg 30ml 1 2 25g not specified | H5: 1631.61 | I5: 6 | J5: 6 | K5: TFCB | L5: 4325.1197 | M5: 466.67334 | N5: =SUM(L5+M5) -> 4791.793 | O5: =N5/J5 -> 798.63217 | P5: =100*L5/H5 -> 265.08293
A6: Meat | B6: Beef | C6: Main | D6: Beef jerky risotto | E6: arroz carreteiro | F6: beef jerky vegetable oil bacon onion clove garlic sausage white rice red chilli pepper parsley spring onions black pepper | G6: 500g 45ml 115g 1 3 65g 375g 1 30ml 2 not specified | H6: 1240.615 | I6: 46181 | J6: 7 | K6: TFCB | L6: 4419.7819 | M6: 472.75848 | N6: =SUM(L6+M6) -> 4892.5404 | O6: =N6/J6 -> 698.93434 | P6: =100*L6/H6 -> 356.25733
A7: Meat | B7: Beef | C7: Main | D7: Grilled rump steak | E7: Picanha fatiada | F7: picanha coarse sea salt | G7: 1.25Kg 30ml | H7: 1288.4 | I7: 4 | J7: 4 | K7: TFCB | L7: 25860.48 | M7: 0 | N7: =SUM(L7+M7) -> 25860.48 | O7: =N7/J7 -> 6465.1201 | P7: =100*L7/H7 -> 2007.1779
A8: Meat | B8: Beef | C8: Main | D8: Beef stroganoff | E8: Estrogonoffe de carne | F8: fillet steak salt black pepper sweet paprika plain flour olive oil butter onion cognac dijon mustard ketchup worceterchire sauce tomato mushroom heavy cream | G8: 907g not specified not specified 7g 8g 35ml 28g 2 60ml 15ml 30ml 30ml 397g 170g 240ml | H8: 2069.49 | I8: 6 | J8: 6 | K8: ABHC | L8: 2720.9722 | M8: 166.79988 | N8: =SUM(L8+M8) -> 2887.772 | O8: =N8/J8 -> 481.29534 | P8: =100*L8/H8 -> 131.48032
A9: Meat | B9: Beef | C9: Main | D9: Braised beef with onions, tomato and peppers | E9: Carne louca | F9: chuck roast salt black pepper vegetable oil onion clove garlic red wine tomato paste brown sugar tomato sauce worcetershire sauce beef broth bay leaf red bell pepper balsamic vinegar parsley onion | G9: 1.1Kg not specified not specified 15ml 2 4 120ml 16g 14g 397g 30ml 240ml 1 2 10ml 21g 2 | H9: 2370.855 | I9: 6 | J9: 6 | K9: ABHC | L9: 26297.36 | M9: 812.68908 | N9: =SUM(L9+M9) -> 27110.049 | O9: =N9/J9 -> 4518.3415 | P9: =100*L9/H9 -> 1109.1931
A10: Meat | B10: Beef | C10: Main | D10: Filet Parmigiana | E10: Filé à parmigiana | F10: tomato butter onion salt black pepper fillet steak salt black pepper plain flour egg breadcrumbs vegetable oil clove garlic mozzarella parmesan cheese | G10: 794g 57g 1 not specified not specified 454g not specified not specified 125g 2 216g not specified 1 226g 100g | H10: 2136.4 | I10: 46057 | J10: 3 | K10: ABHC | L10: 3258.8694 | M10: 208.61118 | N10: =SUM(L10+M10) -> 3467.4805 | O10: =N10/J10 -> 1155.8268 | P10: =100*L10/H10 -> 152.54022
A11: Meat | B11: Beef | C11: Main | D11: Instant pot cumin beef stew | E11: Barreado na panela de pressão | F11: chuck roast salt black pepper cumin red wine vinegar onion tomato clove garlic parsley spring onions vegetable oil bacon bay leaf water | G11: 1.5Kg not specified not specified 2-4g 30ml 2 4 1 30g 3 1tsp 226g 3 960ml | H11: 2611.685 | I11: 46244 | J11: 9 | K11: ABHC | L11: 21502.427 | M11: 609.392 | N11: =SUM(L11+M11) -> 22111.819 | O11: =N11/J11 -> 2456.8688 | P11: =100*L11/H11 -> 823.31624
A12: Meat | B12: Beef | C12: Main | D12: Oven-roasted picanha with garlic butter | E12: Picanha no forno com manteiga de alho | F12: clove garlic olive oil salt black pepper butter picanha potato red onion thyme sprig | G12: 8 80ml not specified not specified 57g 1.6Kg 8 3 4 | H12: 3857.4 | I12: 46181 | J12: 7 | K12: ABHC | L12: 33598.448 | M12: 294.77535 | N12: =SUM(L12+M12) -> 33893.223 | O12: =N12/J12 -> 4841.8891 | P12: =100*L12/H12 -> 871.01281
A13: Meat | B13: Beef | C13: Main | D13: Picanha Burguer with green milk mayo | E13: Hambúrguer de picanha com maionese verde | F13: milk clove garlic spring onions parsley dijon mustard worcetershire sauce lime salt black pepper vegetable oil picanha salt black pepper cheddar burguer buns | G13: 240ml 2 2 60g 15ml 15ml 1 not specified not specified 480ml 907g not specified not specified 6 6 | H13: 2299.56 | I13: 6 | J13: 6 | K13: ABHC | L13: 26145.561 | M13: 5.4908333 | N13: =SUM(L13+M13) -> 26151.051 | O13: =N13/J13 -> 4358.5086 | P13: =100*L13/H13 -> 1136.981
A14: Meat | B14: Beef | C14: Main | D14: Beef tips in beer sauce | E14: Picadinho na cerveja | F14: tenderloin salt black pepper smooked paprika plain flour vegetable oil bacon small onion clove garlic brown ale beef broth brown sugar dijon mustard worcetershire sauce parsley butter plain flour | G14: 680g not specified not specified 1/2 tsp 8g 30ml 57g 1 3 240ml 120ml 1tsp 15g 15g 4g 14g 8g | H14: 834.76 | I14: 4 | J14: 4 | K14: ABHC | L14: 2164.8166 | M14: 149.98169 | N14: 2314.7983 | O14: 578.69957 | P14: 259.33401
A15: Meat | B15: Beef | C15: Main | D15: Plantain Gnocchi | E15: Nhoque de banana da terra com carne seca | F15: banana salt cornstarch water plain flour butter onion tomato clove garlic beef jerky parsley | G15: 4 not specififed 64g 120ml not specified 42g 1 2 3 454g 15g | H15: 1218.2 | I15: 4 | J15: 4 | K15: ABHC | L15: 993.74863 | M15: 219.59521 | N15: =SUM(L15+M15) -> 1213.3438 | O15: =N15/J15 -> 303.33596 | P15: =100*L15/H15 -> 81.575162
A16: Meat | B16: Beef | C16: Main | D16: Brasília rice with black-eyed peas, beef and cheese | E16: Baião de dois | F16: white rice butter onion clove garlic salt turmeric hot water bay leaf butter bacon red onion clove garlic beef jerky black-eyed peas salt black pepper beef broth queijo coalho parsley | G16: 200g 14g 1 4 1tsp 1/4tsp 420ml 1 42g 113g 1 4 85g 397g not specified not specified 120ml 142g 21g | H16: 1722.36 | I16: 46118 | J16: 5 | K16: ABHC | L16: 3904.3161 | M16: 215.08498 | N16: =SUM(L16+M16) -> 4119.4011 | O16: =N16/J16 -> 823.88022 | P16: =100*L16/H16 -> 226.68409
